Workbook

Sheet Como_usar
B1: Herramienta Demand Planner — Watt's — Grupo Lacteos Y Jugos (datos al 22-10-2026)
B3: Hojas de este libro:
B4: • Excepciones — tu tablero diario. Una fila por SKU; solo mira las que tienen alerta. Columna "Qué revisar" te dice la acción.
B5: • Stock_Seguridad — cálculo de SS, punto de reorden y techo por vida útil para cada SKU.
B6: • ABC_XYZ — segmentación de cada SKU y cómo planificarlo. Incluye calidad del forecast (WMAPE y sesgo).
B7: • Cadenas_vs_FCST — qué cadena pidió más y cuál se desvió más del forecast (S38-S41).
B8: • Parametros — celdas amarillas editables: cortes, niveles de servicio, lead time, umbrales.
B9: • Datos_Semanales — pedidos y FCST por SKU (fuente). Para actualizar: pega las semanas nuevas aquí.
B10: Convención de colores: texto azul en celda amarilla = dato que tú editas. Texto negro = fórmula. Texto verde = viene de otra hoja.
B12: 1. ¿Qué es ABC/XYZ? — Ejemplo con fórmulas (cambia los números azules y mira cómo cambia)
B13: ABC mide CUÁNTO vende el SKU (importancia). XYZ mide QUÉ TAN ESTABLE es (predictibilidad). Se cruzan en 9 segmentos.
B15: SKU ejemplo | C15: Sem 1 | D15: Sem 2 | E15: Sem 3 | F15: Sem 4 | G15: Sem 5 | H15: Sem 6 | I15: Promedio | J15: Desv. est. | K15: CV | L15: XYZ
B16: Leche entera 1L (estable) | C16: 10000 | D16: 10400 | E16: 9800 | F16: 10200 | G16: 9900 | H16: 10100 | I16: =AVERAGE(C16:H16) -> 10066.667 | J16: =STDEV(C16:H16) -> 216.02469 | K16: =J16/I16 -> 0.021459406 | L16: =IF(K16<=Parametros!$B$6,"X",IF(K16<=Parametros!$B$7,"Y","Z")) -> X
B17: Yogurt con promo (variable) | C17: 1500 | D17: 5200 | E17: 1000 | F17: 4800 | G17: 900 | H17: 3500 | I17: =AVERAGE(C17:H17) -> 2816.6667 | J17: =STDEV(C17:H17) -> 1938.4702 | K17: =J17/I17 -> 0.68821427 | L17: =IF(K17<=Parametros!$B$6,"X",IF(K17<=Parametros!$B$7,"Y","Z")) -> Y
B18: Queso especial (errático) | C18: 200 | D18: 1500 | E18: 0 | F18: 900 | G18: 50 | H18: 1800 | I18: =AVERAGE(C18:H18) -> 741.66667 | J18: =STDEV(C18:H18) -> 780.01068 | K18: =J18/I18 -> 1.0516998 | L18: =IF(K18<=Parametros!$B$6,"X",IF(K18<=Parametros!$B$7,"Y","Z")) -> Z
B20: CV (coeficiente de variación) = desviación estándar ÷ promedio. CV 0,02 = la leche vende casi igual todas las semanas → X.
B21: CV ≤ 0,5 → X (estable, se planifica con estadística). 0,5–1,0 → Y (variable, hay que entender por qué). > 1,0 → Z (errático).
B22: ABC: ordenas los SKU de mayor a menor volumen y sumas. Los que llegan al 80% del total son A; hasta el 95% son B; el resto C.
B23: Ejemplo: si un SKU es A (mucho volumen) y Z (errático) = AZ → es donde un error te cuesta más: ahí va tu tiempo.
B24: Un AX (mucho volumen, estable) casi se planifica solo: no lo toques cada semana. Un CZ (poco y errático) no merece tu tiempo: stock mínimo.
B25: Tu lista real está en la hoja ABC_XYZ; la matriz de acciones por segmento está en Parametros.
B27: 2. Stock de seguridad — Ejemplo con fórmulas
B28: El SS cubre el ERROR del forecast durante el tiempo que tardas en reponer. Por eso usa σ del error (no de la venta).
B30: FCST semanal (kg) | D30: 10000
B31: σ del error del forecast (kg/sem) | D31: 2000
B32: Lead time (semanas) | D32: 2
B33: Nivel de servicio | D33: 0.98
B34: Z (=NORMSINV(nivel)) | D34: =NORMSINV(D33) -> 2.0537489
B35: SS = Z × σ × √LT (kg) | D35: =D34*D31*SQRT(D32) -> 5808.8791
B36: Punto de reorden = SS + FCST × LT (kg) | D36: =D35+D30*D32 -> 25808.879
B37: VU del producto (días) | D37: 50
B38: Tope avance cadena más exigente | D38: 0.35
B39: Semanas vendibles = VU × tope / 7 | D39: =D37*D38/7 -> 2.5
B40: Stock máx. vendible = FCST × semanas vendibles | D40: =D30*D39 -> 25000
B41: SS final = MIN(SS, máx. vendible − FCST × LT) | D41: =MAX(0,MIN(D35,D40-D30*D32)) -> 5000
B43: Lectura: con 98% de servicio necesitas ~5.800 kg de SS. Pero si el producto dura 50 días y la cadena más exigente acepta hasta 35% de avance,
B44: solo tienes 2,5 semanas para venderlo: máx. vendible 25.000 kg − 20.000 kg que vendes durante el lead time = SS topado en 5.000 kg. Producir más = merma.
B45: Z según nivel de servicio: 90% → 1,28 · 95% → 1,64 · 98% → 2,05 · 99% → 2,33. Subir de 95% a 99% casi aumenta el SS en 42%.
B46: Dato pendiente: el lead time real por categoría (hoy se usa 1 semana por defecto). Cárgalo en Parametros y todo se recalcula.
B48: 3. Gestión por excepción — rutina sugerida
B49: LUNES (30 min): actualizar archivos → hoja Excepciones → filtrar Prioridad 1-ALTA. Revisar ALERTA QUIEBRE y QUIEBRE ENCUBIERTO.
B50: LUNES: hoja Cadenas_vs_FCST → ¿qué cadena se desvió más? Llevar los SKU "SOBRE/BAJO FCST" a la reunión con KAM.
B51: Estados de stock: BAJO SS = stock + por liberar no alcanza el SS (crítico) · BAJO SS (XLIB CUBRE) = se salva solo si liberan a tiempo ·
B52: BAJO P.REORDEN = no es alerta, es la señal normal de programar producción · SOBRE MAX VENDIBLE = más stock del que se alcanza a vender dentro del filtro.
B53: MARTES-JUEVES (15 min/día): solo SKU AZ, AY y BZ + nuevas alertas. Ignorar los AX y CX salvo que tengan alerta.
B54: VIERNES (20 min): ALERTA MERMA/VU → lotes a ≤6 pts del filtro: priorizar despacho (FEFO) o venta intermedia antes de que se pierdan.
B55: MENSUAL: revisar WMAPE y sesgo en ABC_XYZ. Si un SKU tiene sesgo persistente > ±10%, corregir el forecast base, no parchar semana a semana.
... B58: MERMA/VU (sobrestock vs vida útil o lotes fuera/cerca del filtro) · DESVIACIÓN (pedidos ±20% vs FCST en 4 semanas).

Sheet Parametros
A1: Parámetros — edita solo las celdas amarillas (texto azul)
A3: Parámetro | B3: Valor | C3: Nota / fuente
A4: Corte ABC: A hasta % acumulado | B4: 0.8 | C4: Pareto estándar: los SKU que suman el 80% del volumen son A.
A5: Corte ABC: B hasta % acumulado | B5: 0.95 | C5: Del 80% al 95% son B; el resto (5% del volumen) son C.
A6: Corte XYZ: X si CV ≤ | B6: 0.5 | C6: CV = desviación estándar / promedio semanal. Corte usual en demanda semanal por SKU.
A7: Corte XYZ: Y si CV ≤ | B7: 1 | C7: Sobre este valor el SKU es Z (errático).
A8: Nivel de servicio A | B8: 0.98 | C8: Supuesto inicial (benchmark internacional). Ajustar según política Watt's.
A9: Nivel de servicio B | B9: 0.95 | C9: Supuesto inicial.
A10: Nivel de servicio C | B10: 0.9 | C10: Supuesto inicial.
A11: Nivel de servicio SKU sin historial | B11: 0.95 | C11: Para SKU sin ventas en la base S36-S41.
A12: Lead time por defecto (semanas) | B12: 1 | C12: SUPUESTO: no se recibió lead time real. Reemplazar por categoría en la tabla de abajo.
A13: σ por defecto (% del FCST semanal) si no hay historial | B13: 0.3 | C13: SUPUESTO para SKU sin historial de pedidos.
A14: Umbral desviación pedido vs FCST (±) | B14: 0.2 | C14: Alerta si |Solicitado/FCST − 1| supera este valor.
A15: Volumen mínimo para alertar desviación SKU (kg, 4 sem) | B15: 2000 | C15: Evita alertas por SKU de volumen marginal.
... A18: Margen de alerta VU (puntos de avance antes del filtro) | B18: 0.06 | C18: Misma regla del dashboard: alerta si el lote está a ≤ 6 pts del tope de la cadena más exigente.
A21: Matriz ABC/XYZ — qué hacer con cada segmento
A22: Segmento | B22: Cómo planificarlo | C22: Frecuencia de revisión
A23: AX | B23: Forecast estadístico casi automático. Ajustes mínimos. SS bajo porque la demanda es estable. | C23: Mensual
A24: AY | B24: Alto volumen con variaciones: entender causas (promos, cadenas). Validar con KAM antes de ajustar. | C24: Semanal
A25: AZ | B25: FOCO MÁXIMO. Mucho volumen y errático: CPFR con cadenas, separar promociones de la base, SS alto. | C25: 2 veces por semana
A26: BX | B26: Estadístico + revisión de tendencia. | C26: Mensual
A27: BY | B27: Validar promociones y eventos con comercial. | C27: Quincenal
A28: BZ | B28: Investigar causa de la variabilidad; evaluar producir contra pedido confirmado. | C28: Semanal
A29: CX | B29: Reposición simple mín/máx. | C29: Trimestral
A30: CY | B30: Mín/máx con stock bajo; evaluar continuidad del SKU. | C30: Mensual
A31: CZ | B31: Contra pedido o stock mínimo. Candidato a racionalizar/descontinuar. | C31: Mensual
A34: Lead time de reposición por categoría (semanas) — reemplaza con el dato real
A35: Categoría | B35: Lead time (sem) | C35: Nota
A36: CREMA | B36: =Parametros!$B$12 -> 1 | C36: Usa el valor por defecto hasta que ingreses el real
A37: JUGOS Y NECTARES | B37: =Parametros!$B$12 -> 1 | C37: Usa el valor por defecto hasta que ingreses el real
A38: LECHE EVAPORADA | B38: =Parametros!$B$12 -> 1 | C38: Usa el valor por defecto hasta que ingreses el real
A39: LECHES EN POLVO | B39: =Parametros!$B$12 -> 1 | C39: Usa el valor por defecto hasta que ingreses el real
A40: LECHES LIQUIDAS | B40: =Parametros!$B$12 -> 1 | C40: Usa el valor por defecto hasta que ingreses el real
A41: MANJAR | B41: =Parametros!$B$12 -> 1 | C41: Usa el valor por defecto hasta que ingreses el real

Sheet Excepciones
A1: Tablero de excepciones — revisa solo lo que tiene alerta — Grupo Lacteos Y Jugos
A2: Ordena por Puntaje (mayor a menor) y trabaja de arriba hacia abajo. Puntaje = (Quiebre×3 + Encubierto×2 + Merma/VU×2 + Desviación×1) × peso ABC (A=3, B=2, C=1). Cada fila dice qué revisar. Datos al 22-10-2026.
A4: SKU | B4: Producto | C4: Categoría | D4: Segmento | E4: Estado stock | F4: Cobertura (sem) | G4: Stock disp (kg) | H4: SS final (kg) | I4: Punto reorden (kg) | J4: XLIB (kg) | K4: Próx. liberación | L4: Kg fuera filtro cadena exigente | M4: Kg a ≤6 pts del filtro | N4: Kg fuera de TODAS las cadenas | O4: Avance VU ponderado | P4: Tope cadena exigente | Q4: Margen (pts) | R4: Stock útil cadena exigente (kg) | S4: Solicitado 4 sem (kg) | T4: FCST 4 sem (kg) | U4: Desv. % | V4: ALERTA QUIEBRE | W4: QUIEBRE ENCUBIERTO (VU) | X4: ALERTA MERMA/VU | Y4: ALERTA DESVIACIÓN | Z4: N° alertas | AA4: Puntaje | AB4: Prioridad | AC4: Qué revisar | AE4: Resumen
A5: =Stock_Seguridad!A5 -> 30000522 | B5: =Stock_Seguridad!B5 -> LECHE BLANCA LONCO ENTERA BASE 12X1LT | C5: =Stock_Seguridad!C5 -> LECHES LIQUIDAS | D5: =Stock_Seguridad!F5 -> AX | E5: =Stock_Seguridad!X5 -> OK | F5: =Stock_Seguridad!W5 -> 1.666979 | G5: =Stock_Seguridad!T5 -> 276372 | H5: =Stock_Seguridad!R5 -> 203849.72 | I5: =Stock_Seguridad!S5 -> 530963.62 | J5: =Stock_Seguridad!U5 -> 268920 | K5: 46321 | L5: 684 | M5: 16080 | N5: 0 | O5: 0.033237672 | P5: =IF(ISNUMBER(Stock_Seguridad!N5),Stock_Seguridad!N5,"") -> 0.18848168 | Q5: =IF(AND(ISNUMBER(O5),ISNUMBER(P5)),P5-O5,"") -> 0.155244 | R5: =MAX(0,G5-N(L5)) -> 275688 | S5: =SUMIFS(Cadenas_vs_FCST!$D$17:$D$652,Cadenas_vs_FCST!$A$17:$A$652,A5) -> 1522272 | T5: =SUMIFS(Cadenas_vs_FCST!$E$17:$E$652,Cadenas_vs_FCST!$A$17:$A$652,A5) -> 1455276.1 | U5: =IF(T5>0,S5/T5-1,"") -> 0.046036548 | V5: =IF(OR(E5="BAJO SS",E5="BAJO SS (XLIB CUBRE)"),"SÍ","") | W5: =IF(AND(V5="",N(L5)>=Parametros!$B$17,G5>=H5,R5<H5),"SÍ","") | X5: =IF(OR(E5="SOBRE MAX VENDIBLE",N(N5)>=Parametros!$B$17,N(M5)>=Parametros!$B$17),"SÍ","") -> SÍ | Y5: =IF(AND(ISNUMBER(U5),MAX(S5,T5)>=Parametros!$B$15,ABS(N(U5))>Parametros!$B$14),"SÍ","") | Z5: =COUNTIF(V5:Y5,"SÍ") -> 1 | AA5: =(3*(V5="SÍ")+2*(W5="SÍ")+2*(X5="SÍ")+(Y5="SÍ"))*IF(LEFT(D5,1)="A",3,IF(OR(LEFT(D5,1)="B",D5="SIN HIST"),2,1)) -> 6 | AB5: =IF(AA5>=9,"1-ALTA",IF(AA5>=4,"2-MEDIA",IF(AA5>0,"3-BAJA",""))) -> 2-MEDIA | AC5: =IF(E5="BAJO SS","Stock + XLIB bajo el SS: riesgo real de quiebre, adelantar producción. ","")&IF(E5="BAJO SS (XLIB CUBRE)","Disponible bajo el SS; depende de liberar "&TEXT(J5,"#,##0")&" kg"&IF(ISNUMBER(K5)," el "&TEXT(K5,"dd-mm"),"")&". ","")&IF(W5="SÍ","Stock parece sano pero "&TEXT(L5,"#,##0")&" kg no pasan filtro "&Stock_Seguridad!O5&": sin ellos queda bajo el SS para esa cadena. ","")&IF(E5="SOBRE MAX VENDIBLE","Sobrestock vs vida útil: frenar producción/activar venta. ","")&IF(N(N5)>=Parametros!$B$17,TEXT(N5,"#,##0")&" kg ya no los acepta ninguna cadena: venta intermedia/liquidación. ","")&IF(N(M5)>=Parametros!$B$17,TEXT(M5,"#,##0")&" kg a punto de salir del filtro: despachar primero (FEFO). ","")&IF(Y5="SÍ","Pedidos "&IF(N(U5)>0,"sobre","bajo")&" FCST "&TEXT(ABS(N(U5)),"0%")&": revisar forecast con KAM.","") -> 16,080 kg a punto de salir del filtro: despachar primero (FEFO). | AE5: SKU con alerta de quiebre | AF5: =COUNTIF(V5:V118,"SÍ") -> 7
A6: =Stock_Seguridad!A6 -> 30000325 | B6: =Stock_Seguridad!B6 -> LECHE LONCO ENTERA S/LAC NAT 12X1LT | C6: =Stock_Seguridad!C6 -> LECHES LIQUIDAS | D6: =Stock_Seguridad!F6 -> AX | E6: =Stock_Seguridad!X6 -> OK | F6: =Stock_Seguridad!W6 -> 4.5409173 | G6: =Stock_Seguridad!T6 -> 582228 | H6: =Stock_Seguridad!R6 -> 54787.834 | I6: =Stock_Seguridad!S6 -> 236577.53 | J6: =Stock_Seguridad!U6 -> 243264 | K6: 46322 | L6: 1512 | M6: 89844 | N6: 768 | O6: 0.10510591 | P6: =IF(ISNUMBER(Stock_Seguridad!N6),Stock_Seguridad!N6,"") -> 0.25543478 | Q6: =IF(AND(ISNUMBER(O6),ISNUMBER(P6)),P6-O6,"") -> 0.15032887 | R6: =MAX(0,G6-N(L6)) -> 580716 | S6: =SUMIFS(Cadenas_vs_FCST!$D$17:$D$652,Cadenas_vs_FCST!$A$17:$A$652,A6) -> 502932 | T6: =SUMIFS(Cadenas_vs_FCST!$E$17:$E$652,Cadenas_vs_FCST!$A$17:$A$652,A6) -> 543530.18 | U6: =IF(T6>0,S6/T6-1,"") -> -0.07469351 | V6: =IF(OR(E6="BAJO SS",E6="BAJO SS (XLIB CUBRE)"),"SÍ","") | W6: =IF(AND(V6="",N(L6)>=Parametros!$B$17,G6>=H6,R6<H6),"SÍ","") | X6: =IF(OR(E6="SOBRE MAX VENDIBLE",N(N6)>=Parametros!$B$17,N(M6)>=Parametros!$B$17),"SÍ","") -> SÍ | Y6: =IF(AND(ISNUMBER(U6),MAX(S6,T6)>=Parametros!$B$15,ABS(N(U6))>Parametros!$B$14),"SÍ","") | Z6: =COUNTIF(V6:Y6,"SÍ") -> 1 | AA6: =(3*(V6="SÍ")+2*(W6="SÍ")+2*(X6="SÍ")+(Y6="SÍ"))*IF(LEFT(D6,1)="A",3,IF(OR(LEFT(D6,1)="B",D6="SIN HIST"),2,1)) -> 6 | AB6: =IF(AA6>=9,"1-ALTA",IF(AA6>=4,"2-MEDIA",IF(AA6>0,"3-BAJA",""))) -> 2-MEDIA | AC6: =IF(E6="BAJO SS","Stock + XLIB bajo el SS: riesgo real de quiebre, adelantar producción. ","")&IF(E6="BAJO SS (XLIB CUBRE)","Disponible bajo el SS; depende de liberar "&TEXT(J6,"#,##0")&" kg"&IF(ISNUMBER(K6)," el "&TEXT(K6,"dd-mm"),"")&". ","")&IF(W6="SÍ","Stock parece sano pero "&TEXT(L6,"#,##0")&" kg no pasan filtro "&Stock_Seguridad!O6&": sin ellos queda bajo el SS para esa cadena. ","")&IF(E6="SOBRE MAX VENDIBLE","Sobrestock vs vida útil: frenar producción/activar venta. ","")&IF(N(N6)>=Parametros!$B$17,TEXT(N6,"#,##0")&" kg ya no los acepta ninguna cadena: venta intermedia/liquidación. ","")&IF(N(M6)>=Parametros!$B$17,TEXT(M6,"#,##0")&" kg a punto de salir del filtro: despachar primero (FEFO). ","")&IF(Y6="SÍ","Pedidos "&IF(N(U6)>0,"sobre","bajo")&" FCST "&TEXT(ABS(N(U6)),"0%")&": revisar forecast con KAM.","") -> 768 kg ya no los acepta ninguna cadena: venta intermedia/liquidación. 89,844 kg a punto de salir del filtro: despachar primero (FEFO). | AE6: SKU con quiebre encubierto (VU) | AF6: =COUNTIF(W5:W118,"SÍ") -> 9
A7: =Stock_Seguridad!A7 -> 30000326 | B7: =Stock_Seguridad!B7 -> LECHE LONCO SEMIDESCREMADA S/LACT 12X1LT | C7: =Stock_Seguridad!C7 -> LECHES LIQUIDAS | D7: =Stock_Seguridad!F7 -> AX | E7: =Stock_Seguridad!X7 -> OK | F7: =Stock_Seguridad!W7 -> 2.2546197 | G7: =Stock_Seguridad!T7 -> 236280 | H7: =Stock_Seguridad!R7 -> 37565.447 | I7: =Stock_Seguridad!S7 -> 211357.95 | J7: =Stock_Seguridad!U7 -> 155556 | K7: 46319 | L7: 15576 | M7: 0 | N7: 4248 | O7: 0.076387075 | P7: =IF(ISNUMBER(Stock_Seguridad!N7),Stock_Seguridad!N7,"") -> 0.23913043 | Q7: =IF(AND(ISNUMBER(O7),ISNUMBER(P7)),P7-O7,"") -> 0.16274336 | R7: =MAX(0,G7-N(L7)) -> 220704 | S7: =SUMIFS(Cadenas_vs_FCST!$D$17:$D$652,Cadenas_vs_FCST!$A$17:$A$652,A7) -> 482760 | T7: =SUMIFS(Cadenas_vs_FCST!$E$17:$E$652,Cadenas_vs_FCST!$A$17:$A$652,A7) -> 521443.37 | U7: =IF(T7>0,S7/T7-1,"") -> -0.074185179 | V7: =IF(OR(E7="BAJO SS",E7="BAJO SS (XLIB CUBRE)"),"SÍ","") | W7: =IF(AND(V7="",N(L7)>=Parametros!$B$17,G7>=H7,R7<H7),"SÍ","") | X7: =IF(OR(E7="SOBRE MAX VENDIBLE",N(N7)>=Parametros!$B$17,N(M7)>=Parametros!$B$17),"SÍ","") -> SÍ | Y7: =IF(AND(ISNUMBER(U7),MAX(S7,T7)>=Parametros!$B$15,ABS(N(U7))>Parametros!$B$14),"SÍ","") | Z7: =COUNTIF(V7:Y7,"SÍ") -> 1 | AA7: =(3*(V7="SÍ")+2*(W7="SÍ")+2*(X7="SÍ")+(Y7="SÍ"))*IF(LEFT(D7,1)="A",3,IF(OR(LEFT(D7,1)="B",D7="SIN HIST"),2,1)) -> 6 | AB7: =IF(AA7>=9,"1-ALTA",IF(AA7>=4,"2-MEDIA",IF(AA7>0,"3-BAJA",""))) -> 2-MEDIA | AC7: =IF(E7="BAJO SS","Stock + XLIB bajo el SS: riesgo real de quiebre, adelantar producción. ","")&IF(E7="BAJO SS (XLIB CUBRE)","Disponible bajo el SS; depende de liberar "&TEXT(J7,"#,##0")&" kg"&IF(ISNUMBER(K7)," el "&TEXT(K7,"dd-mm"),"")&". ","")&IF(W7="SÍ","Stock parece sano pero "&TEXT(L7,"#,##0")&" kg no pasan filtro "&Stock_Seguridad!O7&": sin ellos queda bajo el SS para esa cadena. ","")&IF(E7="SOBRE MAX VENDIBLE","Sobrestock vs vida útil: frenar producción/activar venta. ","")&IF(N(N7)>=Parametros!$B$17,TEXT(N7,"#,##0")&" kg ya no los acepta ninguna cadena: venta intermedia/liquidación. ","")&IF(N(M7)>=Parametros!$B$17,TEXT(M7,"#,##0")&" kg a punto de salir del filtro: despachar primero (FEFO). ","")&IF(Y7="SÍ","Pedidos "&IF(N(U7)>0,"sobre","bajo")&" FCST "&TEXT(ABS(N(U7)),"0%")&": revisar forecast con KAM.","") -> 4,248 kg ya no los acepta ninguna cadena: venta intermedia/liquidación. | AE7: SKU con alerta merma/VU | AF7: =COUNTIF(X5:X118,"SÍ") -> 46
A8: =Stock_Seguridad!A8 -> 30000353 | B8: =Stock_Seguridad!B8 -> LECHE LONCO DESC S/LACTOSA 12X1LT | C8: =Stock_Seguridad!C8 -> LECHES LIQUIDAS | D8: =Stock_Seguridad!F8 -> AX | E8: =Stock_Seguridad!X8 -> OK | F8: =Stock_Seguridad!W8 -> 1.8538981 | G8: =Stock_Seguridad!T8 -> 218316 | H8: =Stock_Seguridad!R8 -> 51160.828 | I8: =Stock_Seguridad!S8 -> 183109.83 | J8: =Stock_Seguridad!U8 -> 26304 | K8: 46318 | L8: 2208 | M8: 252 | N8: 312 | O8: 0.071246848 | P8: =IF(ISNUMBER(Stock_Seguridad!N8),Stock_Seguridad!N8,"") -> 0.23913043 | Q8: =IF(AND(ISNUMBER(O8),ISNUMBER(P8)),P8-O8,"") -> 0.16788359 | R8: =MAX(0,G8-N(L8)) -> 216108 | S8: =SUMIFS(Cadenas_vs_FCST!$D$17:$D$652,Cadenas_vs_FCST!$A$17:$A$652,A8) -> 427464 | T8: =SUMIFS(Cadenas_vs_FCST!$E$17:$E$652,Cadenas_vs_FCST!$A$17:$A$652,A8) -> 393661.16 | U8: =IF(T8>0,S8/T8-1,"") -> 0.085867861 | V8: =IF(OR(E8="BAJO SS",E8="BAJO SS (XLIB CUBRE)"),"SÍ","") | W8: =IF(AND(V8="",N(L8)>=Parametros!$B$17,G8>=H8,R8<H8),"SÍ","") | X8: =IF(OR(E8="SOBRE MAX VENDIBLE",N(N8)>=Parametros!$B$17,N(M8)>=Parametros!$B$17),"SÍ","") | Y8: =IF(AND(ISNUMBER(U8),MAX(S8,T8)>=Parametros!$B$15,ABS(N(U8))>Parametros!$B$14),"SÍ","") | Z8: =COUNTIF(V8:Y8,"SÍ") -> 0 | AA8: =(3*(V8="SÍ")+2*(W8="SÍ")+2*(X8="SÍ")+(Y8="SÍ"))*IF(LEFT(D8,1)="A",3,IF(OR(LEFT(D8,1)="B",D8="SIN HIST"),2,1)) -> 0 | AB8: =IF(AA8>=9,"1-ALTA",IF(AA8>=4,"2-MEDIA",IF(AA8>0,"3-BAJA",""))) | AC8: =IF(E8="BAJO SS","Stock + XLIB bajo el SS: riesgo real de quiebre, adelantar producción. ","")&IF(E8="BAJO SS (XLIB CUBRE)","Disponible bajo el SS; depende de liberar "&TEXT(J8,"#,##0")&" kg"&IF(ISNUMBER(K8)," el "&TEXT(K8,"dd-mm"),"")&". ","")&IF(W8="SÍ","Stock parece sano pero "&TEXT(L8,"#,##0")&" kg no pasan filtro "&Stock_Seguridad!O8&": sin ellos queda bajo el SS para esa cadena. ","")&IF(E8="SOBRE MAX VENDIBLE","Sobrestock vs vida útil: frenar producción/activar venta. ","")&IF(N(N8)>=Parametros!$B$17,TEXT(N8,"#,##0")&" kg ya no los acepta ninguna cadena: venta intermedia/liquidación. ","")&IF(N(M8)>=Parametros!$B$17,TEXT(M8,"#,##0")&" kg a punto de salir del filtro: despachar primero (FEFO). ","")&IF(Y8="SÍ","Pedidos "&IF(N(U8)>0,"sobre","bajo")&" FCST "&TEXT(ABS(N(U8)),"0%")&": revisar forecast con KAM.","") | AE8: SKU con desviación pedido vs FCST | AF8: =COUNTIF(Y5:Y118,"SÍ") -> 42
A9: =Stock_Seguridad!A9 -> 30000523 | B9: =Stock_Seguridad!B9 -> LECHE BLANCA LONCO SEMI BASE 12X1LT | C9: =Stock_Seguridad!C9 -> LECHES LIQUIDAS | D9: =Stock_Seguridad!F9 -> AX | E9: =Stock_Seguridad!X9 -> SOBRE MAX VENDIBLE | F9: =Stock_Seguridad!W9 -> 7.3496743 | G9: =Stock_Seguridad!T9 -> 757980 | H9: =Stock_Seguridad!R9 -> 136290.41 | I9: =Stock_Seguridad!S9 -> 239421.51 | J9: =Stock_Seguridad!U9 -> 0 | L9: 318540 | M9: 102420 | N9: 768 | O9: 0.16776155 | P9: =IF(ISNUMBER(Stock_Seguridad!N9),Stock_Seguridad!N9,"") -> 0.18848168 | Q9: =IF(AND(ISNUMBER(O9),ISNUMBER(P9)),P9-O9,"") -> 0.020720129 | R9: =MAX(0,G9-N(L9)) -> 439440 | S9: =SUMIFS(Cadenas_vs_FCST!$D$17:$D$652,Cadenas_vs_FCST!$A$17:$A$652,A9) -> 273588 | T9: =SUMIFS(Cadenas_vs_FCST!$E$17:$E$652,Cadenas_vs_FCST!$A$17:$A$652,A9) -> 461942.51 | U9: =IF(T9>0,S9/T9-1,"") -> -0.40774448 | V9: =IF(OR(E9="BAJO SS",E9="BAJO SS (XLIB CUBRE)"),"SÍ","") | W9: =IF(AND(V9="",N(L9)>=Parametros!$B$17,G9>=H9,R9<H9),"SÍ","") | X9: =IF(OR(E9="SOBRE MAX VENDIBLE",N(N9)>=Parametros!$B$17,N(M9)>=Parametros!$B$17),"SÍ","") -> SÍ | Y9: =IF(AND(ISNUMBER(U9),MAX(S9,T9)>=Parametros!$B$15,ABS(N(U9))>Parametros!$B$14),"SÍ","") -> SÍ | Z9: =COUNTIF(V9:Y9,"SÍ") -> 2 | AA9: =(3*(V9="SÍ")+2*(W9="SÍ")+2*(X9="SÍ")+(Y9="SÍ"))*IF(LEFT(D9,1)="A",3,IF(OR(LEFT(D9,1)="B",D9="SIN HIST"),2,1)) -> 9 | AB9: =IF(AA9>=9,"1-ALTA",IF(AA9>=4,"2-MEDIA",IF(AA9>0,"3-BAJA",""))) -> 1-ALTA | AC9: =IF(E9="BAJO SS","Stock + XLIB bajo el SS: riesgo real de quiebre, adelantar producción. ","")&IF(E9="BAJO SS (XLIB CUBRE)","Disponible bajo el SS; depende de liberar "&TEXT(J9,"#,##0")&" kg"&IF(ISNUMBER(K9)," el "&TEXT(K9,"dd-mm"),"")&". ","")&IF(W9="SÍ","Stock parece sano pero "&TEXT(L9,"#,##0")&" kg no pasan filtro "&Stock_Seguridad!O9&": sin ellos queda bajo el SS para esa cadena. ","")&IF(E9="SOBRE MAX VENDIBLE","Sobrestock vs vida útil: frenar producción/activar venta. ","")&IF(N(N9)>=Parametros!$B$17,TEXT(N9,"#,##0")&" kg ya no los acepta ninguna cadena: venta intermedia/liquidación. ","")&IF(N(M9)>=Parametros!$B$17,TEXT(M9,"#,##0")&" kg a punto de salir del filtro: despachar primero (FEFO). ","")&IF(Y9="SÍ","Pedidos "&IF(N(U9)>0,"sobre","bajo")&" FCST "&TEXT(ABS(N(U9)),"0%")&": revisar forecast con KAM.","") -> Sobrestock vs vida útil: frenar producción/activar venta. 768 kg ya no los acepta ninguna cadena: venta intermedia/liquidación. 102,420 kg a punto de salir del filtro: despachar primero (FEFO). Pedidos bajo FCST 41%: revisar forecast con KAM. | AE9: Prioridad 1-ALTA | AF9: =COUNTIF(AB5:AB118,"1-ALTA") -> 5
A10: =Stock_Seguridad!A10 -> 30000255 | B10: =Stock_Seguridad!B10 -> NECTAR WATTS DZNO SIXPACK 30X200ML | C10: =Stock_Seguridad!C10 -> JUGOS Y NECTARES | D10: =Stock_Seguridad!F10 -> AY | E10: =Stock_Seguridad!X10 -> OK | F10: =Stock_Seguridad!W10 -> 5.2935953 | G10: =Stock_Seguridad!T10 -> 429072 | H10: =Stock_Seguridad!R10 -> 58177.81 | I10: =Stock_Seguridad!S10 -> 142305.51 | J10: =Stock_Seguridad!U10 -> 16266 | K10: 46317 | L10: 0 | M10: 0 | N10: 0 | O10: 0.052301643 | P10: =IF(ISNUMBER(Stock_Seguridad!N10),Stock_Seguridad!N10,"") -> 0.32054795 | Q10: =IF(AND(ISNUMBER(O10),ISNUMBER(P10)),P10-O10,"") -> 0.2682463 | R10: =MAX(0,G10-N(L10)) -> 429072 | S10: =SUMIFS(Cadenas_vs_FCST!$D$17:$D$652,Cadenas_vs_FCST!$A$17:$A$652,A10) -> 317406 | T10: =SUMIFS(Cadenas_vs_FCST!$E$17:$E$652,Cadenas_vs_FCST!$A$17:$A$652,A10) -> 276949.48 | U10: =IF(T10>0,S10/T10-1,"") -> 0.14607906 | V10: =IF(OR(E10="BAJO SS",E10="BAJO SS (XLIB CUBRE)"),"SÍ","") | W10: =IF(AND(V10="",N(L10)>=Parametros!$B$17,G10>=H10,R10<H10),"SÍ","") | X10: =IF(OR(E10="SOBRE MAX VENDIBLE",N(N10)>=Parametros!$B$17,N(M10)>=Parametros!$B$17),"SÍ","") | Y10: =IF(AND(ISNUMBER(U10),MAX(S10,T10)>=Parametros!$B$15,ABS(N(U10))>Parametros!$B$14),"SÍ","") | Z10: =COUNTIF(V10:Y10,"SÍ") -> 0 | AA10: =(3*(V10="SÍ")+2*(W10="SÍ")+2*(X10="SÍ")+(Y10="SÍ"))*IF(LEFT(D10,1)="A",3,IF(OR(LEFT(D10,1)="B",D10="SIN HIST"),2,1)) -> 0 | AB10: =IF(AA10>=9,"1-ALTA",IF(AA10>=4,"2-MEDIA",IF(AA10>0,"3-BAJA",""))) | AC10: =IF(E10="BAJO SS","Stock + XLIB bajo el SS: riesgo real de quiebre, adelantar producción. ","")&IF(E10="BAJO SS (XLIB CUBRE)","Disponible bajo el SS; depende de liberar "&TEXT(J10,"#,##0")&" kg"&IF(ISNUMBER(K10)," el "&TEXT(K10,"dd-mm"),"")&". ","")&IF(W10="SÍ","Stock parece sano pero "&TEXT(L10,"#,##0")&" kg no pasan filtro "&Stock_Seguridad!O10&": sin ellos queda bajo el SS para esa cadena. ","")&IF(E10="SOBRE MAX VENDIBLE","Sobrestock vs vida útil: frenar producción/activar venta. ","")&IF(N(N10)>=Parametros!$B$17,TEXT(N10,"#,##0")&" kg ya no los acepta ninguna cadena: venta intermedia/liquidación. ","")&IF(N(M10)>=Parametros!$B$17,TEXT(M10,"#,##0")&" kg a punto de salir del filtro: despachar primero (FEFO). ","")&IF(Y10="SÍ","Pedidos "&IF(N(U10)>0,"sobre","bajo")&" FCST "&TEXT(ABS(N(U10)),"0%")&": revisar forecast con KAM.","") | AE10: Prioridad 2-MEDIA | AF10: =COUNTIF(AB5:AB118,"2-MEDIA") -> 34
A11: =Stock_Seguridad!A11 -> 30000524 | B11: =Stock_Seguridad!B11 -> LECHE BLANCA LONCO DESC BASE 12X1LT | C11: =Stock_Seguridad!C11 -> LECHES LIQUIDAS | D11: =Stock_Seguridad!F11 -> AZ | E11: =Stock_Seguridad!X11 -> BAJO P.REORDEN | F11: =Stock_Seguridad!W11 -> 2.9294902 | G11: =Stock_Seguridad!T11 -> 208800 | H11: =Stock_Seguridad!R11 -> 205028.97 | I11: =Stock_Seguridad!S11 -> 276304.17 | J11: =Stock_Seguridad!U11 -> 0 | L11: 4020 | M11: 8232 | N11: 4020 | O11: 0.09304873 | P11: =IF(ISNUMBER(Stock_Seguridad!N11),Stock_Seguridad!N11,"") -> 0.18848168 | Q11: =IF(AND(ISNUMBER(O11),ISNUMBER(P11)),P11-O11,"") -> 0.095432945 | R11: =MAX(0,G11-N(L11)) -> 204780 | S11: =SUMIFS(Cadenas_vs_FCST!$D$17:$D$652,Cadenas_vs_FCST!$A$17:$A$652,A11) -> 426432 | T11: =SUMIFS(Cadenas_vs_FCST!$E$17:$E$652,Cadenas_vs_FCST!$A$17:$A$652,A11) -> 225993.6 | U11: =IF(T11>0,S11/T11-1,"") -> 0.88692067 | V11: =IF(OR(E11="BAJO SS",E11="BAJO SS (XLIB CUBRE)"),"SÍ","") | W11: =IF(AND(V11="",N(L11)>=Parametros!$B$17,G11>=H11,R11<H11),"SÍ","") -> SÍ | X11: =IF(OR(E11="SOBRE MAX VENDIBLE",N(N11)>=Parametros!$B$17,N(M11)>=Parametros!$B$17),"SÍ","") -> SÍ | Y11: =IF(AND(ISNUMBER(U11),MAX(S11,T11)>=Parametros!$B$15,ABS(N(U11))>Parametros!$B$14),"SÍ","") -> SÍ | Z11: =COUNTIF(V11:Y11,"SÍ") -> 3 | AA11: =(3*(V11="SÍ")+2*(W11="SÍ")+2*(X11="SÍ")+(Y11="SÍ"))*IF(LEFT(D11,1)="A",3,IF(OR(LEFT(D11,1)="B",D11="SIN HIST"),2,1)) -> 15 | AB11: =IF(AA11>=9,"1-ALTA",IF(AA11>=4,"2-MEDIA",IF(AA11>0,"3-BAJA",""))) -> 1-ALTA | AC11: =IF(E11="BAJO SS","Stock + XLIB bajo el SS: riesgo real de quiebre, adelantar producción. ","")&IF(E11="BAJO SS (XLIB CUBRE)","Disponible bajo el SS; depende de liberar "&TEXT(J11,"#,##0")&" kg"&IF(ISNUMBER(K11)," el "&TEXT(K11,"dd-mm"),"")&". ","")&IF(W11="SÍ","Stock parece sano pero "&TEXT(L11,"#,##0")&" kg no pasan filtro "&Stock_Seguridad!O11&": sin ellos queda bajo el SS para esa cadena. ","")&IF(E11="SOBRE MAX VENDIBLE","Sobrestock vs vida útil: frenar producción/activar venta. ","")&IF(N(N11)>=Parametros!$B$17,TEXT(N11,"#,##0")&" kg ya no los acepta ninguna cadena: venta intermedia/liquidación. ","")&IF(N(M11)>=Parametros!$B$17,TEXT(M11,"#,##0")&" kg a punto de salir del filtro: despachar primero (FEFO). ","")&IF(Y11="SÍ","Pedidos "&IF(N(U11)>0,"sobre","bajo")&" FCST "&TEXT(ABS(N(U11)),"0%")&": revisar forecast con KAM.","") -> Stock parece sano pero 4,020 kg no pasan filtro CENCOSUD CENTRAL: sin ellos queda bajo el SS para esa cadena. 4,020 kg ya no los acepta ninguna cadena: venta intermedia/liquidación. 8,232 kg a punto de salir del filtro: despachar primero (FEFO). Pedidos sobre FCST 89%: revisar forecast con KAM. | AE11: Kg fuera de filtro cadena exigente | AF11: =SUM(L5:L118) -> 444051.37
A12: =Stock_Seguridad!A12 -> 30000256 | B12: =Stock_Seguridad!B12 -> NECTAR WATTS PIÑA SIXPACK 30X200ML | C12: =Stock_Seguridad!C12 -> JUGOS Y NECTARES | D12: =Stock_Seguridad!F12 -> AY | E12: =Stock_Seguridad!X12 -> OK | F12: =Stock_Seguridad!W12 -> 3.7490697 | G12: =Stock_Seguridad!T12 -> 222156 | H12: =Stock_Seguridad!R12 -> 54208.244 | I12: =Stock_Seguridad!S12 -> 113464.54 | J12: =Stock_Seguridad!U12 -> 0 | L12: 306 | M12: 2436 | N12: 0 | O12: 0.10928945 | P12: =IF(ISNUMBER(Stock_Seguridad!N12),Stock_Seguridad!N12,"") -> 0.32054795 | Q12: =IF(AND(ISNUMBER(O12),ISNUMBER(P12)),P12-O12,"") -> 0.2112585 | R12: =MAX(0,G12-N(L12)) -> 221850 | S12: =SUMIFS(Cadenas_vs_FCST!$D$17:$D$652,Cadenas_vs_FCST!$A$17:$A$652,A12) -> 223524 | T12: =SUMIFS(Cadenas_vs_FCST!$E$17:$E$652,Cadenas_vs_FCST!$A$17:$A$652,A12) -> 203815.38 | U12: =IF(T12>0,S12/T12-1,"") -> 0.096698413 | V12: =IF(OR(E12="BAJO SS",E12="BAJO SS (XLIB CUBRE)"),"SÍ","") | W12: =IF(AND(V12="",N(L12)>=Parametros!$B$17,G12>=H12,R12<H12),"SÍ","") | X12: =IF(OR(E12="SOBRE MAX VENDIBLE",N(N12)>=Parametros!$B$17,N(M12)>=Parametros!$B$17),"SÍ","") -> SÍ | Y12: =IF(AND(ISNUMBER(U12),MAX(S12,T12)>=Parametros!$B$15,ABS(N(U12))>Parametros!$B$14),"SÍ","") | Z12: =COUNTIF(V12:Y12,"SÍ") -> 1 | AA12: =(3*(V12="SÍ")+2*(W12="SÍ")+2*(X12="SÍ")+(Y12="SÍ"))*IF(LEFT(D12,1)="A",3,IF(OR(LEFT(D12,1)="B",D12="SIN HIST"),2,1)) -> 6 | AB12: =IF(AA12>=9,"1-ALTA",IF(AA12>=4,"2-MEDIA",IF(AA12>0,"3-BAJA",""))) -> 2-MEDIA | AC12: =IF(E12="BAJO SS","Stock + XLIB bajo el SS: riesgo real de quiebre, adelantar producción. ","")&IF(E12="BAJO SS (XLIB CUBRE)","Disponible bajo el SS; depende de liberar "&TEXT(J12,"#,##0")&" kg"&IF(ISNUMBER(K12)," el "&TEXT(K12,"dd-mm"),"")&". ","")&IF(W12="SÍ","Stock parece sano pero "&TEXT(L12,"#,##0")&" kg no pasan filtro "&Stock_Seguridad!O12&": sin ellos queda bajo el SS para esa cadena. ","")&IF(E12="SOBRE MAX VENDIBLE","Sobrestock vs vida útil: frenar producción/activar venta. ","")&IF(N(N12)>=Parametros!$B$17,TEXT(N12,"#,##0")&" kg ya no los acepta ninguna cadena: venta intermedia/liquidación. ","")&IF(N(M12)>=Parametros!$B$17,TEXT(M12,"#,##0")&" kg a punto de salir del filtro: despachar primero (FEFO). ","")&IF(Y12="SÍ","Pedidos "&IF(N(U12)>0,"sobre","bajo")&" FCST "&TEXT(ABS(N(U12)),"0%")&": revisar forecast con KAM.","") -> 2,436 kg a punto de salir del filtro: despachar primero (FEFO). | AE12: Kg fuera de TODAS las cadenas | AF12: =SUM(N5:N118) -> 18608.7
A13: =Stock_Seguridad!A13 -> 30000257 | B13: =Stock_Seguridad!B13 -> NECTAR WATTS MZNA SIXPACK 30X200ML | C13: =Stock_Seguridad!C13 -> JUGOS Y NECTARES | D13: =Stock_Seguridad!F13 -> AX | E13: =Stock_Seguridad!X13 -> OK | F13: =Stock_Seguridad!W13 -> 5.8345525 | G13: =Stock_Seguridad!T13 -> 325398 | H13: =Stock_Seguridad!R13 -> 39827.553 | I13: =Stock_Seguridad!S13 -> 95741.353 | J13: =Stock_Seguridad!U13 -> 834 | K13: 46263 | L13: 0 | M13: 3690 | N13: 0 | O13: 0.079453459 | P13: =IF(ISNUMBER(Stock_Seguridad!N13),Stock_Seguridad!N13,"") -> 0.32054795 | Q13: =IF(AND(ISNUMBER(O13),ISNUMBER(P13)),P13-O13,"") -> 0.24109449 | R13: =MAX(0,G13-N(L13)) -> 325398 | S13: =SUMIFS(Cadenas_vs_FCST!$D$17:$D$652,Cadenas_vs_FCST!$A$17:$A$652,A13) -> 209526 | T13: =SUMIFS(Cadenas_vs_FCST!$E$17:$E$652,Cadenas_vs_FCST!$A$17:$A$652,A13) -> 224854.5 | U13: =IF(T13>0,S13/T13-1,"") -> -0.068170753 | V13: =IF(OR(E13="BAJO SS",E13="BAJO SS (XLIB CUBRE)"),"SÍ","") | W13: =IF(AND(V13="",N(L13)>=Parametros!$B$17,G13>=H13,R13<H13),"SÍ","") | X13: =IF(OR(E13="SOBRE MAX VENDIBLE",N(N13)>=Parametros!$B$17,N(M13)>=Parametros!$B$17),"SÍ","") -> SÍ | Y13: =IF(AND(ISNUMBER(U13),MAX(S13,T13)>=Parametros!$B$15,ABS(N(U13))>Parametros!$B$14),"SÍ","") | Z13: =COUNTIF(V13:Y13,"SÍ") -> 1 | AA13: =(3*(V13="SÍ")+2*(W13="SÍ")+2*(X13="SÍ")+(Y13="SÍ"))*IF(LEFT(D13,1)="A",3,IF(OR(LEFT(D13,1)="B",D13="SIN HIST"),2,1)) -> 6 | AB13: =IF(AA13>=9,"1-ALTA",IF(AA13>=4,"2-MEDIA",IF(AA13>0,"3-BAJA",""))) -> 2-MEDIA | AC13: =IF(E13="BAJO SS","Stock + XLIB bajo el SS: riesgo real de quiebre, adelantar producción. ","")&IF(E13="BAJO SS (XLIB CUBRE)","Disponible bajo el SS; depende de liberar "&TEXT(J13,"#,##0")&" kg"&IF(ISNUMBER(K13)," el "&TEXT(K13,"dd-mm"),"")&". ","")&IF(W13="SÍ","Stock parece sano pero "&TEXT(L13,"#,##0")&" kg no pasan filtro "&Stock_Seguridad!O13&": sin ellos queda bajo el SS para esa cadena. ","")&IF(E13="SOBRE MAX VENDIBLE","Sobrestock vs vida útil: frenar producción/activar venta. ","")&IF(N(N13)>=Parametros!$B$17,TEXT(N13,"#,##0")&" kg ya no los acepta ninguna cadena: venta intermedia/liquidación. ","")&IF(N(M13)>=Parametros!$B$17,TEXT(M13,"#,##0")&" kg a punto de salir del filtro: despachar primero (FEFO). ","")&IF(Y13="SÍ","Pedidos "&IF(N(U13)>0,"sobre","bajo")&" FCST "&TEXT(ABS(N(U13)),"0%")&": revisar forecast con KAM.","") -> 3,690 kg a punto de salir del filtro: despachar primero (FEFO).
A14: =Stock_Seguridad!A14 -> 30000258 | B14: =Stock_Seguridad!B14 -> NECTAR WATTS NJA SIXPACK 30X200ML | C14: =Stock_Seguridad!C14 -> JUGOS Y NECTARES | D14: =Stock_Seguridad!F14 -> AY | E14: =Stock_Seguridad!X14 -> OK | F14: =Stock_Seguridad!W14 -> 3.326752 | G14: =Stock_Seguridad!T14 -> 165294 | H14: =Stock_Seguridad!R14 -> 50190.009 | I14: =Stock_Seguridad!S14 -> 99876.309 | J14: =Stock_Seguridad!U14 -> 0 | L14: 0 | M14: 0 | N14: 0 | O14: 0.18631696 | P14: =IF(ISNUMBER(Stock_Seguridad!N14),Stock_Seguridad!N14,"") -> 0.32054795 | Q14: =IF(AND(ISNUMBER(O14),ISNUMBER(P14)),P14-O14,"") -> 0.13423099 | R14: =MAX(0,G14-N(L14)) -> 165294 | S14: =SUMIFS(Cadenas_vs_FCST!$D$17:$D$652,Cadenas_vs_FCST!$A$17:$A$652,A14) -> 150780 | T14: =SUMIFS(Cadenas_vs_FCST!$E$17:$E$652,Cadenas_vs_FCST!$A$17:$A$652,A14) -> 241835.55 | U14: =IF(T14>0,S14/T14-1,"") -> -0.37651846 | V14: =IF(OR(E14="BAJO SS",E14="BAJO SS (XLIB CUBRE)"),"SÍ","") | W14: =IF(AND(V14="",N(L14)>=Parametros!$B$17,G14>=H14,R14<H14),"SÍ","") | X14: =IF(OR(E14="SOBRE MAX VENDIBLE",N(N14)>=Parametros!$B$17,N(M14)>=Parametros!$B$17),"SÍ","") | Y14: =IF(AND(ISNUMBER(U14),MAX(S14,T14)>=Parametros!$B$15,ABS(N(U14))>Parametros!$B$14),"SÍ","") -> SÍ | Z14: =COUNTIF(V14:Y14,"SÍ") -> 1 | AA14: =(3*(V14="SÍ")+2*(W14="SÍ")+2*(X14="SÍ")+(Y14="SÍ"))*IF(LEFT(D14,1)="A",3,IF(OR(LEFT(D14,1)="B",D14="SIN HIST"),2,1)) -> 3 | AB14: =IF(AA14>=9,"1-ALTA",IF(AA14>=4,"2-MEDIA",IF(AA14>0,"3-BAJA",""))) -> 3-BAJA | AC14: =IF(E14="BAJO SS","Stock + XLIB bajo el SS: riesgo real de quiebre, adelantar producción. ","")&IF(E14="BAJO SS (XLIB CUBRE)","Disponible bajo el SS; depende de liberar "&TEXT(J14,"#,##0")&" kg"&IF(ISNUMBER(K14)," el "&TEXT(K14,"dd-mm"),"")&". ","")&IF(W14="SÍ","Stock parece sano pero "&TEXT(L14,"#,##0")&" kg no pasan filtro "&Stock_Seguridad!O14&": sin ellos queda bajo el SS para esa cadena. ","")&IF(E14="SOBRE MAX VENDIBLE","Sobrestock vs vida útil: frenar producción/activar venta. ","")&IF(N(N14)>=Parametros!$B$17,TEXT(N14,"#,##0")&" kg ya no los acepta ninguna cadena: venta intermedia/liquidación. ","")&IF(N(M14)>=Parametros!$B$17,TEXT(M14,"#,##0")&" kg a punto de salir del filtro: despachar primero (FEFO). ","")&IF(Y14="SÍ","Pedidos "&IF(N(U14)>0,"sobre","bajo")&" FCST "&TEXT(ABS(N(U14)),"0%")&": revisar forecast con KAM.","") -> Pedidos bajo FCST 38%: revisar forecast con KAM.
A15: =Stock_Seguridad!A15 -> 30000481 | B15: =Stock_Seguridad!B15 -> LECHE LONCO EXTRA PROTEINA 12X1LT | C15: =Stock_Seguridad!C15 -> LECHES LIQUIDAS | D15: =Stock_Seguridad!F15 -> AX | E15: =Stock_Seguridad!X15 -> OK | F15: =Stock_Seguridad!W15 -> 3.9810244 | G15: =Stock_Seguridad!T15 -> 114012 | H15: =Stock_Seguridad!R15 -> 29103.242 | I15: =Stock_Seguridad!S15 -> 69618.442 | J15: =Stock_Seguridad!U15 -> 47280 | K15: 46318 | L15: 972 | M15: 112992 | N15: 144 | O15: 0.16948128 | P15: =IF(ISNUMBER(Stock_Seguridad!N15),Stock_Seguridad!N15,"") -> 0.25925926 | Q15: =IF(AND(ISNUMBER(O15),ISNUMBER(P15)),P15-O15,"") -> 0.089777976 | R15: =MAX(0,G15-N(L15)) -> 113040 | S15: =SUMIFS(Cadenas_vs_FCST!$D$17:$D$652,Cadenas_vs_FCST!$A$17:$A$652,A15) -> 134016 | T15: =SUMIFS(Cadenas_vs_FCST!$E$17:$E$652,Cadenas_vs_FCST!$A$17:$A$652,A15) -> 139268.35 | U15: =IF(T15>0,S15/T15-1,"") -> -0.037713907 | V15: =IF(OR(E15="BAJO SS",E15="BAJO SS (XLIB CUBRE)"),"SÍ","") | W15: =IF(AND(V15="",N(L15)>=Parametros!$B$17,G15>=H15,R15<H15),"SÍ","") | X15: =IF(OR(E15="SOBRE MAX VENDIBLE",N(N15)>=Parametros!$B$17,N(M15)>=Parametros!$B$17),"SÍ","") -> SÍ | Y15: =IF(AND(ISNUMBER(U15),MAX(S15,T15)>=Parametros!$B$15,ABS(N(U15))>Parametros!$B$14),"SÍ","") | Z15: =COUNTIF(V15:Y15,"SÍ") -> 1 | AA15: =(3*(V15="SÍ")+2*(W15="SÍ")+2*(X15="SÍ")+(Y15="SÍ"))*IF(LEFT(D15,1)="A",3,IF(OR(LEFT(D15,1)="B",D15="SIN HIST"),2,1)) -> 6 | AB15: =IF(AA15>=9,"1-ALTA",IF(AA15>=4,"2-MEDIA",IF(AA15>0,"3-BAJA",""))) -> 2-MEDIA | AC15: =IF(E15="BAJO SS","Stock + XLIB bajo el SS: riesgo real de quiebre, adelantar producción. ","")&IF(E15="BAJO SS (XLIB CUBRE)","Disponible bajo el SS; depende de liberar "&TEXT(J15,"#,##0")&" kg"&IF(ISNUMBER(K15)," el "&TEXT(K15,"dd-mm"),"")&". ","")&IF(W15="SÍ","Stock parece sano pero "&TEXT(L15,"#,##0")&" kg no pasan filtro "&Stock_Seguridad!O15&": sin ellos queda bajo el SS para esa cadena. ","")&IF(E15="SOBRE MAX VENDIBLE","Sobrestock vs vida útil: frenar producción/activar venta. ","")&IF(N(N15)>=Parametros!$B$17,TEXT(N15,"#,##0")&" kg ya no los acepta ninguna cadena: venta intermedia/liquidación. ","")&IF(N(M15)>=Parametros!$B$17,TEXT(M15,"#,##0")&" kg a punto de salir del filtro: despachar primero (FEFO). ","")&IF(Y15="SÍ","Pedidos "&IF(N(U15)>0,"sobre","bajo")&" FCST "&TEXT(ABS(N(U15)),"0%")&": revisar forecast con KAM.","") -> 112,992 kg a punto de salir del filtro: despachar primero (FEFO).
A16: =Stock_Seguridad!A16 -> 30000309 | B16: =Stock_Seguridad!B16 -> YOGU YOGU MORA 30X200GR | C16: =Stock_Seguridad!C16 -> LECHES LIQUIDAS | D16: =Stock_Seguridad!F16 -> AX | E16: =Stock_Seguridad!X16 -> OK | F16: =Stock_Seguridad!W16 -> 3.3867875 | G16: =Stock_Seguridad!T16 -> 136686 | H16: =Stock_Seguridad!R16 -> 5302.3633 | I16: =Stock_Seguridad!S16 -> 45660.963 | J16: =Stock_Seguridad!U16 -> 0 | L16: 1188 | M16: 32928 | N16: 0 | O16: 0.105551 | P16: =IF(ISNUMBER(Stock_Seguridad!N16),Stock_Seguridad!N16,"") -> 0.24081633 | Q16: =IF(AND(ISNUMBER(O16),ISNUMBER(P16)),P16-O16,"") -> 0.13526533 | R16: =MAX(0,G16-N(L16)) -> 135498 | S16: =SUMIFS(Cadenas_vs_FCST!$D$17:$D$652,Cadenas_vs_FCST!$A$17:$A$652,A16) -> 151452 | T16: =SUMIFS(Cadenas_vs_FCST!$E$17:$E$652,Cadenas_vs_FCST!$A$17:$A$652,A16) -> 156937.08 | U16: =IF(T16>0,S16/T16-1,"") -> -0.034950824 | V16: =IF(OR(E16="BAJO SS",E16="BAJO SS (XLIB CUBRE)"),"SÍ","") | W16: =IF(AND(V16="",N(L16)>=Parametros!$B$17,G16>=H16,R16<H16),"SÍ","") | X16: =IF(OR(E16="SOBRE MAX VENDIBLE",N(N16)>=Parametros!$B$17,N(M16)>=Parametros!$B$17),"SÍ","") -> SÍ | Y16: =IF(AND(ISNUMBER(U16),MAX(S16,T16)>=Parametros!$B$15,ABS(N(U16))>Parametros!$B$14),"SÍ","") | Z16: =COUNTIF(V16:Y16,"SÍ") -> 1 | AA16: =(3*(V16="SÍ")+2*(W16="SÍ")+2*(X16="SÍ")+(Y16="SÍ"))*IF(LEFT(D16,1)="A",3,IF(OR(LEFT(D16,1)="B",D16="SIN HIST"),2,1)) -> 6 | AB16: =IF(AA16>=9,"1-ALTA",IF(AA16>=4,"2-MEDIA",IF(AA16>0,"3-BAJA",""))) -> 2-MEDIA | AC16: =IF(E16="BAJO SS","Stock + XLIB bajo el SS: riesgo real de quiebre, adelantar producción. ","")&IF(E16="BAJO SS (XLIB CUBRE)","Disponible bajo el SS; depende de liberar "&TEXT(J16,"#,##0")&" kg"&IF(ISNUMBER(K16)," el "&TEXT(K16,"dd-mm"),"")&". ","")&IF(W16="SÍ","Stock parece sano pero "&TEXT(L16,"#,##0")&" kg no pasan filtro "&Stock_Seguridad!O16&": sin ellos queda bajo el SS para esa cadena. ","")&IF(E16="SOBRE MAX VENDIBLE","Sobrestock vs vida útil: frenar producción/activar venta. ","")&IF(N(N16)>=Parametros!$B$17,TEXT(N16,"#,##0")&" kg ya no los acepta ninguna cadena: venta intermedia/liquidación. ","")&IF(N(M16)>=Parametros!$B$17,TEXT(M16,"#,##0")&" kg a punto de salir del filtro: despachar primero (FEFO). ","")&IF(Y16="SÍ","Pedidos "&IF(N(U16)>0,"sobre","bajo")&" FCST "&TEXT(ABS(N(U16)),"0%")&": revisar forecast con KAM.","") -> 32,928 kg a punto de salir del filtro: despachar primero (FEFO).
A17: =Stock_Seguridad!A17 -> 30000400 | B17: =Stock_Seguridad!B17 -> LECHE CHOC LONCO 30X200ML | C17: =Stock_Seguridad!C17 -> LECHES LIQUIDAS | D17: =Stock_Seguridad!F17 -> AX | E17: =Stock_Seguridad!X17 -> OK | F17: =Stock_Seguridad!W17 -> 4.2464086 | G17: =Stock_Seguridad!T17 -> 57756 | H17: =Stock_Seguridad!R17 -> 14461.343 | I17: =Stock_Seguridad!S17 -> 46495.943 | J17: =Stock_Seguridad!U17 -> 78276 | K17: 46320 | L17: 0 | M17: 72 | N17: 0 | O17: 0.047700314 | P17: =IF(ISNUMBER(Stock_Seguridad!N17),Stock_Seguridad!N17,"") -> 0.23831776 | Q17: =IF(AND(ISNUMBER(O17),ISNUMBER(P17)),P17-O17,"") -> 0.19061744 | R17: =MAX(0,G17-N(L17)) -> 57756 | S17: =SUMIFS(Cadenas_vs_FCST!$D$17:$D$652,Cadenas_vs_FCST!$A$17:$A$652,A17) -> 174120 | T17: =SUMIFS(Cadenas_vs_FCST!$E$17:$E$652,Cadenas_vs_FCST!$A$17:$A$652,A17) -> 145442.72 | U17: =IF(T17>0,S17/T17-1,"") -> 0.19717232 | V17: =IF(OR(E17="BAJO SS",E17="BAJO SS (XLIB CUBRE)"),"SÍ","") | W17: =IF(AND(V17="",N(L17)>=Parametros!$B$17,G17>=H17,R17<H17),"SÍ","") | X17: =IF(OR(E17="SOBRE MAX VENDIBLE",N(N17)>=Parametros!$B$17,N(M17)>=Parametros!$B$17),"SÍ","") | Y17: =IF(AND(ISNUMBER(U17),MAX(S17,T17)>=Parametros!$B$15,ABS(N(U17))>Parametros!$B$14),"SÍ","") | Z17: =COUNTIF(V17:Y17,"SÍ") -> 0 | AA17: =(3*(V17="SÍ")+2*(W17="SÍ")+2*(X17="SÍ")+(Y17="SÍ"))*IF(LEFT(D17,1)="A",3,IF(OR(LEFT(D17,1)="B",D17="SIN HIST"),2,1)) -> 0 | AB17: =IF(AA17>=9,"1-ALTA",IF(AA17>=4,"2-MEDIA",IF(AA17>0,"3-BAJA",""))) | AC17: =IF(E17="BAJO SS","Stock + XLIB bajo el SS: riesgo real de quiebre, adelantar producción. ","")&IF(E17="BAJO SS (XLIB CUBRE)","Disponible bajo el SS; depende de liberar "&TEXT(J17,"#,##0")&" kg"&IF(ISNUMBER(K17)," el "&TEXT(K17,"dd-mm"),"")&". ","")&IF(W17="SÍ","Stock parece sano pero "&TEXT(L17,"#,##0")&" kg no pasan filtro "&Stock_Seguridad!O17&": sin ellos queda bajo el SS para esa cadena. ","")&IF(E17="SOBRE MAX VENDIBLE","Sobrestock vs vida útil: frenar producción/activar venta. ","")&IF(N(N17)>=Parametros!$B$17,TEXT(N17,"#,##0")&" kg ya no los acepta ninguna cadena: venta intermedia/liquidación. ","")&IF(N(M17)>=Parametros!$B$17,TEXT(M17,"#,##0")&" kg a punto de salir del filtro: despachar primero (FEFO). ","")&IF(Y17="SÍ","Pedidos "&IF(N(U17)>0,"sobre","bajo")&" FCST "&TEXT(ABS(N(U17)),"0%")&": revisar forecast con KAM.","")
A18: =Stock_Seguridad!A18 -> 30000514 | B18: =Stock_Seguridad!B18 -> LECHE LONCO PROTEIN MILK CAPP 12X1LT | C18: =Stock_Seguridad!C18 -> LECHES LIQUIDAS | D18: =Stock_Seguridad!F18 -> AX | E18: =Stock_Seguridad!X18 -> BAJO P.REORDEN | F18: =Stock_Seguridad!W18 -> 1.1256679 | G18: =Stock_Seguridad!T18 -> 31284 | H18: =Stock_Seguridad!R18 -> 14942.281 | I18: =Stock_Seguridad!S18 -> 42733.781 | J18: =Stock_Seguridad!U18 -> 0 | L18: 2976 | M18: 3672 | N18: 0 | O18: 0.088589547 | P18: =IF(ISNUMBER(Stock_Seguridad!N18),Stock_Seguridad!N18,"") -> 0.21875 | Q18: =IF(AND(ISNUMBER(O18),ISNUMBER(P18)),P18-O18,"") -> 0.13016045 | R18: =MAX(0,G18-N(L18)) -> 28308 | S18: =SUMIFS(Cadenas_vs_FCST!$D$17:$D$652,Cadenas_vs_FCST!$A$17:$A$652,A18) -> 93684 | T18: =SUMIFS(Cadenas_vs_FCST!$E$17:$E$652,Cadenas_vs_FCST!$A$17:$A$652,A18) -> 78905.377 | U18: =IF(T18>0,S18/T18-1,"") -> 0.18729551 | V18: =IF(OR(E18="BAJO SS",E18="BAJO SS (XLIB CUBRE)"),"SÍ","") | W18: =IF(AND(V18="",N(L18)>=Parametros!$B$17,G18>=H18,R18<H18),"SÍ","") | X18: =IF(OR(E18="SOBRE MAX VENDIBLE",N(N18)>=Parametros!$B$17,N(M18)>=Parametros!$B$17),"SÍ","") -> SÍ | Y18: =IF(AND(ISNUMBER(U18),MAX(S18,T18)>=Parametros!$B$15,ABS(N(U18))>Parametros!$B$14),"SÍ","") | Z18: =COUNTIF(V18:Y18,"SÍ") -> 1 | AA18: =(3*(V18="SÍ")+2*(W18="SÍ")+2*(X18="SÍ")+(Y18="SÍ"))*IF(LEFT(D18,1)="A",3,IF(OR(LEFT(D18,1)="B",D18="SIN HIST"),2,1)) -> 6 | AB18: =IF(AA18>=9,"1-ALTA",IF(AA18>=4,"2-MEDIA",IF(AA18>0,"3-BAJA",""))) -> 2-MEDIA | AC18: =IF(E18="BAJO SS","Stock + XLIB bajo el SS: riesgo real de quiebre, adelantar producción. ","")&IF(E18="BAJO SS (XLIB CUBRE)","Disponible bajo el SS; depende de liberar "&TEXT(J18,"#,##0")&" kg"&IF(ISNUMBER(K18)," el "&TEXT(K18,"dd-mm"),"")&". ","")&IF(W18="SÍ","Stock parece sano pero "&TEXT(L18,"#,##0")&" kg no pasan filtro "&Stock_Seguridad!O18&": sin ellos queda bajo el SS para esa cadena. ","")&IF(E18="SOBRE MAX VENDIBLE","Sobrestock vs vida útil: frenar producción/activar venta. ","")&IF(N(N18)>=Parametros!$B$17,TEXT(N18,"#,##0")&" kg ya no los acepta ninguna cadena: venta intermedia/liquidación. ","")&IF(N(M18)>=Parametros!$B$17,TEXT(M18,"#,##0")&" kg a punto de salir del filtro: despachar primero (FEFO). ","")&IF(Y18="SÍ","Pedidos "&IF(N(U18)>0,"sobre","bajo")&" FCST "&TEXT(ABS(N(U18)),"0%")&": revisar forecast con KAM.","") -> 3,672 kg a punto de salir del filtro: despachar primero (FEFO).
A19: =Stock_Seguridad!A19 -> 30000305 | B19: =Stock_Seguridad!B19 -> YOGU YOGU FRUTILLA 30X200GR | C19: =Stock_Seguridad!C19 -> LECHES LIQUIDAS | D19: =Stock_Seguridad!F19 -> AX | E19: =Stock_Seguridad!X19 -> OK | F19: =Stock_Seguridad!W19 -> 3.8535218 | G19: =Stock_Seguridad!T19 -> 96918 | H19: =Stock_Seguridad!R19 -> 6844.4321 | I19: =Stock_Seguridad!S19 -> 31994.932 | J19: =Stock_Seguridad!U19 -> 0 | L19: 960 | M19: 41184 | N19: 0 | O19: 0.13009032 | P19: =IF(ISNUMBER(Stock_Seguridad!N19),Stock_Seguridad!N19,"") -> 0.22040816 | Q19: =IF(AND(ISNUMBER(O19),ISNUMBER(P19)),P19-O19,"") -> 0.090317843 | R19: =MAX(0,G19-N(L19)) -> 95958 | S19: =SUMIFS(Cadenas_vs_FCST!$D$17:$D$652,Cadenas_vs_FCST!$A$17:$A$652,A19) -> 83280 | T19: =SUMIFS(Cadenas_vs_FCST!$E$17:$E$652,Cadenas_vs_FCST!$A$17:$A$652,A19) -> 85037.805 | U19: =IF(T19>0,S19/T19-1,"") -> -0.020670867 | V19: =IF(OR(E19="BAJO SS",E19="BAJO SS (XLIB CUBRE)"),"SÍ","") | W19: =IF(AND(V19="",N(L19)>=Parametros!$B$17,G19>=H19,R19<H19),"SÍ","") | X19: =IF(OR(E19="SOBRE MAX VENDIBLE",N(N19)>=Parametros!$B$17,N(M19)>=Parametros!$B$17),"SÍ","") -> SÍ | Y19: =IF(AND(ISNUMBER(U19),MAX(S19,T19)>=Parametros!$B$15,ABS(N(U19))>Parametros!$B$14),"SÍ","") | Z19: =COUNTIF(V19:Y19,"SÍ") -> 1 | AA19: =(3*(V19="SÍ")+2*(W19="SÍ")+2*(X19="SÍ")+(Y19="SÍ"))*IF(LEFT(D19,1)="A",3,IF(OR(LEFT(D19,1)="B",D19="SIN HIST"),2,1)) -> 6 | AB19: =IF(AA19>=9,"1-ALTA",IF(AA19>=4,"2-MEDIA",IF(AA19>0,"3-BAJA",""))) -> 2-MEDIA | AC19: =IF(E19="BAJO SS","Stock + XLIB bajo el SS: riesgo real de quiebre, adelantar producción. ","")&IF(E19="BAJO SS (XLIB CUBRE)","Disponible bajo el SS; depende de liberar "&TEXT(J19,"#,##0")&" kg"&IF(ISNUMBER(K19)," el "&TEXT(K19,"dd-mm"),"")&". ","")&IF(W19="SÍ","Stock parece sano pero "&TEXT(L19,"#,##0")&" kg no pasan filtro "&Stock_Seguridad!O19&": sin ellos queda bajo el SS para esa cadena. ","")&IF(E19="SOBRE MAX VENDIBLE","Sobrestock vs vida útil: frenar producción/activar venta. ","")&IF(N(N19)>=Parametros!$B$17,TEXT(N19,"#,##0")&" kg ya no los acepta ninguna cadena: venta intermedia/liquidación. ","")&IF(N(M19)>=Parametros!$B$17,TEXT(M19,"#,##0")&" kg a punto de salir del filtro: despachar primero (FEFO). ","")&IF(Y19="SÍ","Pedidos "&IF(N(U19)>0,"sobre","bajo")&" FCST "&TEXT(ABS(N(U19)),"0%")&": revisar forecast con KAM.","") -> 41,184 kg a punto de salir del filtro: despachar primero (FEFO).
A20: =Stock_Seguridad!A20 -> 30002329 | B20: =Stock_Seguridad!B20 -> LECHE LONCO PROTEIN CAPPUCCINO 30X200ML | C20: =Stock_Seguridad!C20 -> LECHES LIQUIDAS | D20: =Stock_Seguridad!F20 -> AX | E20: =Stock_Seguridad!X20 -> OK | F20: =Stock_Seguridad!W20 -> 3.6094252 | G20: =Stock_Seguridad!T20 -> 86946 | H20: =Stock_Seguridad!R20 -> 11825.155 | I20: =Stock_Seguridad!S20 -> 35913.755 | J20: =Stock_Seguridad!U20 -> 0 | L20: 0 | M20: 0 | N20: 0 | O20: 0.10672072 | P20: =IF(ISNUMBER(Stock_Seguridad!N20),Stock_Seguridad!N20,"") | Q20: =IF(AND(ISNUMBER(O20),ISNUMBER(P20)),P20-O20,"") | R20: =MAX(0,G20-N(L20)) -> 86946 | S20: =SUMIFS(Cadenas_vs_FCST!$D$17:$D$652,Cadenas_vs_FCST!$A$17:$A$652,A20) -> 83460 | T20: =SUMIFS(Cadenas_vs_FCST!$E$17:$E$652,Cadenas_vs_FCST!$A$17:$A$652,A20) -> 81679.087 | U20: =IF(T20>0,S20/T20-1,"") -> 0.021803783 | V20: =IF(OR(E20="BAJO SS",E20="BAJO SS (XLIB CUBRE)"),"SÍ","") | W20: =IF(AND(V20="",N(L20)>=Parametros!$B$17,G20>=H20,R20<H20),"SÍ","") | X20: =IF(OR(E20="SOBRE MAX VENDIBLE",N(N20)>=Parametros!$B$17,N(M20)>=Parametros!$B$17),"SÍ","") | Y20: =IF(AND(ISNUMBER(U20),MAX(S20,T20)>=Parametros!$B$15,ABS(N(U20))>Parametros!$B$14),"SÍ","") | Z20: =COUNTIF(V20:Y20,"SÍ") -> 0 | AA20: =(3*(V20="SÍ")+2*(W20="SÍ")+2*(X20="SÍ")+(Y20="SÍ"))*IF(LEFT(D20,1)="A",3,IF(OR(LEFT(D20,1)="B",D20="SIN HIST"),2,1)) -> 0 | AB20: =IF(AA20>=9,"1-ALTA",IF(AA20>=4,"2-MEDIA",IF(AA20>0,"3-BAJA",""))) | AC20: =IF(E20="BAJO SS","Stock + XLIB bajo el SS: riesgo real de quiebre, adelantar producción. ","")&IF(E20="BAJO SS (XLIB CUBRE)","Disponible bajo el SS; depende de liberar "&TEXT(J20,"#,##0")&" kg"&IF(ISNUMBER(K20)," el "&TEXT(K20,"dd-mm"),"")&". ","")&IF(W20="SÍ","Stock parece sano pero "&TEXT(L20,"#,##0")&" kg no pasan filtro "&Stock_Seguridad!O20&": sin ellos queda bajo el SS para esa cadena. ","")&IF(E20="SOBRE MAX VENDIBLE","Sobrestock vs vida útil: frenar producción/activar venta. ","")&IF(N(N20)>=Parametros!$B$17,TEXT(N20,"#,##0")&" kg ya no los acepta ninguna cadena: venta intermedia/liquidación. ","")&IF(N(M20)>=Parametros!$B$17,TEXT(M20,"#,##0")&" kg a punto de salir del filtro: despachar primero (FEFO). ","")&IF(Y20="SÍ","Pedidos "&IF(N(U20)>0,"sobre","bajo")&" FCST "&TEXT(ABS(N(U20)),"0%")&": revisar forecast con KAM.","")
A21: =Stock_Seguridad!A21 -> 30000384 | B21: =Stock_Seguridad!B21 -> CREMA S/LAC LONCO 30X200ML | C21: =Stock_Seguridad!C21 -> CREMA | D21: =Stock_Seguridad!F21 -> AX | E21: =Stock_Seguridad!X21 -> OK | F21: =Stock_Seguridad!W21 -> 2.382303 | G21: =Stock_Seguridad!T21 -> 56862 | H21: =Stock_Seguridad!R21 -> 15904.195 | I21: =Stock_Seguridad!S21 -> 39772.695 | J21: =Stock_Seguridad!U21 -> 0 | L21: 48 | M21: 168 | N21: 0 | O21: 0.10590895 | P21: =IF(ISNUMBER(Stock_Seguridad!N21),Stock_Seguridad!N21,"") -> 0.25925926 | Q21: =IF(AND(ISNUMBER(O21),ISNUMBER(P21)),P21-O21,"") -> 0.15335031 | R21: =MAX(0,G21-N(L21)) -> 56814 | S21: =SUMIFS(Cadenas_vs_FCST!$D$17:$D$652,Cadenas_vs_FCST!$A$17:$A$652,A21) -> 80772 | T21: =SUMIFS(Cadenas_vs_FCST!$E$17:$E$652,Cadenas_vs_FCST!$A$17:$A$652,A21) -> 72959.844 | U21: =IF(T21>0,S21/T21-1,"") -> 0.10707473 | V21: =IF(OR(E21="BAJO SS",E21="BAJO SS (XLIB CUBRE)"),"SÍ","") | W21: =IF(AND(V21="",N(L21)>=Parametros!$B$17,G21>=H21,R21<H21),"SÍ","") | X21: =IF(OR(E21="SOBRE MAX VENDIBLE",N(N21)>=Parametros!$B$17,N(M21)>=Parametros!$B$17),"SÍ","") | Y21: =IF(AND(ISNUMBER(U21),MAX(S21,T21)>=Parametros!$B$15,ABS(N(U21))>Parametros!$B$14),"SÍ","") | Z21: =COUNTIF(V21:Y21,"SÍ") -> 0 | AA21: =(3*(V21="SÍ")+2*(W21="SÍ")+2*(X21="SÍ")+(Y21="SÍ"))*IF(LEFT(D21,1)="A",3,IF(OR(LEFT(D21,1)="B",D21="SIN HIST"),2,1)) -> 0 | AB21: =IF(AA21>=9,"1-ALTA",IF(AA21>=4,"2-MEDIA",IF(AA21>0,"3-BAJA",""))) | AC21: =IF(E21="BAJO SS","Stock + XLIB bajo el SS: riesgo real de quiebre, adelantar producción. ","")&IF(E21="BAJO SS (XLIB CUBRE)","Disponible bajo el SS; depende de liberar "&TEXT(J21,"#,##0")&" kg"&IF(ISNUMBER(K21)," el "&TEXT(K21,"dd-mm"),"")&". ","")&IF(W21="SÍ","Stock parece sano pero "&TEXT(L21,"#,##0")&" kg no pasan filtro "&Stock_Seguridad!O21&": sin ellos queda bajo el SS para esa cadena. ","")&IF(E21="SOBRE MAX VENDIBLE","Sobrestock vs vida útil: frenar producción/activar venta. ","")&IF(N(N21)>=Parametros!$B$17,TEXT(N21,"#,##0")&" kg ya no los acepta ninguna cadena: venta intermedia/liquidación. ","")&IF(N(M21)>=Parametros!$B$17,TEXT(M21,"#,##0")&" kg a punto de salir del filtro: despachar primero (FEFO). ","")&IF(Y21="SÍ","Pedidos "&IF(N(U21)>0,"sobre","bajo")&" FCST "&TEXT(ABS(N(U21)),"0%")&": revisar forecast con KAM.","")
A22: =Stock_Seguridad!A22 -> 30002099 | B22: =Stock_Seguridad!B22 -> NECTAR WATTS TUTTIFLLA SIXPACK 30X200ML | C22: =Stock_Seguridad!C22 -> JUGOS Y NECTARES | D22: =Stock_Seguridad!F22 -> AY | E22: =Stock_Seguridad!X22 -> OK | F22: =Stock_Seguridad!W22 -> 6.8047919 | G22: =Stock_Seguridad!T22 -> 146766 | H22: =Stock_Seguridad!R22 -> 52827.681 | I22: =Stock_Seguridad!S22 -> 74397.481 | J22: =Stock_Seguridad!U22 -> 12 | K22: 46317 | L22: 198 | M22: 0 | N22: 0 | O22: 0.047139353 | P22: =IF(ISNUMBER(Stock_Seguridad!N22),Stock_Seguridad!N22,"") -> 0.19444444 | Q22: =IF(AND(ISNUMBER(O22),ISNUMBER(P22)),P22-O22,"") -> 0.14730509 | R22: =MAX(0,G22-N(L22)) -> 146568 | S22: =SUMIFS(Cadenas_vs_FCST!$D$17:$D$652,Cadenas_vs_FCST!$A$17:$A$652,A22) -> 119580 | T22: =SUMIFS(Cadenas_vs_FCST!$E$17:$E$652,Cadenas_vs_FCST!$A$17:$A$652,A22) -> 127888.8 | U22: =IF(T22>0,S22/T22-1,"") -> -0.064968964 | V22: =IF(OR(E22="BAJO SS",E22="BAJO SS (XLIB CUBRE)"),"SÍ","") | W22: =IF(AND(V22="",N(L22)>=Parametros!$B$17,G22>=H22,R22<H22),"SÍ","") | X22: =IF(OR(E22="SOBRE MAX VENDIBLE",N(N22)>=Parametros!$B$17,N(M22)>=Parametros!$B$17),"SÍ","") | Y22: =IF(AND(ISNUMBER(U22),MAX(S22,T22)>=Parametros!$B$15,ABS(N(U22))>Parametros!$B$14),"SÍ","") | Z22: =COUNTIF(V22:Y22,"SÍ") -> 0 | AA22: =(3*(V22="SÍ")+2*(W22="SÍ")+2*(X22="SÍ")+(Y22="SÍ"))*IF(LEFT(D22,1)="A",3,IF(OR(LEFT(D22,1)="B",D22="SIN HIST"),2,1)) -> 0 | AB22: =IF(AA22>=9,"1-ALTA",IF(AA22>=4,"2-MEDIA",IF(AA22>0,"3-BAJA",""))) | AC22: =IF(E22="BAJO SS","Stock + XLIB bajo el SS: riesgo real de quiebre, adelantar producción. ","")&IF(E22="BAJO SS (XLIB CUBRE)","Disponible bajo el SS; depende de liberar "&TEXT(J22,"#,##0")&" kg"&IF(ISNUMBER(K22)," el "&TEXT(K22,"dd-mm"),"")&". ","")&IF(W22="SÍ","Stock parece sano pero "&TEXT(L22,"#,##0")&" kg no pasan filtro "&Stock_Seguridad!O22&": sin ellos queda bajo el SS para esa cadena. ","")&IF(E22="SOBRE MAX VENDIBLE","Sobrestock vs vida útil: frenar producción/activar venta. ","")&IF(N(N22)>=Parametros!$B$17,TEXT(N22,"#,##0")&" kg ya no los acepta ninguna cadena: venta intermedia/liquidación. ","")&IF(N(M22)>=Parametros!$B$17,TEXT(M22,"#,##0")&" kg a punto de salir del filtro: despachar primero (FEFO). ","")&IF(Y22="SÍ","Pedidos "&IF(N(U22)>0,"sobre","bajo")&" FCST "&TEXT(ABS(N(U22)),"0%")&": revisar forecast con KAM.","")
A23: =Stock_Seguridad!A23 -> 30002066 | B23: =Stock_Seguridad!B23 -> LECHE FRUTILLA LONCOLECHE 12X1LT | C23: =Stock_Seguridad!C23 -> LECHES LIQUIDAS | D23: =Stock_Seguridad!F23 -> AX | E23: =Stock_Seguridad!X23 -> BAJO SS | F23: =Stock_Seguridad!W23 -> 1.8335788 | G23: =Stock_Seguridad!T23 -> 34860 | H23: =Stock_Seguridad!R23 -> 41008.139 | I23: =Stock_Seguridad!S23 -> 60020.139 | J23: =Stock_Seguridad!U23 -> 0 | L23: 492 | M23: 0 | N23: 36 | O23: 0.037311532 | P23: =IF(ISNUMBER(Stock_Seguridad!N23),Stock_Seguridad!N23,"") -> 0.23831776 | Q23: =IF(AND(ISNUMBER(O23),ISNUMBER(P23)),P23-O23,"") -> 0.20100623 | R23: =MAX(0,G23-N(L23)) -> 34368 | S23: =SUMIFS(Cadenas_vs_FCST!$D$17:$D$652,Cadenas_vs_FCST!$A$17:$A$652,A23) -> 108816 | T23: =SUMIFS(Cadenas_vs_FCST!$E$17:$E$652,Cadenas_vs_FCST!$A$17:$A$652,A23) -> 38172.57 | U23: =IF(T23>0,S23/T23-1,"") -> 1.8506334 | V23: =IF(OR(E23="BAJO SS",E23="BAJO SS (XLIB CUBRE)"),"SÍ","") -> SÍ | W23: =IF(AND(V23="",N(L23)>=Parametros!$B$17,G23>=H23,R23<H23),"SÍ","") | X23: =IF(OR(E23="SOBRE MAX VENDIBLE",N(N23)>=Parametros!$B$17,N(M23)>=Parametros!$B$17),"SÍ","") | Y23: =IF(AND(ISNUMBER(U23),MAX(S23,T23)>=Parametros!$B$15,ABS(N(U23))>Parametros!$B$14),"SÍ","") -> SÍ | Z23: =COUNTIF(V23:Y23,"SÍ") -> 2 | AA23: =(3*(V23="SÍ")+2*(W23="SÍ")+2*(X23="SÍ")+(Y23="SÍ"))*IF(LEFT(D23,1)="A",3,IF(OR(LEFT(D23,1)="B",D23="SIN HIST"),2,1)) -> 12 | AB23: =IF(AA23>=9,"1-ALTA",IF(AA23>=4,"2-MEDIA",IF(AA23>0,"3-BAJA",""))) -> 1-ALTA | AC23: =IF(E23="BAJO SS","Stock + XLIB bajo el SS: riesgo real de quiebre, adelantar producción. ","")&IF(E23="BAJO SS (XLIB CUBRE)","Disponible bajo el SS; depende de liberar "&TEXT(J23,"#,##0")&" kg"&IF(ISNUMBER(K23)," el "&TEXT(K23,"dd-mm"),"")&". ","")&IF(W23="SÍ","Stock parece sano pero "&TEXT(L23,"#,##0")&" kg no pasan filtro "&Stock_Seguridad!O23&": sin ellos queda bajo el SS para esa cadena. ","")&IF(E23="SOBRE MAX VENDIBLE","Sobrestock vs vida útil: frenar producción/activar venta. ","")&IF(N(N23)>=Parametros!$B$17,TEXT(N23,"#,##0")&" kg ya no los acepta ninguna cadena: venta intermedia/liquidación. ","")&IF(N(M23)>=Parametros!$B$17,TEXT(M23,"#,##0")&" kg a punto de salir del filtro: despachar primero (FEFO). ","")&IF(Y23="SÍ","Pedidos "&IF(N(U23)>0,"sobre","bajo")&" FCST "&TEXT(ABS(N(U23)),"0%")&": revisar forecast con KAM.","") -> Stock + XLIB bajo el SS: riesgo real de quiebre, adelantar producción. Pedidos sobre FCST 185%: revisar forecast con KAM.
A24: =Stock_Seguridad!A24 -> 30002065 | B24: =Stock_Seguridad!B24 -> LECHE CHOCOLATE LONCOLECHE 12X1LT | C24: =Stock_Seguridad!C24 -> LECHES LIQUIDAS | D24: =Stock_Seguridad!F24 -> BY | E24: =Stock_Seguridad!X24 -> BAJO P.REORDEN | F24: =Stock_Seguridad!W24 -> 0.67784505 | G24: =Stock_Seguridad!T24 -> 11520 | H24: =Stock_Seguridad!R24 -> 8108.6827 | I24: =Stock_Seguridad!S24 -> 26590.783 | J24: =Stock_Seguridad!U24 -> 1008 | K24: 46320 | L24: 0 | M24: 96 | N24: 0 | O24: 0.071082375 | P24: =IF(ISNUMBER(Stock_Seguridad!N24),Stock_Seguridad!N24,"") -> 0.23831776 | Q24: =IF(AND(ISNUMBER(O24),ISNUMBER(P24)),P24-O24,"") -> 0.16723538 | R24: =MAX(0,G24-N(L24)) -> 11520 | S24: =SUMIFS(Cadenas_vs_FCST!$D$17:$D$652,Cadenas_vs_FCST!$A$17:$A$652,A24) -> 28884 | T24: =SUMIFS(Cadenas_vs_FCST!$E$17:$E$652,Cadenas_vs_FCST!$A$17:$A$652,A24) -> 31045.235 | U24: =IF(T24>0,S24/T24-1,"") -> -0.069615674 | V24: =IF(OR(E24="BAJO SS",E24="BAJO SS (XLIB CUBRE)"),"SÍ","") | W24: =IF(AND(V24="",N(L24)>=Parametros!$B$17,G24>=H24,R24<H24),"SÍ","") | X24: =IF(OR(E24="SOBRE MAX VENDIBLE",N(N24)>=Parametros!$B$17,N(M24)>=Parametros!$B$17),"SÍ","") | Y24: =IF(AND(ISNUMBER(U24),MAX(S24,T24)>=Parametros!$B$15,ABS(N(U24))>Parametros!$B$14),"SÍ","") | Z24: =COUNTIF(V24:Y24,"SÍ") -> 0 | AA24: =(3*(V24="SÍ")+2*(W24="SÍ")+2*(X24="SÍ")+(Y24="SÍ"))*IF(LEFT(D24,1)="A",3,IF(OR(LEFT(D24,1)="B",D24="SIN HIST"),2,1)) -> 0 | AB24: =IF(AA24>=9,"1-ALTA",IF(AA24>=4,"2-MEDIA",IF(AA24>0,"3-BAJA",""))) | AC24: =IF(E24="BAJO SS","Stock + XLIB bajo el SS: riesgo real de quiebre, adelantar producción. ","")&IF(E24="BAJO SS (XLIB CUBRE)","Disponible bajo el SS; depende de liberar "&TEXT(J24,"#,##0")&" kg"&IF(ISNUMBER(K24)," el "&TEXT(K24,"dd-mm"),"")&". ","")&IF(W24="SÍ","Stock parece sano pero "&TEXT(L24,"#,##0")&" kg no pasan filtro "&Stock_Seguridad!O24&": sin ellos queda bajo el SS para esa cadena. ","")&IF(E24="SOBRE MAX VENDIBLE","Sobrestock vs vida útil: frenar producción/activar venta. ","")&IF(N(N24)>=Parametros!$B$17,TEXT(N24,"#,##0")&" kg ya no los acepta ninguna cadena: venta intermedia/liquidación. ","")&IF(N(M24)>=Parametros!$B$17,TEXT(M24,"#,##0")&" kg a punto de salir del filtro: despachar primero (FEFO). ","")&IF(Y24="SÍ","Pedidos "&IF(N(U24)>0,"sobre","bajo")&" FCST "&TEXT(ABS(N(U24)),"0%")&": revisar forecast con KAM.","")
A25: =Stock_Seguridad!A25 -> 30000401 | B25: =Stock_Seguridad!B25 -> LECHE LONCO FRUTILLA 30X200ML | C25: =Stock_Seguridad!C25 -> LECHES LIQUIDAS | D25: =Stock_Seguridad!F25 -> AY | E25: =Stock_Seguridad!X25 -> OK | F25: =Stock_Seguridad!W25 -> 5.1576248 | G25: =Stock_Seguridad!T25 -> 91698 | H25: =Stock_Seguridad!R25 -> 47041.835 | I25: =Stock_Seguridad!S25 -> 64976.835 | J25: =Stock_Seguridad!U25 -> 804 | K25: 46313 | L25: 5064 | M25: 4008 | N25: 0 | O25: 0.091508271 | P25: =IF(ISNUMBER(Stock_Seguridad!N25),Stock_Seguridad!N25,"") -> 0.23831776 | Q25: =IF(AND(ISNUMBER(O25),ISNUMBER(P25)),P25-O25,"") -> 0.14680949 | R25: =MAX(0,G25-N(L25)) -> 86634 | S25: =SUMIFS(Cadenas_vs_FCST!$D$17:$D$652,Cadenas_vs_FCST!$A$17:$A$652,A25) -> 140712 | T25: =SUMIFS(Cadenas_vs_FCST!$E$17:$E$652,Cadenas_vs_FCST!$A$17:$A$652,A25) -> 122422.75 | U25: =IF(T25>0,S25/T25-1,"") -> 0.14939421 | V25: =IF(OR(E25="BAJO SS",E25="BAJO SS (XLIB CUBRE)"),"SÍ","") | W25: =IF(AND(V25="",N(L25)>=Parametros!$B$17,G25>=H25,R25<H25),"SÍ","") | X25: =IF(OR(E25="SOBRE MAX VENDIBLE",N(N25)>=Parametros!$B$17,N(M25)>=Parametros!$B$17),"SÍ","") -> SÍ | Y25: =IF(AND(ISNUMBER(U25),MAX(S25,T25)>=Parametros!$B$15,ABS(N(U25))>Parametros!$B$14),"SÍ","") | Z25: =COUNTIF(V25:Y25,"SÍ") -> 1 | AA25: =(3*(V25="SÍ")+2*(W25="SÍ")+2*(X25="SÍ")+(Y25="SÍ"))*IF(LEFT(D25,1)="A",3,IF(OR(LEFT(D25,1)="B",D25="SIN HIST"),2,1)) -> 6 | AB25: =IF(AA25>=9,"1-ALTA",IF(AA25>=4,"2-MEDIA",IF(AA25>0,"3-BAJA",""))) -> 2-MEDIA | AC25: =IF(E25="BAJO SS","Stock + XLIB bajo el SS: riesgo real de quiebre, adelantar producción. ","")&IF(E25="BAJO SS (XLIB CUBRE)","Disponible bajo el SS; depende de liberar "&TEXT(J25,"#,##0")&" kg"&IF(ISNUMBER(K25)," el "&TEXT(K25,"dd-mm"),"")&". ","")&IF(W25="SÍ","Stock parece sano pero "&TEXT(L25,"#,##0")&" kg no pasan filtro "&Stock_Seguridad!O25&": sin ellos queda bajo el SS para esa cadena. ","")&IF(E25="SOBRE MAX VENDIBLE","Sobrestock vs vida útil: frenar producción/activar venta. ","")&IF(N(N25)>=Parametros!$B$17,TEXT(N25,"#,##0")&" kg ya no los acepta ninguna cadena: venta intermedia/liquidación. ","")&IF(N(M25)>=Parametros!$B$17,TEXT(M25,"#,##0")&" kg a punto de salir del filtro: despachar primero (FEFO). ","")&IF(Y25="SÍ","Pedidos "&IF(N(U25)>0,"sobre","bajo")&" FCST "&TEXT(ABS(N(U25)),"0%")&": revisar forecast con KAM.","") -> 4,008 kg a punto de salir del filtro: despachar primero (FEFO).
A26: =Stock_Seguridad!A26 -> 30000516 | B26: =Stock_Seguridad!B26 -> LECHE LONCO PROTEIN MILK CHOCO 12X1LT | C26: =Stock_Seguridad!C26 -> LECHES LIQUIDAS | D26: =Stock_Seguridad!F26 -> BX | E26: =Stock_Seguridad!X26 -> OK | F26: =Stock_Seguridad!W26 -> 3.1129305 | G26: =Stock_Seguridad!T26 -> 54372 | H26: =Stock_Seguridad!R26 -> 4762.8588 | I26: =Stock_Seguridad!S26 -> 22229.359 | J26: =Stock_Seguridad!U26 -> 0 | L26: 24 | M26: 14388 | N26: 12 | O26: 0.10630382 | P26: =IF(ISNUMBER(Stock_Seguridad!N26),Stock_Seguridad!N26,"") -> 0.25925926 | Q26: =IF(AND(ISNUMBER(O26),ISNUMBER(P26)),P26-O26,"") -> 0.15295544 | R26: =MAX(0,G26-N(L26)) -> 54348 | S26: =SUMIFS(Cadenas_vs_FCST!$D$17:$D$652,Cadenas_vs_FCST!$A$17:$A$652,A26) -> 51792 | T26: =SUMIFS(Cadenas_vs_FCST!$E$17:$E$652,Cadenas_vs_FCST!$A$17:$A$652,A26) -> 52663.766 | U26: =IF(T26>0,S26/T26-1,"") -> -0.016553429 | V26: =IF(OR(E26="BAJO SS",E26="BAJO SS (XLIB CUBRE)"),"SÍ","") | W26: =IF(AND(V26="",N(L26)>=Parametros!$B$17,G26>=H26,R26<H26),"SÍ","") | X26: =IF(OR(E26="SOBRE MAX VENDIBLE",N(N26)>=Parametros!$B$17,N(M26)>=Parametros!$B$17),"SÍ","") -> SÍ | Y26: =IF(AND(ISNUMBER(U26),MAX(S26,T26)>=Parametros!$B$15,ABS(N(U26))>Parametros!$B$14),"SÍ","") | Z26: =COUNTIF(V26:Y26,"SÍ") -> 1 | AA26: =(3*(V26="SÍ")+2*(W26="SÍ")+2*(X26="SÍ")+(Y26="SÍ"))*IF(LEFT(D26,1)="A",3,IF(OR(LEFT(D26,1)="B",D26="SIN HIST"),2,1)) -> 4 | AB26: =IF(AA26>=9,"1-ALTA",IF(AA26>=4,"2-MEDIA",IF(AA26>0,"3-BAJA",""))) -> 2-MEDIA | AC26: =IF(E26="BAJO SS","Stock + XLIB bajo el SS: riesgo real de quiebre, adelantar producción. ","")&IF(E26="BAJO SS (XLIB CUBRE)","Disponible bajo el SS; depende de liberar "&TEXT(J26,"#,##0")&" kg"&IF(ISNUMBER(K26)," el "&TEXT(K26,"dd-mm"),"")&". ","")&IF(W26="SÍ","Stock parece sano pero "&TEXT(L26,"#,##0")&" kg no pasan filtro "&Stock_Seguridad!O26&": sin ellos queda bajo el SS para esa cadena. ","")&IF(E26="SOBRE MAX VENDIBLE","Sobrestock vs vida útil: frenar producción/activar venta. ","")&IF(N(N26)>=Parametros!$B$17,TEXT(N26,"#,##0")&" kg ya no los acepta ninguna cadena: venta intermedia/liquidación. ","")&IF(N(M26)>=Parametros!$B$17,TEXT(M26,"#,##0")&" kg a punto de salir del filtro: despachar primero (FEFO). ","")&IF(Y26="SÍ","Pedidos "&IF(N(U26)>0,"sobre","bajo")&" FCST "&TEXT(ABS(N(U26)),"0%")&": revisar forecast con KAM.","") -> 14,388 kg a punto de salir del filtro: despachar primero (FEFO).
A27: =Stock_Seguridad!A27 -> 30002315 | B27: =Stock_Seguridad!B27 -> LECHE LONCO FULL PRO DESCR 12X1LT | C27: =Stock_Seguridad!C27 -> LECHES LIQUIDAS | D27: =Stock_Seguridad!F27 -> AX | E27: =Stock_Seguridad!X27 -> BAJO SS (XLIB CUBRE) | F27: =Stock_Seguridad!W27 -> 3.1991718 | G27: =Stock_Seguridad!T27 -> 2268 | H27: =Stock_Seguridad!R27 -> 16055.17 | I27: =Stock_Seguridad!S27 -> 32863.27 | J27: =Stock_Seguridad!U27 -> 51504 | K27: 46317 | L27: 0 | M27: 0 | N27: 0 | O27: 0.039122964 | P27: =IF(ISNUMBER(Stock_Seguridad!N27),Stock_Seguridad!N27,"") | Q27: =IF(AND(ISNUMBER(O27),ISNUMBER(P27)),P27-O27,"") | R27: =MAX(0,G27-N(L27)) -> 2268 | S27: =SUMIFS(Cadenas_vs_FCST!$D$17:$D$652,Cadenas_vs_FCST!$A$17:$A$652,A27) -> 73680 | T27: =SUMIFS(Cadenas_vs_FCST!$E$17:$E$652,Cadenas_vs_FCST!$A$17:$A$652,A27) -> 53368.418 | U27: =IF(T27>0,S27/T27-1,"") -> 0.3805918 | V27: =IF(OR(E27="BAJO SS",E27="BAJO SS (XLIB CUBRE)"),"SÍ","") -> SÍ | W27: =IF(AND(V27="",N(L27)>=Parametros!$B$17,G27>=H27,R27<H27),"SÍ","") | X27: =IF(OR(E27="SOBRE MAX VENDIBLE",N(N27)>=Parametros!$B$17,N(M27)>=Parametros!$B$17),"SÍ","") | Y27: =IF(AND(ISNUMBER(U27),MAX(S27,T27)>=Parametros!$B$15,ABS(N(U27))>Parametros!$B$14),"SÍ","") -> SÍ | Z27: =COUNTIF(V27:Y27,"SÍ") -> 2 | AA27: =(3*(V27="SÍ")+2*(W27="SÍ")+2*(X27="SÍ")+(Y27="SÍ"))*IF(LEFT(D27,1)="A",3,IF(OR(LEFT(D27,1)="B",D27="SIN HIST"),2,1)) -> 12 | AB27: =IF(AA27>=9,"1-ALTA",IF(AA27>=4,"2-MEDIA",IF(AA27>0,"3-BAJA",""))) -> 1-ALTA | AC27: =IF(E27="BAJO SS","Stock + XLIB bajo el SS: riesgo real de quiebre, adelantar producción. ","")&IF(E27="BAJO SS (XLIB CUBRE)","Disponible bajo el SS; depende de liberar "&TEXT(J27,"#,##0")&" kg"&IF(ISNUMBER(K27)," el "&TEXT(K27,"dd-mm"),"")&". ","")&IF(W27="SÍ","Stock parece sano pero "&TEXT(L27,"#,##0")&" kg no pasan filtro "&Stock_Seguridad!O27&": sin ellos queda bajo el SS para esa cadena. ","")&IF(E27="SOBRE MAX VENDIBLE","Sobrestock vs vida útil: frenar producción/activar venta. ","")&IF(N(N27)>=Parametros!$B$17,TEXT(N27,"#,##0")&" kg ya no los acepta ninguna cadena: venta intermedia/liquidación. ","")&IF(N(M27)>=Parametros!$B$17,TEXT(M27,"#,##0")&" kg a punto de salir del filtro: despachar primero (FEFO). ","")&IF(Y27="SÍ","Pedidos "&IF(N(U27)>0,"sobre","bajo")&" FCST "&TEXT(ABS(N(U27)),"0%")&": revisar forecast con KAM.","") -> Disponible bajo el SS; depende de liberar 51,504 kg el 22-10. Pedidos sobre FCST 38%: revisar forecast con KAM.
A28: =Stock_Seguridad!A28 -> 30000254 | B28: =Stock_Seguridad!B28 -> NECTAR WATTS NJA LIGHT SIXPACK 30X200ML | C28: =Stock_Seguridad!C28 -> JUGOS Y NECTARES | D28: =Stock_Seguridad!F28 -> AX | E28: =Stock_Seguridad!X28 -> OK | F28: =Stock_Seguridad!W28 -> 4.9168917 | G28: =Stock_Seguridad!T28 -> 81378 | H28: =Stock_Seguridad!R28 -> 11571.68 | I28: =Stock_Seguridad!S28 -> 28122.38 | J28: =Stock_Seguridad!U28 -> 0 | L28: 126 | M28: 108 | N28: 0 | O28: 0.0509251 | P28: =IF(ISNUMBER(Stock_Seguridad!N28),Stock_Seguridad!N28,"") -> 0.31636364 | Q28: =IF(AND(ISNUMBER(O28),ISNUMBER(P28)),P28-O28,"") -> 0.26543854 | R28: =MAX(0,G28-N(L28)) -> 81252 | S28: =SUMIFS(Cadenas_vs_FCST!$D$17:$D$652,Cadenas_vs_FCST!$A$17:$A$652,A28) -> 50724 | T28: =SUMIFS(Cadenas_vs_FCST!$E$17:$E$652,Cadenas_vs_FCST!$A$17:$A$652,A28) -> 61200.664 | U28: =IF(T28>0,S28/T28-1,"") -> -0.17118546 | V28: =IF(OR(E28="BAJO SS",E28="BAJO SS (XLIB CUBRE)"),"SÍ","") | W28: =IF(AND(V28="",N(L28)>=Parametros!$B$17,G28>=H28,R28<H28),"SÍ","") | X28: =IF(OR(E28="SOBRE MAX VENDIBLE",N(N28)>=Parametros!$B$17,N(M28)>=Parametros!$B$17),"SÍ","") | Y28: =IF(AND(ISNUMBER(U28),MAX(S28,T28)>=Parametros!$B$15,ABS(N(U28))>Parametros!$B$14),"SÍ","") | Z28: =COUNTIF(V28:Y28,"SÍ") -> 0 | AA28: =(3*(V28="SÍ")+2*(W28="SÍ")+2*(X28="SÍ")+(Y28="SÍ"))*IF(LEFT(D28,1)="A",3,IF(OR(LEFT(D28,1)="B",D28="SIN HIST"),2,1)) -> 0 | AB28: =IF(AA28>=9,"1-ALTA",IF(AA28>=4,"2-MEDIA",IF(AA28>0,"3-BAJA",""))) | AC28: =IF(E28="BAJO SS","Stock + XLIB bajo el SS: riesgo real de quiebre, adelantar producción. ","")&IF(E28="BAJO SS (XLIB CUBRE)","Disponible bajo el SS; depende de liberar "&TEXT(J28,"#,##0")&" kg"&IF(ISNUMBER(K28)," el "&TEXT(K28,"dd-mm"),"")&". ","")&IF(W28="SÍ","Stock parece sano pero "&TEXT(L28,"#,##0")&" kg no pasan filtro "&Stock_Seguridad!O28&": sin ellos queda bajo el SS para esa cadena. ","")&IF(E28="SOBRE MAX VENDIBLE","Sobrestock vs vida útil: frenar producción/activar venta. ","")&IF(N(N28)>=Parametros!$B$17,TEXT(N28,"#,##0")&" kg ya no los acepta ninguna cadena: venta intermedia/liquidación. ","")&IF(N(M28)>=Parametros!$B$17,TEXT(M28,"#,##0")&" kg a punto de salir del filtro: despachar primero (FEFO). ","")&IF(Y28="SÍ","Pedidos "&IF(N(U28)>0,"sobre","bajo")&" FCST "&TEXT(ABS(N(U28)),"0%")&": revisar forecast con KAM.","")
A29: =Stock_Seguridad!A29 -> 30000206 | B29: =Stock_Seguridad!B29 -> NECTAR WATTS MZNA LIGHT 30X200ML | C29: =Stock_Seguridad!C29 -> JUGOS Y NECTARES | D29: =Stock_Seguridad!F29 -> BX | E29: =Stock_Seguridad!X29 -> OK | F29: =Stock_Seguridad!W29 -> 4.2141232 | G29: =Stock_Seguridad!T29 -> 65364 | H29: =Stock_Seguridad!R29 -> 4365.5903 | I29: =Stock_Seguridad!S29 -> 19876.29 | J29: =Stock_Seguridad!U29 -> 0 | L29: 726 | M29: 8688 | N29: 36 | O29: 0.081144722 | P29: =IF(ISNUMBER(Stock_Seguridad!N29),Stock_Seguridad!N29,"") -> 0.19272727 | Q29: =IF(AND(ISNUMBER(O29),ISNUMBER(P29)),P29-O29,"") -> 0.11158255 | R29: =MAX(0,G29-N(L29)) -> 64638 | S29: =SUMIFS(Cadenas_vs_FCST!$D$17:$D$652,Cadenas_vs_FCST!$A$17:$A$652,A29) -> 40806 | T29: =SUMIFS(Cadenas_vs_FCST!$E$17:$E$652,Cadenas_vs_FCST!$A$17:$A$652,A29) -> 47482.562 | U29: =IF(T29>0,S29/T29-1,"") -> -0.14061082 | V29: =IF(OR(E29="BAJO SS",E29="BAJO SS (XLIB CUBRE)"),"SÍ","") | W29: =IF(AND(V29="",N(L29)>=Parametros!$B$17,G29>=H29,R29<H29),"SÍ","") | X29: =IF(OR(E29="SOBRE MAX VENDIBLE",N(N29)>=Parametros!$B$17,N(M29)>=Parametros!$B$17),"SÍ","") -> SÍ | Y29: =IF(AND(ISNUMBER(U29),MAX(S29,T29)>=Parametros!$B$15,ABS(N(U29))>Parametros!$B$14),"SÍ","") | Z29: =COUNTIF(V29:Y29,"SÍ") -> 1 | AA29: =(3*(V29="SÍ")+2*(W29="SÍ")+2*(X29="SÍ")+(Y29="SÍ"))*IF(LEFT(D29,1)="A",3,IF(OR(LEFT(D29,1)="B",D29="SIN HIST"),2,1)) -> 4 | AB29: =IF(AA29>=9,"1-ALTA",IF(AA29>=4,"2-MEDIA",IF(AA29>0,"3-BAJA",""))) -> 2-MEDIA | AC29: =IF(E29="BAJO SS","Stock + XLIB bajo el SS: riesgo real de quiebre, adelantar producción. ","")&IF(E29="BAJO SS (XLIB CUBRE)","Disponible bajo el SS; depende de liberar "&TEXT(J29,"#,##0")&" kg"&IF(ISNUMBER(K29)," el "&TEXT(K29,"dd-mm"),"")&". ","")&IF(W29="SÍ","Stock parece sano pero "&TEXT(L29,"#,##0")&" kg no pasan filtro "&Stock_Seguridad!O29&": sin ellos queda bajo el SS para esa cadena. ","")&IF(E29="SOBRE MAX VENDIBLE","Sobrestock vs vida útil: frenar producción/activar venta. ","")&IF(N(N29)>=Parametros!$B$17,TEXT(N29,"#,##0")&" kg ya no los acepta ninguna cadena: venta intermedia/liquidación. ","")&IF(N(M29)>=Parametros!$B$17,TEXT(M29,"#,##0")&" kg a punto de salir del filtro: despachar primero (FEFO). ","")&IF(Y29="SÍ","Pedidos "&IF(N(U29)>0,"sobre","bajo")&" FCST "&TEXT(ABS(N(U29)),"0%")&": revisar forecast con KAM.","") -> 8,688 kg a punto de salir del filtro: despachar primero (FEFO).
A30: =Stock_Seguridad!A30 -> 30001684 | B30: =Stock_Seguridad!B30 -> NECTAR WATTS DZNO S/A 30X200ML | C30: =Stock_Seguridad!C30 -> JUGOS Y NECTARES | D30: =Stock_Seguridad!F30 -> AX | E30: =Stock_Seguridad!X30 -> OK | F30: =Stock_Seguridad!W30 -> 5.0045373 | G30: =Stock_Seguridad!T30 -> 42978 | H30: =Stock_Seguridad!R30 -> 6684.4985 | I30: =Stock_Seguridad!S30 -> 22112.099 | J30: =Stock_Seguridad!U30 -> 34230 | K30: 46317 | L30: 264 | M30: 16746 | N30: 0 | O30: 0.069157657 | P30: =IF(ISNUMBER(Stock_Seguridad!N30),Stock_Seguridad!N30,"") -> 0.19272727 | Q30: =IF(AND(ISNUMBER(O30),ISNUMBER(P30)),P30-O30,"") -> 0.12356962 | R30: =MAX(0,G30-N(L30)) -> 42714 | S30: =SUMIFS(Cadenas_vs_FCST!$D$17:$D$652,Cadenas_vs_FCST!$A$17:$A$652,A30) -> 55818 | T30: =SUMIFS(Cadenas_vs_FCST!$E$17:$E$652,Cadenas_vs_FCST!$A$17:$A$652,A30) -> 63864.747 | U30: =IF(T30>0,S30/T30-1,"") -> -0.1259967 | V30: =IF(OR(E30="BAJO SS",E30="BAJO SS (XLIB CUBRE)"),"SÍ","") | W30: =IF(AND(V30="",N(L30)>=Parametros!$B$17,G30>=H30,R30<H30),"SÍ","") | X30: =IF(OR(E30="SOBRE MAX VENDIBLE",N(N30)>=Parametros!$B$17,N(M30)>=Parametros!$B$17),"SÍ","") -> SÍ | Y30: =IF(AND(ISNUMBER(U30),MAX(S30,T30)>=Parametros!$B$15,ABS(N(U30))>Parametros!$B$14),"SÍ","") | Z30: =COUNTIF(V30:Y30,"SÍ") -> 1 | AA30: =(3*(V30="SÍ")+2*(W30="SÍ")+2*(X30="SÍ")+(Y30="SÍ"))*IF(LEFT(D30,1)="A",3,IF(OR(LEFT(D30,1)="B",D30="SIN HIST"),2,1)) -> 6 | AB30: =IF(AA30>=9,"1-ALTA",IF(AA30>=4,"2-MEDIA",IF(AA30>0,"3-BAJA",""))) -> 2-MEDIA | AC30: =IF(E30="BAJO SS","Stock + XLIB bajo el SS: riesgo real de quiebre, adelantar producción. ","")&IF(E30="BAJO SS (XLIB CUBRE)","Disponible bajo el SS; depende de liberar "&TEXT(J30,"#,##0")&" kg"&IF(ISNUMBER(K30)," el "&TEXT(K30,"dd-mm"),"")&". ","")&IF(W30="SÍ","Stock parece sano pero "&TEXT(L30,"#,##0")&" kg no pasan filtro "&Stock_Seguridad!O30&": sin ellos queda bajo el SS para esa cadena. ","")&IF(E30="SOBRE MAX VENDIBLE","Sobrestock vs vida útil: frenar producción/activar venta. ","")&IF(N(N30)>=Parametros!$B$17,TEXT(N30,"#,##0")&" kg ya no los acepta ninguna cadena: venta intermedia/liquidación. ","")&IF(N(M30)>=Parametros!$B$17,TEXT(M30,"#,##0")&" kg a punto de salir del filtro: despachar primero (FEFO). ","")&IF(Y30="SÍ","Pedidos "&IF(N(U30)>0,"sobre","bajo")&" FCST "&TEXT(ABS(N(U30)),"0%")&": revisar forecast con KAM.","") -> 16,746 kg a punto de salir del filtro: despachar primero (FEFO).
A31: =Stock_Seguridad!A31 -> 30001409 | B31: =Stock_Seguridad!B31 -> LECHE POLVO CALO ENTERA INST 20X850GR | C31: =Stock_Seguridad!C31 -> LECHES EN POLVO | D31: =Stock_Seguridad!F31 -> AX | E31: =Stock_Seguridad!X31 -> OK | F31: =Stock_Seguridad!W31 -> 5.3891654 | G31: =Stock_Seguridad!T31 -> 81634 | H31: =Stock_Seguridad!R31 -> 8565.5828 | I31: =Stock_Seguridad!S31 -> 23713.383 | J31: =Stock_Seguridad!U31 -> 0 | L31: 0 | M31: 0 | N31: 0 | O31: 0.05184464 | P31: =IF(ISNUMBER(Stock_Seguridad!N31),Stock_Seguridad!N31,"") -> 0.32054795 | Q31: =IF(AND(ISNUMBER(O31),ISNUMBER(P31)),P31-O31,"") -> 0.26870331 | R31: =MAX(0,G31-N(L31)) -> 81634 | S31: =SUMIFS(Cadenas_vs_FCST!$D$17:$D$652,Cadenas_vs_FCST!$A$17:$A$652,A31) -> 60299 | T31: =SUMIFS(Cadenas_vs_FCST!$E$17:$E$652,Cadenas_vs_FCST!$A$17:$A$652,A31) -> 66053.322 | U31: =IF(T31>0,S31/T31-1,"") -> -0.087116322 | V31: =IF(OR(E31="BAJO SS",E31="BAJO SS (XLIB CUBRE)"),"SÍ","") | W31: =IF(AND(V31="",N(L31)>=Parametros!$B$17,G31>=H31,R31<H31),"SÍ","") | X31: =IF(OR(E31="SOBRE MAX VENDIBLE",N(N31)>=Parametros!$B$17,N(M31)>=Parametros!$B$17),"SÍ","") | Y31: =IF(AND(ISNUMBER(U31),MAX(S31,T31)>=Parametros!$B$15,ABS(N(U31))>Parametros!$B$14),"SÍ","") | Z31: =COUNTIF(V31:Y31,"SÍ") -> 0 | AA31: =(3*(V31="SÍ")+2*(W31="SÍ")+2*(X31="SÍ")+(Y31="SÍ"))*IF(LEFT(D31,1)="A",3,IF(OR(LEFT(D31,1)="B",D31="SIN HIST"),2,1)) -> 0 | AB31: =IF(AA31>=9,"1-ALTA",IF(AA31>=4,"2-MEDIA",IF(AA31>0,"3-BAJA",""))) | AC31: =IF(E31="BAJO SS","Stock + XLIB bajo el SS: riesgo real de quiebre, adelantar producción. ","")&IF(E31="BAJO SS (XLIB CUBRE)","Disponible bajo el SS; depende de liberar "&TEXT(J31,"#,##0")&" kg"&IF(ISNUMBER(K31)," el "&TEXT(K31,"dd-mm"),"")&". ","")&IF(W31="SÍ","Stock parece sano pero "&TEXT(L31,"#,##0")&" kg no pasan filtro "&Stock_Seguridad!O31&": sin ellos queda bajo el SS para esa cadena. ","")&IF(E31="SOBRE MAX VENDIBLE","Sobrestock vs vida útil: frenar producción/activar venta. ","")&IF(N(N31)>=Parametros!$B$17,TEXT(N31,"#,##0")&" kg ya no los acepta ninguna cadena: venta intermedia/liquidación. ","")&IF(N(M31)>=Parametros!$B$17,TEXT(M31,"#,##0")&" kg a punto de salir del filtro: despachar primero (FEFO). ","")&IF(Y31="SÍ","Pedidos "&IF(N(U31)>0,"sobre","bajo")&" FCST "&TEXT(ABS(N(U31)),"0%")&": revisar forecast con KAM.","")
A32: =Stock_Seguridad!A32 -> 30002330 | B32: =Stock_Seguridad!B32 -> LECHE LONCO PROTEIN CHOCOLATE 30X200ML | C32: =Stock_Seguridad!C32 -> LECHES LIQUIDAS | D32: =Stock_Seguridad!F32 -> BX | E32: =Stock_Seguridad!X32 -> OK | F32: =Stock_Seguridad!W32 -> 2.0801696 | G32: =Stock_Seguridad!T32 -> 29040 | H32: =Stock_Seguridad!R32 -> 10140.198 | I32: =Stock_Seguridad!S32 -> 24100.598 | J32: =Stock_Seguridad!U32 -> 0 | L32: 0 | M32: 0 | N32: 0 | O32: 0.10277686 | P32: =IF(ISNUMBER(Stock_Seguridad!N32),Stock_Seguridad!N32,"") | Q32: =IF(AND(ISNUMBER(O32),ISNUMBER(P32)),P32-O32,"") | R32: =MAX(0,G32-N(L32)) -> 29040 | S32: =SUMIFS(Cadenas_vs_FCST!$D$17:$D$652,Cadenas_vs_FCST!$A$17:$A$652,A32) -> 57954 | T32: =SUMIFS(Cadenas_vs_FCST!$E$17:$E$652,Cadenas_vs_FCST!$A$17:$A$652,A32) -> 40869.728 | U32: =IF(T32>0,S32/T32-1,"") -> 0.41801777 | V32: =IF(OR(E32="BAJO SS",E32="BAJO SS (XLIB CUBRE)"),"SÍ","") | W32: =IF(AND(V32="",N(L32)>=Parametros!$B$17,G32>=H32,R32<H32),"SÍ","") | X32: =IF(OR(E32="SOBRE MAX VENDIBLE",N(N32)>=Parametros!$B$17,N(M32)>=Parametros!$B$17),"SÍ","") | Y32: =IF(AND(ISNUMBER(U32),MAX(S32,T32)>=Parametros!$B$15,ABS(N(U32))>Parametros!$B$14),"SÍ","") -> SÍ | Z32: =COUNTIF(V32:Y32,"SÍ") -> 1 | AA32: =(3*(V32="SÍ")+2*(W32="SÍ")+2*(X32="SÍ")+(Y32="SÍ"))*IF(LEFT(D32,1)="A",3,IF(OR(LEFT(D32,1)="B",D32="SIN HIST"),2,1)) -> 2 | AB32: =IF(AA32>=9,"1-ALTA",IF(AA32>=4,"2-MEDIA",IF(AA32>0,"3-BAJA",""))) -> 3-BAJA | AC32: =IF(E32="BAJO SS","Stock + XLIB bajo el SS: riesgo real de quiebre, adelantar producción. ","")&IF(E32="BAJO SS (XLIB CUBRE)","Disponible bajo el SS; depende de liberar "&TEXT(J32,"#,##0")&" kg"&IF(ISNUMBER(K32)," el "&TEXT(K32,"dd-mm"),"")&". ","")&IF(W32="SÍ","Stock parece sano pero "&TEXT(L32,"#,##0")&" kg no pasan filtro "&Stock_Seguridad!O32&": sin ellos queda bajo el SS para esa cadena. ","")&IF(E32="SOBRE MAX VENDIBLE","Sobrestock vs vida útil: frenar producción/activar venta. ","")&IF(N(N32)>=Parametros!$B$17,TEXT(N32,"#,##0")&" kg ya no los acepta ninguna cadena: venta intermedia/liquidación. ","")&IF(N(M32)>=Parametros!$B$17,TEXT(M32,"#,##0")&" kg a punto de salir del filtro: despachar primero (FEFO). ","")&IF(Y32="SÍ","Pedidos "&IF(N(U32)>0,"sobre","bajo")&" FCST "&TEXT(ABS(N(U32)),"0%")&": revisar forecast con KAM.","") -> Pedidos sobre FCST 42%: revisar forecast con KAM.
A33: =Stock_Seguridad!A33 -> 30002177 | B33: =Stock_Seguridad!B33 -> MANJAR LONCOLECHE BOLSA 10X920GR | C33: =Stock_Seguridad!C33 -> MANJAR | D33: =Stock_Seguridad!F33 -> BX | E33: =Stock_Seguridad!X33 -> SOBRE MAX VENDIBLE | F33: =Stock_Seguridad!W33 -> 5.0768947 | G33: =Stock_Seguridad!T33 -> 66129.6 | H33: =Stock_Seguridad!R33 -> 5963.6522 | I33: =Stock_Seguridad!S33 -> 18989.252 | J33: =Stock_Seguridad!U33 -> 0 | L33: 3367.2 | M33: 9862.4 | N33: 0 | O33: 0.083014747 | P33: =IF(ISNUMBER(Stock_Seguridad!N33),Stock_Seguridad!N33,"") -> 0.19021739 | Q33: =IF(AND(ISNUMBER(O33),ISNUMBER(P33)),P33-O33,"") -> 0.10720264 | R33: =MAX(0,G33-N(L33)) -> 62762.4 | S33: =SUMIFS(Cadenas_vs_FCST!$D$17:$D$652,Cadenas_vs_FCST!$A$17:$A$652,A33) -> 46791.2 | T33: =SUMIFS(Cadenas_vs_FCST!$E$17:$E$652,Cadenas_vs_FCST!$A$17:$A$652,A33) -> 48916.398 | U33: =IF(T33>0,S33/T33-1,"") -> -0.043445519 | V33: =IF(OR(E33="BAJO SS",E33="BAJO SS (XLIB CUBRE)"),"SÍ","") | W33: =IF(AND(V33="",N(L33)>=Parametros!$B$17,G33>=H33,R33<H33),"SÍ","") | X33: =IF(OR(E33="SOBRE MAX VENDIBLE",N(N33)>=Parametros!$B$17,N(M33)>=Parametros!$B$17),"SÍ","") -> SÍ | Y33: =IF(AND(ISNUMBER(U33),MAX(S33,T33)>=Parametros!$B$15,ABS(N(U33))>Parametros!$B$14),"SÍ","") | Z33: =COUNTIF(V33:Y33,"SÍ") -> 1 | AA33: =(3*(V33="SÍ")+2*(W33="SÍ")+2*(X33="SÍ")+(Y33="SÍ"))*IF(LEFT(D33,1)="A",3,IF(OR(LEFT(D33,1)="B",D33="SIN HIST"),2,1)) -> 4 | AB33: =IF(AA33>=9,"1-ALTA",IF(AA33>=4,"2-MEDIA",IF(AA33>0,"3-BAJA",""))) -> 2-MEDIA | AC33: =IF(E33="BAJO SS","Stock + XLIB bajo el SS: riesgo real de quiebre, adelantar producción. ","")&IF(E33="BAJO SS (XLIB CUBRE)","Disponible bajo el SS; depende de liberar "&TEXT(J33,"#,##0")&" kg"&IF(ISNUMBER(K33)," el "&TEXT(K33,"dd-mm"),"")&". ","")&IF(W33="SÍ","Stock parece sano pero "&TEXT(L33,"#,##0")&" kg no pasan filtro "&Stock_Seguridad!O33&": sin ellos queda bajo el SS para esa cadena. ","")&IF(E33="SOBRE MAX VENDIBLE","Sobrestock vs vida útil: frenar producción/activar venta. ","")&IF(N(N33)>=Parametros!$B$17,TEXT(N33,"#,##0")&" kg ya no los acepta ninguna cadena: venta intermedia/liquidación. ","")&IF(N(M33)>=Parametros!$B$17,TEXT(M33,"#,##0")&" kg a punto de salir del filtro: despachar primero (FEFO). ","")&IF(Y33="SÍ","Pedidos "&IF(N(U33)>0,"sobre","bajo")&" FCST "&TEXT(ABS(N(U33)),"0%")&": revisar forecast con KAM.","") -> Sobrestock vs vida útil: frenar producción/activar venta. 9,862 kg a punto de salir del filtro: despachar primero (FEFO).
A34: =Stock_Seguridad!A34 -> 30000398 | B34: =Stock_Seguridad!B34 -> LECHE S/LACT CHOC LONCO 30X200ML | C34: =Stock_Seguridad!C34 -> LECHES LIQUIDAS | D34: =Stock_Seguridad!F34 -> BX | E34: =Stock_Seguridad!X34 -> OK | F34: =Stock_Seguridad!W34 -> 3.4199497 | G34: =Stock_Seguridad!T34 -> 37944 | H34: =Stock_Seguridad!R34 -> 4748.256 | I34: =Stock_Seguridad!S34 -> 15843.156 | J34: =Stock_Seguridad!U34 -> 0 | L34: 156 | M34: 3048 | N34: 0 | O34: 0.088803297 | P34: =IF(ISNUMBER(Stock_Seguridad!N34),Stock_Seguridad!N34,"") -> 0.25925926 | Q34: =IF(AND(ISNUMBER(O34),ISNUMBER(P34)),P34-O34,"") -> 0.17045596 | R34: =MAX(0,G34-N(L34)) -> 37788 | S34: =SUMIFS(Cadenas_vs_FCST!$D$17:$D$652,Cadenas_vs_FCST!$A$17:$A$652,A34) -> 44634 | T34: =SUMIFS(Cadenas_vs_FCST!$E$17:$E$652,Cadenas_vs_FCST!$A$17:$A$652,A34) -> 37069.817 | U34: =IF(T34>0,S34/T34-1,"") -> 0.20405233 | V34: =IF(OR(E34="BAJO SS",E34="BAJO SS (XLIB CUBRE)"),"SÍ","") | W34: =IF(AND(V34="",N(L34)>=Parametros!$B$17,G34>=H34,R34<H34),"SÍ","") | X34: =IF(OR(E34="SOBRE MAX VENDIBLE",N(N34)>=Parametros!$B$17,N(M34)>=Parametros!$B$17),"SÍ","") -> SÍ | Y34: =IF(AND(ISNUMBER(U34),MAX(S34,T34)>=Parametros!$B$15,ABS(N(U34))>Parametros!$B$14),"SÍ","") -> SÍ | Z34: =COUNTIF(V34:Y34,"SÍ") -> 2 | AA34: =(3*(V34="SÍ")+2*(W34="SÍ")+2*(X34="SÍ")+(Y34="SÍ"))*IF(LEFT(D34,1)="A",3,IF(OR(LEFT(D34,1)="B",D34="SIN HIST"),2,1)) -> 6 | AB34: =IF(AA34>=9,"1-ALTA",IF(AA34>=4,"2-MEDIA",IF(AA34>0,"3-BAJA",""))) -> 2-MEDIA | AC34: =IF(E34="BAJO SS","Stock + XLIB bajo el SS: riesgo real de quiebre, adelantar producción. ","")&IF(E34="BAJO SS (XLIB CUBRE)","Disponible bajo el SS; depende de liberar "&TEXT(J34,"#,##0")&" kg"&IF(ISNUMBER(K34)," el "&TEXT(K34,"dd-mm"),"")&". ","")&IF(W34="SÍ","Stock parece sano pero "&TEXT(L34,"#,##0")&" kg no pasan filtro "&Stock_Seguridad!O34&": sin ellos queda bajo el SS para esa cadena. ","")&IF(E34="SOBRE MAX VENDIBLE","Sobrestock vs vida útil: frenar producción/activar venta. ","")&IF(N(N34)>=Parametros!$B$17,TEXT(N34,"#,##0")&" kg ya no los acepta ninguna cadena: venta intermedia/liquidación. ","")&IF(N(M34)>=Parametros!$B$17,TEXT(M34,"#,##0")&" kg a punto de salir del filtro: despachar primero (FEFO). ","")&IF(Y34="SÍ","Pedidos "&IF(N(U34)>0,"sobre","bajo")&" FCST "&TEXT(ABS(N(U34)),"0%")&": revisar forecast con KAM.","") -> 3,048 kg a punto de salir del filtro: despachar primero (FEFO). Pedidos sobre FCST 20%: revisar forecast con KAM.
A35: =Stock_Seguridad!A35 -> 30000207 | B35: =Stock_Seguridad!B35 -> NECTAR WATTS PIÑA LIGHT 30X200ML | C35: =Stock_Seguridad!C35 -> JUGOS Y NECTARES | D35: =Stock_Seguridad!F35 -> BX | E35: =Stock_Seguridad!X35 -> OK | F35: =Stock_Seguridad!W35 -> 6.8577207 | G35: =Stock_Seguridad!T35 -> 28002 | H35: =Stock_Seguridad!R35 -> 3067.21 | I35: =Stock_Seguridad!S35 -> 14044.91 | J35: =Stock_Seguridad!U35 -> 47280 | K35: 46318 | L35: 168 | M35: 0 | N35: 0 | O35: 0.047965061 | P35: =IF(ISNUMBER(Stock_Seguridad!N35),Stock_Seguridad!N35,"") -> 0.31636364 | Q35: =IF(AND(ISNUMBER(O35),ISNUMBER(P35)),P35-O35,"") -> 0.26839858 | R35: =MAX(0,G35-N(L35)) -> 27834 | S35: =SUMIFS(Cadenas_vs_FCST!$D$17:$D$652,Cadenas_vs_FCST!$A$17:$A$652,A35) -> 35460 | T35: =SUMIFS(Cadenas_vs_FCST!$E$17:$E$652,Cadenas_vs_FCST!$A$17:$A$652,A35) -> 38111.748 | U35: =IF(T35>0,S35/T35-1,"") -> -0.06957823 | V35: =IF(OR(E35="BAJO SS",E35="BAJO SS (XLIB CUBRE)"),"SÍ","") | W35: =IF(AND(V35="",N(L35)>=Parametros!$B$17,G35>=H35,R35<H35),"SÍ","") | X35: =IF(OR(E35="SOBRE MAX VENDIBLE",N(N35)>=Parametros!$B$17,N(M35)>=Parametros!$B$17),"SÍ","") | Y35: =IF(AND(ISNUMBER(U35),MAX(S35,T35)>=Parametros!$B$15,ABS(N(U35))>Parametros!$B$14),"SÍ","") | Z35: =COUNTIF(V35:Y35,"SÍ") -> 0 | AA35: =(3*(V35="SÍ")+2*(W35="SÍ")+2*(X35="SÍ")+(Y35="SÍ"))*IF(LEFT(D35,1)="A",3,IF(OR(LEFT(D35,1)="B",D35="SIN HIST"),2,1)) -> 0 | AB35: =IF(AA35>=9,"1-ALTA",IF(AA35>=4,"2-MEDIA",IF(AA35>0,"3-BAJA",""))) | AC35: =IF(E35="BAJO SS","Stock + XLIB bajo el SS: riesgo real de quiebre, adelantar producción. ","")&IF(E35="BAJO SS (XLIB CUBRE)","Disponible bajo el SS; depende de liberar "&TEXT(J35,"#,##0")&" kg"&IF(ISNUMBER(K35)," el "&TEXT(K35,"dd-mm"),"")&". ","")&IF(W35="SÍ","Stock parece sano pero "&TEXT(L35,"#,##0")&" kg no pasan filtro "&Stock_Seguridad!O35&": sin ellos queda bajo el SS para esa cadena. ","")&IF(E35="SOBRE MAX VENDIBLE","Sobrestock vs vida útil: frenar producción/activar venta. ","")&IF(N(N35)>=Parametros!$B$17,TEXT(N35,"#,##0")&" kg ya no los acepta ninguna cadena: venta intermedia/liquidación. ","")&IF(N(M35)>=Parametros!$B$17,TEXT(M35,"#,##0")&" kg a punto de salir del filtro: despachar primero (FEFO). ","")&IF(Y35="SÍ","Pedidos "&IF(N(U35)>0,"sobre","bajo")&" FCST "&TEXT(ABS(N(U35)),"0%")&": revisar forecast con KAM.","")
A36: =Stock_Seguridad!A36 -> 30000300 | B36: =Stock_Seguridad!B36 -> LECHE PLATANO LONCO 30X200ML | C36: =Stock_Seguridad!C36 -> LECHES LIQUIDAS | D36: =Stock_Seguridad!F36 -> BX | E36: =Stock_Seguridad!X36 -> OK | F36: =Stock_Seguridad!W36 -> 3.4253562 | G36: =Stock_Seguridad!T36 -> 35796 | H36: =Stock_Seguridad!R36 -> 6546.6814 | I36: =Stock_Seguridad!S36 -> 16996.981 | J36: =Stock_Seguridad!U36 -> 0 | L36: 330 | M36: 0 | N36: 330 | O36: 0.091034888 | P36: =IF(ISNUMBER(Stock_Seguridad!N36),Stock_Seguridad!N36,"") -> 0.31775701 | Q36: =IF(AND(ISNUMBER(O36),ISNUMBER(P36)),P36-O36,"") -> 0.22672212 | R36: =MAX(0,G36-N(L36)) -> 35466 | S36: =SUMIFS(Cadenas_vs_FCST!$D$17:$D$652,Cadenas_vs_FCST!$A$17:$A$652,A36) -> 41532 | T36: =SUMIFS(Cadenas_vs_FCST!$E$17:$E$652,Cadenas_vs_FCST!$A$17:$A$652,A36) -> 38984.6 | U36: =IF(T36>0,S36/T36-1,"") -> 0.06534376 | V36: =IF(OR(E36="BAJO SS",E36="BAJO SS (XLIB CUBRE)"),"SÍ","") | W36: =IF(AND(V36="",N(L36)>=Parametros!$B$17,G36>=H36,R36<H36),"SÍ","") | X36: =IF(OR(E36="SOBRE MAX VENDIBLE",N(N36)>=Parametros!$B$17,N(M36)>=Parametros!$B$17),"SÍ","") | Y36: =IF(AND(ISNUMBER(U36),MAX(S36,T36)>=Parametros!$B$15,ABS(N(U36))>Parametros!$B$14),"SÍ","") | Z36: =COUNTIF(V36:Y36,"SÍ") -> 0 | AA36: =(3*(V36="SÍ")+2*(W36="SÍ")+2*(X36="SÍ")+(Y36="SÍ"))*IF(LEFT(D36,1)="A",3,IF(OR(LEFT(D36,1)="B",D36="SIN HIST"),2,1)) -> 0 | AB36: =IF(AA36>=9,"1-ALTA",IF(AA36>=4,"2-MEDIA",IF(AA36>0,"3-BAJA",""))) | AC36: =IF(E36="BAJO SS","Stock + XLIB bajo el SS: riesgo real de quiebre, adelantar producción. ","")&IF(E36="BAJO SS (XLIB CUBRE)","Disponible bajo el SS; depende de liberar "&TEXT(J36,"#,##0")&" kg"&IF(ISNUMBER(K36)," el "&TEXT(K36,"dd-mm"),"")&". ","")&IF(W36="SÍ","Stock parece sano pero "&TEXT(L36,"#,##0")&" kg no pasan filtro "&Stock_Seguridad!O36&": sin ellos queda bajo el SS para esa cadena. ","")&IF(E36="SOBRE MAX VENDIBLE","Sobrestock vs vida útil: frenar producción/activar venta. ","")&IF(N(N36)>=Parametros!$B$17,TEXT(N36,"#,##0")&" kg ya no los acepta ninguna cadena: venta intermedia/liquidación. ","")&IF(N(M36)>=Parametros!$B$17,TEXT(M36,"#,##0")&" kg a punto de salir del filtro: despachar primero (FEFO). ","")&IF(Y36="SÍ","Pedidos "&IF(N(U36)>0,"sobre","bajo")&" FCST "&TEXT(ABS(N(U36)),"0%")&": revisar forecast con KAM.","")
A37: =Stock_Seguridad!A37 -> 30000010 | B37: =Stock_Seguridad!B37 -> LECHE MOMENTS CAPUCHINO 12X1LT | C37: =Stock_Seguridad!C37 -> LECHES LIQUIDAS | D37: =Stock_Seguridad!F37 -> BX | E37: =Stock_Seguridad!X37 -> OK | F37: =Stock_Seguridad!W37 -> 4.6991862 | G37: =Stock_Seguridad!T37 -> 25092 | H37: =Stock_Seguridad!R37 -> 5046.0094 | I37: =Stock_Seguridad!S37 -> 15306.509 | J37: =Stock_Seguridad!U37 -> 23124 | K37: 46318 | L37: 132 | M37: 9156 | N37: 120 | O37: 0.10662102 | P37: =IF(ISNUMBER(Stock_Seguridad!N37),Stock_Seguridad!N37,"") -> 0.24064171 | Q37: =IF(AND(ISNUMBER(O37),ISNUMBER(P37)),P37-O37,"") -> 0.1340207 | R37: =MAX(0,G37-N(L37)) -> 24960 | S37: =SUMIFS(Cadenas_vs_FCST!$D$17:$D$652,Cadenas_vs_FCST!$A$17:$A$652,A37) -> 25560 | T37: =SUMIFS(Cadenas_vs_FCST!$E$17:$E$652,Cadenas_vs_FCST!$A$17:$A$652,A37) -> 31368.737 | U37: =IF(T37>0,S37/T37-1,"") -> -0.185176 | V37: =IF(OR(E37="BAJO SS",E37="BAJO SS (XLIB CUBRE)"),"SÍ","") | W37: =IF(AND(V37="",N(L37)>=Parametros!$B$17,G37>=H37,R37<H37),"SÍ","") | X37: =IF(OR(E37="SOBRE MAX VENDIBLE",N(N37)>=Parametros!$B$17,N(M37)>=Parametros!$B$17),"SÍ","") -> SÍ | Y37: =IF(AND(ISNUMBER(U37),MAX(S37,T37)>=Parametros!$B$15,ABS(N(U37))>Parametros!$B$14),"SÍ","") | Z37: =COUNTIF(V37:Y37,"SÍ") -> 1 | AA37: =(3*(V37="SÍ")+2*(W37="SÍ")+2*(X37="SÍ")+(Y37="SÍ"))*IF(LEFT(D37,1)="A",3,IF(OR(LEFT(D37,1)="B",D37="SIN HIST"),2,1)) -> 4 | AB37: =IF(AA37>=9,"1-ALTA",IF(AA37>=4,"2-MEDIA",IF(AA37>0,"3-BAJA",""))) -> 2-MEDIA | AC37: =IF(E37="BAJO SS","Stock + XLIB bajo el SS: riesgo real de quiebre, adelantar producción. ","")&IF(E37="BAJO SS (XLIB CUBRE)","Disponible bajo el SS; depende de liberar "&TEXT(J37,"#,##0")&" kg"&IF(ISNUMBER(K37)," el "&TEXT(K37,"dd-mm"),"")&". ","")&IF(W37="SÍ","Stock parece sano pero "&TEXT(L37,"#,##0")&" kg no pasan filtro "&Stock_Seguridad!O37&": sin ellos queda bajo el SS para esa cadena. ","")&IF(E37="SOBRE MAX VENDIBLE","Sobrestock vs vida útil: frenar producción/activar venta. ","")&IF(N(N37)>=Parametros!$B$17,TEXT(N37,"#,##0")&" kg ya no los acepta ninguna cadena: venta intermedia/liquidación. ","")&IF(N(M37)>=Parametros!$B$17,TEXT(M37,"#,##0")&" kg a punto de salir del filtro: despachar primero (FEFO). ","")&IF(Y37="SÍ","Pedidos "&IF(N(U37)>0,"sobre","bajo")&" FCST "&TEXT(ABS(N(U37)),"0%")&": revisar forecast con KAM.","") -> 9,156 kg a punto de salir del filtro: despachar primero (FEFO).
A38: =Stock_Seguridad!A38 -> 30001977 | B38: =Stock_Seguridad!B38 -> BEBIDA LONCOLECHE VEGETAL ALMENDRA 6X1LT | C38: =Stock_Seguridad!C38 -> LECHES LIQUIDAS | D38: =Stock_Seguridad!F38 -> BX | E38: =Stock_Seguridad!X38 -> OK | F38: =Stock_Seguridad!W38 -> 5.9085053 | G38: =Stock_Seguridad!T38 -> 59166 | H38: =Stock_Seguridad!R38 -> 9465.8524 | I38: =Stock_Seguridad!S38 -> 19479.552 | J38: =Stock_Seguridad!U38 -> 0 | L38: 0 | M38: 0 | N38: 0 | O38: 0.28328631 | P38: =IF(ISNUMBER(Stock_Seguridad!N38),Stock_Seguridad!N38,"") -> 0.49863014 | Q38: =IF(AND(ISNUMBER(O38),ISNUMBER(P38)),P38-O38,"") -> 0.21534383 | R38: =MAX(0,G38-N(L38)) -> 59166 | S38: =SUMIFS(Cadenas_vs_FCST!$D$17:$D$652,Cadenas_vs_FCST!$A$17:$A$652,A38) -> 44766 | T38: =SUMIFS(Cadenas_vs_FCST!$E$17:$E$652,Cadenas_vs_FCST!$A$17:$A$652,A38) -> 41863.895 | U38: =IF(T38>0,S38/T38-1,"") -> 0.069322375 | V38: =IF(OR(E38="BAJO SS",E38="BAJO SS (XLIB CUBRE)"),"SÍ","") | W38: =IF(AND(V38="",N(L38)>=Parametros!$B$17,G38>=H38,R38<H38),"SÍ","") | X38: =IF(OR(E38="SOBRE MAX VENDIBLE",N(N38)>=Parametros!$B$17,N(M38)>=Parametros!$B$17),"SÍ","") | Y38: =IF(AND(ISNUMBER(U38),MAX(S38,T38)>=Parametros!$B$15,ABS(N(U38))>Parametros!$B$14),"SÍ","") | Z38: =COUNTIF(V38:Y38,"SÍ") -> 0 | AA38: =(3*(V38="SÍ")+2*(W38="SÍ")+2*(X38="SÍ")+(Y38="SÍ"))*IF(LEFT(D38,1)="A",3,IF(OR(LEFT(D38,1)="B",D38="SIN HIST"),2,1)) -> 0 | AB38: =IF(AA38>=9,"1-ALTA",IF(AA38>=4,"2-MEDIA",IF(AA38>0,"3-BAJA",""))) | AC38: =IF(E38="BAJO SS","Stock + XLIB bajo el SS: riesgo real de quiebre, adelantar producción. ","")&IF(E38="BAJO SS (XLIB CUBRE)","Disponible bajo el SS; depende de liberar "&TEXT(J38,"#,##0")&" kg"&IF(ISNUMBER(K38)," el "&TEXT(K38,"dd-mm"),"")&". ","")&IF(W38="SÍ","Stock parece sano pero "&TEXT(L38,"#,##0")&" kg no pasan filtro "&Stock_Seguridad!O38&": sin ellos queda bajo el SS para esa cadena. ","")&IF(E38="SOBRE MAX VENDIBLE","Sobrestock vs vida útil: frenar producción/activar venta. ","")&IF(N(N38)>=Parametros!$B$17,TEXT(N38,"#,##0")&" kg ya no los acepta ninguna cadena: venta intermedia/liquidación. ","")&IF(N(M38)>=Parametros!$B$17,TEXT(M38,"#,##0")&" kg a punto de salir del filtro: despachar primero (FEFO). ","")&IF(Y38="SÍ","Pedidos "&IF(N(U38)>0,"sobre","bajo")&" FCST "&TEXT(ABS(N(U38)),"0%")&": revisar forecast con KAM.","")
A39: =Stock_Seguridad!A39 -> 30000318 | B39: =Stock_Seguridad!B39 -> YOGU YOGU CHIRIMOYA 30X200GR | C39: =Stock_Seguridad!C39 -> LECHES LIQUIDAS | D39: =Stock_Seguridad!F39 -> BX | E39: =Stock_Seguridad!X39 -> OK | F39: =Stock_Seguridad!W39 -> 2.6438283 | G39: =Stock_Seguridad!T39 -> 23832 | H39: =Stock_Seguridad!R39 -> 4541.4744 | I39: =Stock_Seguridad!S39 -> 13882.474 | J39: =Stock_Seguridad!U39 -> 864 | K39: 46320 | L39: 258 | M39: 3138 | N39: 0 | O39: 0.091526224 | P39: =IF(ISNUMBER(Stock_Seguridad!N39),Stock_Seguridad!N39,"") -> 0.22040816 | Q39: =IF(AND(ISNUMBER(O39),ISNUMBER(P39)),P39-O39,"") -> 0.12888194 | R39: =MAX(0,G39-N(L39)) -> 23574 | S39: =SUMIFS(Cadenas_vs_FCST!$D$17:$D$652,Cadenas_vs_FCST!$A$17:$A$652,A39) -> 39282 | T39: =SUMIFS(Cadenas_vs_FCST!$E$17:$E$652,Cadenas_vs_FCST!$A$17:$A$652,A39) -> 39013.784 | U39: =IF(T39>0,S39/T39-1,"") -> 0.0068748986 | V39: =IF(OR(E39="BAJO SS",E39="BAJO SS (XLIB CUBRE)"),"SÍ","") | W39: =IF(AND(V39="",N(L39)>=Parametros!$B$17,G39>=H39,R39<H39),"SÍ","") | X39: =IF(OR(E39="SOBRE MAX VENDIBLE",N(N39)>=Parametros!$B$17,N(M39)>=Parametros!$B$17),"SÍ","") -> SÍ | Y39: =IF(AND(ISNUMBER(U39),MAX(S39,T39)>=Parametros!$B$15,ABS(N(U39))>Parametros!$B$14),"SÍ","") | Z39: =COUNTIF(V39:Y39,"SÍ") -> 1 | AA39: =(3*(V39="SÍ")+2*(W39="SÍ")+2*(X39="SÍ")+(Y39="SÍ"))*IF(LEFT(D39,1)="A",3,IF(OR(LEFT(D39,1)="B",D39="SIN HIST"),2,1)) -> 4 | AB39: =IF(AA39>=9,"1-ALTA",IF(AA39>=4,"2-MEDIA",IF(AA39>0,"3-BAJA",""))) -> 2-MEDIA | AC39: =IF(E39="BAJO SS","Stock + XLIB bajo el SS: riesgo real de quiebre, adelantar producción. ","")&IF(E39="BAJO SS (XLIB CUBRE)","Disponible bajo el SS; depende de liberar "&TEXT(J39,"#,##0")&" kg"&IF(ISNUMBER(K39)," el "&TEXT(K39,"dd-mm"),"")&". ","")&IF(W39="SÍ","Stock parece sano pero "&TEXT(L39,"#,##0")&" kg no pasan filtro "&Stock_Seguridad!O39&": sin ellos queda bajo el SS para esa cadena. ","")&IF(E39="SOBRE MAX VENDIBLE","Sobrestock vs vida útil: frenar producción/activar venta. ","")&IF(N(N39)>=Parametros!$B$17,TEXT(N39,"#,##0")&" kg ya no los acepta ninguna cadena: venta intermedia/liquidación. ","")&IF(N(M39)>=Parametros!$B$17,TEXT(M39,"#,##0")&" kg a punto de salir del filtro: despachar primero (FEFO). ","")&IF(Y39="SÍ","Pedidos "&IF(N(U39)>0,"sobre","bajo")&" FCST "&TEXT(ABS(N(U39)),"0%")&": revisar forecast con KAM.","") -> 3,138 kg a punto de salir del filtro: despachar primero (FEFO).
A40: =Stock_Seguridad!A40 -> 30002078 | B40: =Stock_Seguridad!B40 -> LECHE PLATANO LONCOLECHE 12X1LT | C40: =Stock_Seguridad!C40 -> LECHES LIQUIDAS | D40: =Stock_Seguridad!F40 -> BX | E40: =Stock_Seguridad!X40 -> BAJO P.REORDEN | F40: =Stock_Seguridad!W40 -> 1.3088197 | G40: =Stock_Seguridad!T40 -> 12216 | H40: =Stock_Seguridad!R40 -> 5513.9172 | I40: =Stock_Seguridad!S40 -> 14847.517 | J40: =Stock_Seguridad!U40 -> 0 | L40: 120 | M40: 12096 | N40: 0 | O40: 0.22068762 | P40: =IF(ISNUMBER(Stock_Seguridad!N40),Stock_Seguridad!N40,"") -> 0.23831776 | Q40: =IF(AND(ISNUMBER(O40),ISNUMBER(P40)),P40-O40,"") -> 0.017630134 | R40: =MAX(0,G40-N(L40)) -> 12096 | S40: =SUMIFS(Cadenas_vs_FCST!$D$17:$D$652,Cadenas_vs_FCST!$A$17:$A$652,A40) -> 29100 | T40: =SUMIFS(Cadenas_vs_FCST!$E$17:$E$652,Cadenas_vs_FCST!$A$17:$A$652,A40) -> 27697.853 | U40: =IF(T40>0,S40/T40-1,"") -> 0.050622951 | V40: =IF(OR(E40="BAJO SS",E40="BAJO SS (XLIB CUBRE)"),"SÍ","") | W40: =IF(AND(V40="",N(L40)>=Parametros!$B$17,G40>=H40,R40<H40),"SÍ","") | X40: =IF(OR(E40="SOBRE MAX VENDIBLE",N(N40)>=Parametros!$B$17,N(M40)>=Parametros!$B$17),"SÍ","") -> SÍ | Y40: =IF(AND(ISNUMBER(U40),MAX(S40,T40)>=Parametros!$B$15,ABS(N(U40))>Parametros!$B$14),"SÍ","") | Z40: =COUNTIF(V40:Y40,"SÍ") -> 1 | AA40: =(3*(V40="SÍ")+2*(W40="SÍ")+2*(X40="SÍ")+(Y40="SÍ"))*IF(LEFT(D40,1)="A",3,IF(OR(LEFT(D40,1)="B",D40="SIN HIST"),2,1)) -> 4 | AB40: =IF(AA40>=9,"1-ALTA",IF(AA40>=4,"2-MEDIA",IF(AA40>0,"3-BAJA",""))) -> 2-MEDIA | AC40: =IF(E40="BAJO SS","Stock + XLIB bajo el SS: riesgo real de quiebre, adelantar producción. ","")&IF(E40="BAJO SS (XLIB CUBRE)","Disponible bajo el SS; depende de liberar "&TEXT(J40,"#,##0")&" kg"&IF(ISNUMBER(K40)," el "&TEXT(K40,"dd-mm"),"")&". ","")&IF(W40="SÍ","Stock parece sano pero "&TEXT(L40,"#,##0")&" kg no pasan filtro "&Stock_Seguridad!O40&": sin ellos queda bajo el SS para esa cadena. ","")&IF(E40="SOBRE MAX VENDIBLE","Sobrestock vs vida útil: frenar producción/activar venta. ","")&IF(N(N40)>=Parametros!$B$17,TEXT(N40,"#,##0")&" kg ya no los acepta ninguna cadena: venta intermedia/liquidación. ","")&IF(N(M40)>=Parametros!$B$17,TEXT(M40,"#,##0")&" kg a punto de salir del filtro: despachar primero (FEFO). ","")&IF(Y40="SÍ","Pedidos "&IF(N(U40)>0,"sobre","bajo")&" FCST "&TEXT(ABS(N(U40)),"0%")&": revisar forecast con KAM.","") -> 12,096 kg a punto de salir del filtro: despachar primero (FEFO).
A41: =Stock_Seguridad!A41 -> 30000347 | B41: =Stock_Seguridad!B41 -> CREMA LISTA LONCO 30X200ML | C41: =Stock_Seguridad!C41 -> CREMA | D41: =Stock_Seguridad!F41 -> BX | E41: =Stock_Seguridad!X41 -> OK | F41: =Stock_Seguridad!W41 -> 4.5839018 | G41: =Stock_Seguridad!T41 -> 42000 | H41: =Stock_Seguridad!R41 -> 4967.0069 | I41: =Stock_Seguridad!S41 -> 14129.507 | J41: =Stock_Seguridad!U41 -> 0 | L41: 462 | M41: 8526 | N41: 0 | O41: 0.12258936 | P41: =IF(ISNUMBER(Stock_Seguridad!N41),Stock_Seguridad!N41,"") -> 0.23913043 | Q41: =IF(AND(ISNUMBER(O41),ISNUMBER(P41)),P41-O41,"") -> 0.11654107 | R41: =MAX(0,G41-N(L41)) -> 41538 | S41: =SUMIFS(Cadenas_vs_FCST!$D$17:$D$652,Cadenas_vs_FCST!$A$17:$A$652,A41) -> 29688 | T41: =SUMIFS(Cadenas_vs_FCST!$E$17:$E$652,Cadenas_vs_FCST!$A$17:$A$652,A41) -> 34209.244 | U41: =IF(T41>0,S41/T41-1,"") -> -0.13216439 | V41: =IF(OR(E41="BAJO SS",E41="BAJO SS (XLIB CUBRE)"),"SÍ","") | W41: =IF(AND(V41="",N(L41)>=Parametros!$B$17,G41>=H41,R41<H41),"SÍ","") | X41: =IF(OR(E41="SOBRE MAX VENDIBLE",N(N41)>=Parametros!$B$17,N(M41)>=Parametros!$B$17),"SÍ","") -> SÍ | Y41: =IF(AND(ISNUMBER(U41),MAX(S41,T41)>=Parametros!$B$15,ABS(N(U41))>Parametros!$B$14),"SÍ","") | Z41: =COUNTIF(V41:Y41,"SÍ") -> 1 | AA41: =(3*(V41="SÍ")+2*(W41="SÍ")+2*(X41="SÍ")+(Y41="SÍ"))*IF(LEFT(D41,1)="A",3,IF(OR(LEFT(D41,1)="B",D41="SIN HIST"),2,1)) -> 4 | AB41: =IF(AA41>=9,"1-ALTA",IF(AA41>=4,"2-MEDIA",IF(AA41>0,"3-BAJA",""))) -> 2-MEDIA | AC41: =IF(E41="BAJO SS","Stock + XLIB bajo el SS: riesgo real de quiebre, adelantar producción. ","")&IF(E41="BAJO SS (XLIB CUBRE)","Disponible bajo el SS; depende de liberar "&TEXT(J41,"#,##0")&" kg"&IF(ISNUMBER(K41)," el "&TEXT(K41,"dd-mm"),"")&". ","")&IF(W41="SÍ","Stock parece sano pero "&TEXT(L41,"#,##0")&" kg no pasan filtro "&Stock_Seguridad!O41&": sin ellos queda bajo el SS para esa cadena. ","")&IF(E41="SOBRE MAX VENDIBLE","Sobrestock vs vida útil: frenar producción/activar venta. ","")&IF(N(N41)>=Parametros!$B$17,TEXT(N41,"#,##0")&" kg ya no los acepta ninguna cadena: venta intermedia/liquidación. ","")&IF(N(M41)>=Parametros!$B$17,TEXT(M41,"#,##0")&" kg a punto de salir del filtro: despachar primero (FEFO). ","")&IF(Y41="SÍ","Pedidos "&IF(N(U41)>0,"sobre","bajo")&" FCST "&TEXT(ABS(N(U41)),"0%")&": revisar forecast con KAM.","") -> 8,526 kg a punto de salir del filtro: despachar primero (FEFO).
A42: =Stock_Seguridad!A42 -> 30001404 | B42: =Stock_Seguridad!B42 -> LECHE BREAK CAPPUCCINO LONCO 18X250ML | C42: =Stock_Seguridad!C42 -> LECHES LIQUIDAS | D42: =Stock_Seguridad!F42 -> BX | E42: =Stock_Seguridad!X42 -> OK | F42: =Stock_Seguridad!W42 -> 3.6385062 | G42: =Stock_Seguridad!T42 -> 33115.5 | H42: =Stock_Seguridad!R42 -> 2645.1482 | I42: =Stock_Seguridad!S42 -> 11746.548 | J42: =Stock_Seguridad!U42 -> 0 | L42: 175.5 | M42: 4.5 | N42: 0 | O42: 0.060650075 | P42: =IF(ISNUMBER(Stock_Seguridad!N42),Stock_Seguridad!N42,"") -> 0.224 | Q42: =IF(AND(ISNUMBER(O42),ISNUMBER(P42)),P42-O42,"") -> 0.16334993 | R42: =MAX(0,G42-N(L42)) -> 32940 | S42: =SUMIFS(Cadenas_vs_FCST!$D$17:$D$652,Cadenas_vs_FCST!$A$17:$A$652,A42) -> 38754 | T42: =SUMIFS(Cadenas_vs_FCST!$E$17:$E$652,Cadenas_vs_FCST!$A$17:$A$652,A42) -> 33603.788 | U42: =IF(T42>0,S42/T42-1,"") -> 0.15326284 | V42: =IF(OR(E42="BAJO SS",E42="BAJO SS (XLIB CUBRE)"),"SÍ","") | W42: =IF(AND(V42="",N(L42)>=Parametros!$B$17,G42>=H42,R42<H42),"SÍ","") | X42: =IF(OR(E42="SOBRE MAX VENDIBLE",N(N42)>=Parametros!$B$17,N(M42)>=Parametros!$B$17),"SÍ","") | Y42: =IF(AND(ISNUMBER(U42),MAX(S42,T42)>=Parametros!$B$15,ABS(N(U42))>Parametros!$B$14),"SÍ","") | Z42: =COUNTIF(V42:Y42,"SÍ") -> 0 | AA42: =(3*(V42="SÍ")+2*(W42="SÍ")+2*(X42="SÍ")+(Y42="SÍ"))*IF(LEFT(D42,1)="A",3,IF(OR(LEFT(D42,1)="B",D42="SIN HIST"),2,1)) -> 0 | AB42: =IF(AA42>=9,"1-ALTA",IF(AA42>=4,"2-MEDIA",IF(AA42>0,"3-BAJA",""))) | AC42: =IF(E42="BAJO SS","Stock + XLIB bajo el SS: riesgo real de quiebre, adelantar producción. ","")&IF(E42="BAJO SS (XLIB CUBRE)","Disponible bajo el SS; depende de liberar "&TEXT(J42,"#,##0")&" kg"&IF(ISNUMBER(K42)," el "&TEXT(K42,"dd-mm"),"")&". ","")&IF(W42="SÍ","Stock parece sano pero "&TEXT(L42,"#,##0")&" kg no pasan filtro "&Stock_Seguridad!O42&": sin ellos queda bajo el SS para esa cadena. ","")&IF(E42="SOBRE MAX VENDIBLE","Sobrestock vs vida útil: frenar producción/activar venta. ","")&IF(N(N42)>=Parametros!$B$17,TEXT(N42,"#,##0")&" kg ya no los acepta ninguna cadena: venta intermedia/liquidación. ","")&IF(N(M42)>=Parametros!$B$17,TEXT(M42,"#,##0")&" kg a punto de salir del filtro: despachar primero (FEFO). ","")&IF(Y42="SÍ","Pedidos "&IF(N(U42)>0,"sobre","bajo")&" FCST "&TEXT(ABS(N(U42)),"0%")&": revisar forecast con KAM.","")
A43: =Stock_Seguridad!A43 -> 30000306 | B43: =Stock_Seguridad!B43 -> YOGU YOGU DAMASCO 30X200GR | C43: =Stock_Seguridad!C43 -> LECHES LIQUIDAS | D43: =Stock_Seguridad!F43 -> BX | E43: =Stock_Seguridad!X43 -> OK | F43: =Stock_Seguridad!W43 -> 4.3264933 | G43: =Stock_Seguridad!T43 -> 36012 | H43: =Stock_Seguridad!R43 -> 3624.9135 | I43: =Stock_Seguridad!S43 -> 11948.513 | J43: =Stock_Seguridad!U43 -> 0 | L43: 300 | M43: 7590 | N43: 0 | O43: 0.13094986 | P43: =IF(ISNUMBER(Stock_Seguridad!N43),Stock_Seguridad!N43,"") -> 0.22040816 | Q43: =IF(AND(ISNUMBER(O43),ISNUMBER(P43)),P43-O43,"") -> 0.0894583 | R43: =MAX(0,G43-N(L43)) -> 35712 | S43: =SUMIFS(Cadenas_vs_FCST!$D$17:$D$652,Cadenas_vs_FCST!$A$17:$A$652,A43) -> 29598 | T43: =SUMIFS(Cadenas_vs_FCST!$E$17:$E$652,Cadenas_vs_FCST!$A$17:$A$652,A43) -> 33059.326 | U43: =IF(T43>0,S43/T43-1,"") -> -0.10470044 | V43: =IF(OR(E43="BAJO SS",E43="BAJO SS (XLIB CUBRE)"),"SÍ","") | W43: =IF(AND(V43="",N(L43)>=Parametros!$B$17,G43>=H43,R43<H43),"SÍ","") | X43: =IF(OR(E43="SOBRE MAX VENDIBLE",N(N43)>=Parametros!$B$17,N(M43)>=Parametros!$B$17),"SÍ","") -> SÍ | Y43: =IF(AND(ISNUMBER(U43),MAX(S43,T43)>=Parametros!$B$15,ABS(N(U43))>Parametros!$B$14),"SÍ","") | Z43: =COUNTIF(V43:Y43,"SÍ") -> 1 | AA43: =(3*(V43="SÍ")+2*(W43="SÍ")+2*(X43="SÍ")+(Y43="SÍ"))*IF(LEFT(D43,1)="A",3,IF(OR(LEFT(D43,1)="B",D43="SIN HIST"),2,1)) -> 4 | AB43: =IF(AA43>=9,"1-ALTA",IF(AA43>=4,"2-MEDIA",IF(AA43>0,"3-BAJA",""))) -> 2-MEDIA | AC43: =IF(E43="BAJO SS","Stock + XLIB bajo el SS: riesgo real de quiebre, adelantar producción. ","")&IF(E43="BAJO SS (XLIB CUBRE)","Disponible bajo el SS; depende de liberar "&TEXT(J43,"#,##0")&" kg"&IF(ISNUMBER(K43)," el "&TEXT(K43,"dd-mm"),"")&". ","")&IF(W43="SÍ","Stock parece sano pero "&TEXT(L43,"#,##0")&" kg no pasan filtro "&Stock_Seguridad!O43&": sin ellos queda bajo el SS para esa cadena. ","")&IF(E43="SOBRE MAX VENDIBLE","Sobrestock vs vida útil: frenar producción/activar venta. ","")&IF(N(N43)>=Parametros!$B$17,TEXT(N43,"#,##0")&" kg ya no los acepta ninguna cadena: venta intermedia/liquidación. ","")&IF(N(M43)>=Parametros!$B$17,TEXT(M43,"#,##0")&" kg a punto de salir del filtro: despachar primero (FEFO). ","")&IF(Y43="SÍ","Pedidos "&IF(N(U43)>0,"sobre","bajo")&" FCST "&TEXT(ABS(N(U43)),"0%")&": revisar forecast con KAM.","") -> 7,590 kg a punto de salir del filtro: despachar primero (FEFO).
A44: =Stock_Seguridad!A44 -> 30000478 | B44: =Stock_Seguridad!B44 -> CAPPUCCINO LONCOLECHE 12X1LT | C44: =Stock_Seguridad!C44 -> LECHES LIQUIDAS | D44: =Stock_Seguridad!F44 -> BX | E44: =Stock_Seguridad!X44 -> OK | F44: =Stock_Seguridad!W44 -> 2.3081568 | G44: =Stock_Seguridad!T44 -> 18348 | H44: =Stock_Seguridad!R44 -> 2057.8802 | I44: =Stock_Seguridad!S44 -> 10007.08 | J44: =Stock_Seguridad!U44 -> 0 | L44: 240 | M44: 2616 | N44: 0 | O44: 0.10311271 | P44: =IF(ISNUMBER(Stock_Seguridad!N44),Stock_Seguridad!N44,"") -> 0.256 | Q44: =IF(AND(ISNUMBER(O44),ISNUMBER(P44)),P44-O44,"") -> 0.15288729 | R44: =MAX(0,G44-N(L44)) -> 18108 | S44: =SUMIFS(Cadenas_vs_FCST!$D$17:$D$652,Cadenas_vs_FCST!$A$17:$A$652,A44) -> 17580 | T44: =SUMIFS(Cadenas_vs_FCST!$E$17:$E$652,Cadenas_vs_FCST!$A$17:$A$652,A44) -> 17653.042 | U44: =IF(T44>0,S44/T44-1,"") -> -0.0041376561 | V44: =IF(OR(E44="BAJO SS",E44="BAJO SS (XLIB CUBRE)"),"SÍ","") | W44: =IF(AND(V44="",N(L44)>=Parametros!$B$17,G44>=H44,R44<H44),"SÍ","") | X44: =IF(OR(E44="SOBRE MAX VENDIBLE",N(N44)>=Parametros!$B$17,N(M44)>=Parametros!$B$17),"SÍ","") -> SÍ | Y44: =IF(AND(ISNUMBER(U44),MAX(S44,T44)>=Parametros!$B$15,ABS(N(U44))>Parametros!$B$14),"SÍ","") | Z44: =COUNTIF(V44:Y44,"SÍ") -> 1 | AA44: =(3*(V44="SÍ")+2*(W44="SÍ")+2*(X44="SÍ")+(Y44="SÍ"))*IF(LEFT(D44,1)="A",3,IF(OR(LEFT(D44,1)="B",D44="SIN HIST"),2,1)) -> 4 | AB44: =IF(AA44>=9,"1-ALTA",IF(AA44>=4,"2-MEDIA",IF(AA44>0,"3-BAJA",""))) -> 2-MEDIA | AC44: =IF(E44="BAJO SS","Stock + XLIB bajo el SS: riesgo real de quiebre, adelantar producción. ","")&IF(E44="BAJO SS (XLIB CUBRE)","Disponible bajo el SS; depende de liberar "&TEXT(J44,"#,##0")&" kg"&IF(ISNUMBER(K44)," el "&TEXT(K44,"dd-mm"),"")&". ","")&IF(W44="SÍ","Stock parece sano pero "&TEXT(L44,"#,##0")&" kg no pasan filtro "&Stock_Seguridad!O44&": sin ellos queda bajo el SS para esa cadena. ","")&IF(E44="SOBRE MAX VENDIBLE","Sobrestock vs vida útil: frenar producción/activar venta. ","")&IF(N(N44)>=Parametros!$B$17,TEXT(N44,"#,##0")&" kg ya no los acepta ninguna cadena: venta intermedia/liquidación. ","")&IF(N(M44)>=Parametros!$B$17,TEXT(M44,"#,##0")&" kg a punto de salir del filtro: despachar primero (FEFO). ","")&IF(Y44="SÍ","Pedidos "&IF(N(U44)>0,"sobre","bajo")&" FCST "&TEXT(ABS(N(U44)),"0%")&": revisar forecast con KAM.","") -> 2,616 kg a punto de salir del filtro: despachar primero (FEFO).
A45: =Stock_Seguridad!A45 -> 30002230 | B45: =Stock_Seguridad!B45 -> NECTAR WATTS MANZANA 5X10X115ML | C45: =Stock_Seguridad!C45 -> JUGOS Y NECTARES | D45: =Stock_Seguridad!F45 -> BY | E45: =Stock_Seguridad!X45 -> OK | F45: =Stock_Seguridad!W45 -> 11.559521 | G45: =Stock_Seguridad!T45 -> 90890.2 | H45: =Stock_Seguridad!R45 -> 8512.0482 | I45: =Stock_Seguridad!S45 -> 16374.848 | J45: =Stock_Seguridad!U45 -> 0 | L45: 626.75 | M45: 4519.5 | N45: 511.75 | O45: 0.069815904 | P45: =IF(ISNUMBER(Stock_Seguridad!N45),Stock_Seguridad!N45,"") -> 0.2739726 | Q45: =IF(AND(ISNUMBER(O45),ISNUMBER(P45)),P45-O45,"") -> 0.2041567 | R45: =MAX(0,G45-N(L45)) -> 90263.45 | S45: =SUMIFS(Cadenas_vs_FCST!$D$17:$D$652,Cadenas_vs_FCST!$A$17:$A$652,A45) -> 46115 | T45: =SUMIFS(Cadenas_vs_FCST!$E$17:$E$652,Cadenas_vs_FCST!$A$17:$A$652,A45) -> 28773.447 | U45: =IF(T45>0,S45/T45-1,"") -> 0.60269292 | V45: =IF(OR(E45="BAJO SS",E45="BAJO SS (XLIB CUBRE)"),"SÍ","") | W45: =IF(AND(V45="",N(L45)>=Parametros!$B$17,G45>=H45,R45<H45),"SÍ","") | X45: =IF(OR(E45="SOBRE MAX VENDIBLE",N(N45)>=Parametros!$B$17,N(M45)>=Parametros!$B$17),"SÍ","") -> SÍ | Y45: =IF(AND(ISNUMBER(U45),MAX(S45,T45)>=Parametros!$B$15,ABS(N(U45))>Parametros!$B$14),"SÍ","") -> SÍ | Z45: =COUNTIF(V45:Y45,"SÍ") -> 2 | AA45: =(3*(V45="SÍ")+2*(W45="SÍ")+2*(X45="SÍ")+(Y45="SÍ"))*IF(LEFT(D45,1)="A",3,IF(OR(LEFT(D45,1)="B",D45="SIN HIST"),2,1)) -> 6 | AB45: =IF(AA45>=9,"1-ALTA",IF(AA45>=4,"2-MEDIA",IF(AA45>0,"3-BAJA",""))) -> 2-MEDIA | AC45: =IF(E45="BAJO SS","Stock + XLIB bajo el SS: riesgo real de quiebre, adelantar producción. ","")&IF(E45="BAJO SS (XLIB CUBRE)","Disponible bajo el SS; depende de liberar "&TEXT(J45,"#,##0")&" kg"&IF(ISNUMBER(K45)," el "&TEXT(K45,"dd-mm"),"")&". ","")&IF(W45="SÍ","Stock parece sano pero "&TEXT(L45,"#,##0")&" kg no pasan filtro "&Stock_Seguridad!O45&": sin ellos queda bajo el SS para esa cadena. ","")&IF(E45="SOBRE MAX VENDIBLE","Sobrestock vs vida útil: frenar producción/activar venta. ","")&IF(N(N45)>=Parametros!$B$17,TEXT(N45,"#,##0")&" kg ya no los acepta ninguna cadena: venta intermedia/liquidación. ","")&IF(N(M45)>=Parametros!$B$17,TEXT(M45,"#,##0")&" kg a punto de salir del filtro: despachar primero (FEFO). ","")&IF(Y45="SÍ","Pedidos "&IF(N(U45)>0,"sobre","bajo")&" FCST "&TEXT(ABS(N(U45)),"0%")&": revisar forecast con KAM.","") -> 512 kg ya no los acepta ninguna cadena: venta intermedia/liquidación. 4,520 kg a punto de salir del filtro: despachar primero (FEFO). Pedidos sobre FCST 60%: revisar forecast con KAM.
A46: =Stock_Seguridad!A46 -> 30000354 | B46: =Stock_Seguridad!B46 -> LECHE LONCO SEMI S/LACTOSA 5X6X200ML | C46: =Stock_Seguridad!C46 -> LECHES LIQUIDAS | D46: =Stock_Seguridad!F46 -> BX | E46: =Stock_Seguridad!X46 -> OK | F46: =Stock_Seguridad!W46 -> 4.5538504 | G46: =Stock_Seguridad!T46 -> 14226 | H46: =Stock_Seguridad!R46 -> 2208.2292 | I46: =Stock_Seguridad!S46 -> 9506.2292 | J46: =Stock_Seguridad!U46 -> 19008 | K46: 46320 | L46: 0 | M46: 0 | N46: 0 | O46: 0.084326767 | P46: =IF(ISNUMBER(Stock_Seguridad!N46),Stock_Seguridad!N46,"") -> 0.27513228 | Q46: =IF(AND(ISNUMBER(O46),ISNUMBER(P46)),P46-O46,"") -> 0.19080551 | R46: =MAX(0,G46-N(L46)) -> 14226 | S46: =SUMIFS(Cadenas_vs_FCST!$D$17:$D$652,Cadenas_vs_FCST!$A$17:$A$652,A46) -> 20922 | T46: =SUMIFS(Cadenas_vs_FCST!$E$17:$E$652,Cadenas_vs_FCST!$A$17:$A$652,A46) -> 22841.34 | U46: =IF(T46>0,S46/T46-1,"") -> -0.084029215 | V46: =IF(OR(E46="BAJO SS",E46="BAJO SS (XLIB CUBRE)"),"SÍ","") | W46: =IF(AND(V46="",N(L46)>=Parametros!$B$17,G46>=H46,R46<H46),"SÍ","") | X46: =IF(OR(E46="SOBRE MAX VENDIBLE",N(N46)>=Parametros!$B$17,N(M46)>=Parametros!$B$17),"SÍ","") | Y46: =IF(AND(ISNUMBER(U46),MAX(S46,T46)>=Parametros!$B$15,ABS(N(U46))>Parametros!$B$14),"SÍ","") | Z46: =COUNTIF(V46:Y46,"SÍ") -> 0 | AA46: =(3*(V46="SÍ")+2*(W46="SÍ")+2*(X46="SÍ")+(Y46="SÍ"))*IF(LEFT(D46,1)="A",3,IF(OR(LEFT(D46,1)="B",D46="SIN HIST"),2,1)) -> 0 | AB46: =IF(AA46>=9,"1-ALTA",IF(AA46>=4,"2-MEDIA",IF(AA46>0,"3-BAJA",""))) | AC46: =IF(E46="BAJO SS","Stock + XLIB bajo el SS: riesgo real de quiebre, adelantar producción. ","")&IF(E46="BAJO SS (XLIB CUBRE)","Disponible bajo el SS; depende de liberar "&TEXT(J46,"#,##0")&" kg"&IF(ISNUMBER(K46)," el "&TEXT(K46,"dd-mm"),"")&". ","")&IF(W46="SÍ","Stock parece sano pero "&TEXT(L46,"#,##0")&" kg no pasan filtro "&Stock_Seguridad!O46&": sin ellos queda bajo el SS para esa cadena. ","")&IF(E46="SOBRE MAX VENDIBLE","Sobrestock vs vida útil: frenar producción/activar venta. ","")&IF(N(N46)>=Parametros!$B$17,TEXT(N46,"#,##0")&" kg ya no los acepta ninguna cadena: venta intermedia/liquidación. ","")&IF(N(M46)>=Parametros!$B$17,TEXT(M46,"#,##0")&" kg a punto de salir del filtro: despachar primero (FEFO). ","")&IF(Y46="SÍ","Pedidos "&IF(N(U46)>0,"sobre","bajo")&" FCST "&TEXT(ABS(N(U46)),"0%")&": revisar forecast con KAM.","")
A47: =Stock_Seguridad!A47 -> 30002272 | B47: =Stock_Seguridad!B47 -> LECHE LONCO PROTEIN DESCREMADA 30X200ML | C47: =Stock_Seguridad!C47 -> LECHES LIQUIDAS | D47: =Stock_Seguridad!F47 -> BX | E47: =Stock_Seguridad!X47 -> OK | F47: =Stock_Seguridad!W47 -> 1.7794917 | G47: =Stock_Seguridad!T47 -> 12828 | H47: =Stock_Seguridad!R47 -> 2889.4045 | I47: =Stock_Seguridad!S47 -> 10098.205 | J47: =Stock_Seguridad!U47 -> 0 | L47: 0 | M47: 0 | N47: 0 | O47: 0.10622077 | P47: =IF(ISNUMBER(Stock_Seguridad!N47),Stock_Seguridad!N47,"") | Q47: =IF(AND(ISNUMBER(O47),ISNUMBER(P47)),P47-O47,"") | R47: =MAX(0,G47-N(L47)) -> 12828 | S47: =SUMIFS(Cadenas_vs_FCST!$D$17:$D$652,Cadenas_vs_FCST!$A$17:$A$652,A47) -> 23064 | T47: =SUMIFS(Cadenas_vs_FCST!$E$17:$E$652,Cadenas_vs_FCST!$A$17:$A$652,A47) -> 19977.211 | U47: =IF(T47>0,S47/T47-1,"") -> 0.15451551 | V47: =IF(OR(E47="BAJO SS",E47="BAJO SS (XLIB CUBRE)"),"SÍ","") | W47: =IF(AND(V47="",N(L47)>=Parametros!$B$17,G47>=H47,R47<H47),"SÍ","") | X47: =IF(OR(E47="SOBRE MAX VENDIBLE",N(N47)>=Parametros!$B$17,N(M47)>=Parametros!$B$17),"SÍ","") | Y47: =IF(AND(ISNUMBER(U47),MAX(S47,T47)>=Parametros!$B$15,ABS(N(U47))>Parametros!$B$14),"SÍ","") | Z47: =COUNTIF(V47:Y47,"SÍ") -> 0 | AA47: =(3*(V47="SÍ")+2*(W47="SÍ")+2*(X47="SÍ")+(Y47="SÍ"))*IF(LEFT(D47,1)="A",3,IF(OR(LEFT(D47,1)="B",D47="SIN HIST"),2,1)) -> 0 | AB47: =IF(AA47>=9,"1-ALTA",IF(AA47>=4,"2-MEDIA",IF(AA47>0,"3-BAJA",""))) | AC47: =IF(E47="BAJO SS","Stock + XLIB bajo el SS: riesgo real de quiebre, adelantar producción. ","")&IF(E47="BAJO SS (XLIB CUBRE)","Disponible bajo el SS; depende de liberar "&TEXT(J47,"#,##0")&" kg"&IF(ISNUMBER(K47)," el "&TEXT(K47,"dd-mm"),"")&". ","")&IF(W47="SÍ","Stock parece sano pero "&TEXT(L47,"#,##0")&" kg no pasan filtro "&Stock_Seguridad!O47&": sin ellos queda bajo el SS para esa cadena. ","")&IF(E47="SOBRE MAX VENDIBLE","Sobrestock vs vida útil: frenar producción/activar venta. ","")&IF(N(N47)>=Parametros!$B$17,TEXT(N47,"#,##0")&" kg ya no los acepta ninguna cadena: venta intermedia/liquidación. ","")&IF(N(M47)>=Parametros!$B$17,TEXT(M47,"#,##0")&" kg a punto de salir del filtro: despachar primero (FEFO). ","")&IF(Y47="SÍ","Pedidos "&IF(N(U47)>0,"sobre","bajo")&" FCST "&TEXT(ABS(N(U47)),"0%")&": revisar forecast con KAM.","")
A48: =Stock_Seguridad!A48 -> 30001882 | B48: =Stock_Seguridad!B48 -> CREMA BATIR LONCO 12X500ML | C48: =Stock_Seguridad!C48 -> CREMA | D48: =Stock_Seguridad!F48 -> BX | E48: =Stock_Seguridad!X48 -> OK | F48: =Stock_Seguridad!W48 -> 2.2266889 | G48: =Stock_Seguridad!T48 -> 8196 | H48: =Stock_Seguridad!R48 -> 1920.6081 | I48: =Stock_Seguridad!S48 -> 8686.7081 | J48: =Stock_Seguridad!U48 -> 6870 | K48: 46319 | L48: 324 | M48: 6 | N48: 306 | O48: 0.058566308 | P48: =IF(ISNUMBER(Stock_Seguridad!N48),Stock_Seguridad!N48,"") -> 0.19021739 | Q48: =IF(AND(ISNUMBER(O48),ISNUMBER(P48)),P48-O48,"") -> 0.13165108 | R48: =MAX(0,G48-N(L48)) -> 7872 | S48: =SUMIFS(Cadenas_vs_FCST!$D$17:$D$652,Cadenas_vs_FCST!$A$17:$A$652,A48) -> 19260 | T48: =SUMIFS(Cadenas_vs_FCST!$E$17:$E$652,Cadenas_vs_FCST!$A$17:$A$652,A48) -> 19368.301 | U48: =IF(T48>0,S48/T48-1,"") -> -0.0055916804 | V48: =IF(OR(E48="BAJO SS",E48="BAJO SS (XLIB CUBRE)"),"SÍ","") | W48: =IF(AND(V48="",N(L48)>=Parametros!$B$17,G48>=H48,R48<H48),"SÍ","") | X48: =IF(OR(E48="SOBRE MAX VENDIBLE",N(N48)>=Parametros!$B$17,N(M48)>=Parametros!$B$17),"SÍ","") | Y48: =IF(AND(ISNUMBER(U48),MAX(S48,T48)>=Parametros!$B$15,ABS(N(U48))>Parametros!$B$14),"SÍ","") | Z48: =COUNTIF(V48:Y48,"SÍ") -> 0 | AA48: =(3*(V48="SÍ")+2*(W48="SÍ")+2*(X48="SÍ")+(Y48="SÍ"))*IF(LEFT(D48,1)="A",3,IF(OR(LEFT(D48,1)="B",D48="SIN HIST"),2,1)) -> 0 | AB48: =IF(AA48>=9,"1-ALTA",IF(AA48>=4,"2-MEDIA",IF(AA48>0,"3-BAJA",""))) | AC48: =IF(E48="BAJO SS","Stock + XLIB bajo el SS: riesgo real de quiebre, adelantar producción. ","")&IF(E48="BAJO SS (XLIB CUBRE)","Disponible bajo el SS; depende de liberar "&TEXT(J48,"#,##0")&" kg"&IF(ISNUMBER(K48)," el "&TEXT(K48,"dd-mm"),"")&". ","")&IF(W48="SÍ","Stock parece sano pero "&TEXT(L48,"#,##0")&" kg no pasan filtro "&Stock_Seguridad!O48&": sin ellos queda bajo el SS para esa cadena. ","")&IF(E48="SOBRE MAX VENDIBLE","Sobrestock vs vida útil: frenar producción/activar venta. ","")&IF(N(N48)>=Parametros!$B$17,TEXT(N48,"#,##0")&" kg ya no los acepta ninguna cadena: venta intermedia/liquidación. ","")&IF(N(M48)>=Parametros!$B$17,TEXT(M48,"#,##0")&" kg a punto de salir del filtro: despachar primero (FEFO). ","")&IF(Y48="SÍ","Pedidos "&IF(N(U48)>0,"sobre","bajo")&" FCST "&TEXT(ABS(N(U48)),"0%")&": revisar forecast con KAM.","")
A49: =Stock_Seguridad!A49 -> 30001423 | B49: =Stock_Seguridad!B49 -> LECHE FULL LONCO PROTEIN VLLA 18X250ML | C49: =Stock_Seguridad!C49 -> LECHES LIQUIDAS | D49: =Stock_Seguridad!F49 -> BX | E49: =Stock_Seguridad!X49 -> OK | F49: =Stock_Seguridad!W49 -> 3.2943957 | G49: =Stock_Seguridad!T49 -> 21744 | H49: =Stock_Seguridad!R49 -> 3168.0967 | I49: =Stock_Seguridad!S49 -> 9768.3967 | J49: =Stock_Seguridad!U49 -> 0 | L49: 4.5 | M49: 0 | N49: 0 | O49: 0.094837373 | P49: =IF(ISNUMBER(Stock_Seguridad!N49),Stock_Seguridad!N49,"") -> 0.21164021 | Q49: =IF(AND(ISNUMBER(O49),ISNUMBER(P49)),P49-O49,"") -> 0.11680284 | R49: =MAX(0,G49-N(L49)) -> 21739.5 | S49: =SUMIFS(Cadenas_vs_FCST!$D$17:$D$652,Cadenas_vs_FCST!$A$17:$A$652,A49) -> 26752.5 | T49: =SUMIFS(Cadenas_vs_FCST!$E$17:$E$652,Cadenas_vs_FCST!$A$17:$A$652,A49) -> 28525.632 | U49: =IF(T49>0,S49/T49-1,"") -> -0.062159242 | V49: =IF(OR(E49="BAJO SS",E49="BAJO SS (XLIB CUBRE)"),"SÍ","") | W49: =IF(AND(V49="",N(L49)>=Parametros!$B$17,G49>=H49,R49<H49),"SÍ","") | X49: =IF(OR(E49="SOBRE MAX VENDIBLE",N(N49)>=Parametros!$B$17,N(M49)>=Parametros!$B$17),"SÍ","") | Y49: =IF(AND(ISNUMBER(U49),MAX(S49,T49)>=Parametros!$B$15,ABS(N(U49))>Parametros!$B$14),"SÍ","") | Z49: =COUNTIF(V49:Y49,"SÍ") -> 0 | AA49: =(3*(V49="SÍ")+2*(W49="SÍ")+2*(X49="SÍ")+(Y49="SÍ"))*IF(LEFT(D49,1)="A",3,IF(OR(LEFT(D49,1)="B",D49="SIN HIST"),2,1)) -> 0 | AB49: =IF(AA49>=9,"1-ALTA",IF(AA49>=4,"2-MEDIA",IF(AA49>0,"3-BAJA",""))) | AC49: =IF(E49="BAJO SS","Stock + XLIB bajo el SS: riesgo real de quiebre, adelantar producción. ","")&IF(E49="BAJO SS (XLIB CUBRE)","Disponible bajo el SS; depende de liberar "&TEXT(J49,"#,##0")&" kg"&IF(ISNUMBER(K49)," el "&TEXT(K49,"dd-mm"),"")&". ","")&IF(W49="SÍ","Stock parece sano pero "&TEXT(L49,"#,##0")&" kg no pasan filtro "&Stock_Seguridad!O49&": sin ellos queda bajo el SS para esa cadena. ","")&IF(E49="SOBRE MAX VENDIBLE","Sobrestock vs vida útil: frenar producción/activar venta. ","")&IF(N(N49)>=Parametros!$B$17,TEXT(N49,"#,##0")&" kg ya no los acepta ninguna cadena: venta intermedia/liquidación. ","")&IF(N(M49)>=Parametros!$B$17,TEXT(M49,"#,##0")&" kg a punto de salir del filtro: despachar primero (FEFO). ","")&IF(Y49="SÍ","Pedidos "&IF(N(U49)>0,"sobre","bajo")&" FCST "&TEXT(ABS(N(U49)),"0%")&": revisar forecast con KAM.","")
A50: =Stock_Seguridad!A50 -> 30001574 | B50: =Stock_Seguridad!B50 -> YOGU YOGU ORIGINAL MORA LV 12x1LT | C50: =Stock_Seguridad!C50 -> LECHES LIQUIDAS | D50: =Stock_Seguridad!F50 -> BX | E50: =Stock_Seguridad!X50 -> OK | F50: =Stock_Seguridad!W50 -> 2.5781141 | G50: =Stock_Seguridad!T50 -> 16560 | H50: =Stock_Seguridad!R50 -> 3745.5561 | I50: =Stock_Seguridad!S50 -> 10168.856 | J50: =Stock_Seguridad!U50 -> 0 | L50: 0 | M50: 4188 | N50: 0 | O50: 0.14787945 | P50: =IF(ISNUMBER(Stock_Seguridad!N50),Stock_Seguridad!N50,"") -> 0.27346939 | Q50: =IF(AND(ISNUMBER(O50),ISNUMBER(P50)),P50-O50,"") -> 0.12558994 | R50: =MAX(0,G50-N(L50)) -> 16560 | S50: =SUMIFS(Cadenas_vs_FCST!$D$17:$D$652,Cadenas_vs_FCST!$A$17:$A$652,A50) -> 24792 | T50: =SUMIFS(Cadenas_vs_FCST!$E$17:$E$652,Cadenas_vs_FCST!$A$17:$A$652,A50) -> 25243.007 | U50: =IF(T50>0,S50/T50-1,"") -> -0.017866609 | V50: =IF(OR(E50="BAJO SS",E50="BAJO SS (XLIB CUBRE)"),"SÍ","") | W50: =IF(AND(V50="",N(L50)>=Parametros!$B$17,G50>=H50,R50<H50),"SÍ","") | X50: =IF(OR(E50="SOBRE MAX VENDIBLE",N(N50)>=Parametros!$B$17,N(M50)>=Parametros!$B$17),"SÍ","") -> SÍ | Y50: =IF(AND(ISNUMBER(U50),MAX(S50,T50)>=Parametros!$B$15,ABS(N(U50))>Parametros!$B$14),"SÍ","") | Z50: =COUNTIF(V50:Y50,"SÍ") -> 1 | AA50: =(3*(V50="SÍ")+2*(W50="SÍ")+2*(X50="SÍ")+(Y50="SÍ"))*IF(LEFT(D50,1)="A",3,IF(OR(LEFT(D50,1)="B",D50="SIN HIST"),2,1)) -> 4 | AB50: =IF(AA50>=9,"1-ALTA",IF(AA50>=4,"2-MEDIA",IF(AA50>0,"3-BAJA",""))) -> 2-MEDIA | AC50: =IF(E50="BAJO SS","Stock + XLIB bajo el SS: riesgo real de quiebre, adelantar producción. ","")&IF(E50="BAJO SS (XLIB CUBRE)","Disponible bajo el SS; depende de liberar "&TEXT(J50,"#,##0")&" kg"&IF(ISNUMBER(K50)," el "&TEXT(K50,"dd-mm"),"")&". ","")&IF(W50="SÍ","Stock parece sano pero "&TEXT(L50,"#,##0")&" kg no pasan filtro "&Stock_Seguridad!O50&": sin ellos queda bajo el SS para esa cadena. ","")&IF(E50="SOBRE MAX VENDIBLE","Sobrestock vs vida útil: frenar producción/activar venta. ","")&IF(N(N50)>=Parametros!$B$17,TEXT(N50,"#,##0")&" kg ya no los acepta ninguna cadena: venta intermedia/liquidación. ","")&IF(N(M50)>=Parametros!$B$17,TEXT(M50,"#,##0")&" kg a punto de salir del filtro: despachar primero (FEFO). ","")&IF(Y50="SÍ","Pedidos "&IF(N(U50)>0,"sobre","bajo")&" FCST "&TEXT(ABS(N(U50)),"0%")&": revisar forecast con KAM.","") -> 4,188 kg a punto de salir del filtro: despachar primero (FEFO).
A51: =Stock_Seguridad!A51 -> 30001923 | B51: =Stock_Seguridad!B51 -> JUGO 100% WATTS NRJA-MZNA LV 30X200ML | C51: =Stock_Seguridad!C51 -> JUGOS Y NECTARES | D51: =Stock_Seguridad!F51 -> BY | E51: =Stock_Seguridad!X51 -> OK | F51: =Stock_Seguridad!W51 -> 1.8700155 | G51: =Stock_Seguridad!T51 -> 10602 | H51: =Stock_Seguridad!R51 -> 2391.7034 | I51: =Stock_Seguridad!S51 -> 8523.2034 | J51: =Stock_Seguridad!U51 -> 864 | K51: 46320 | L51: 936 | M51: 0 | N51: 48 | O51: 0.086567242 | P51: =IF(ISNUMBER(Stock_Seguridad!N51),Stock_Seguridad!N51,"") -> 0.19021739 | Q51: =IF(AND(ISNUMBER(O51),ISNUMBER(P51)),P51-O51,"") -> 0.10365015 | R51: =MAX(0,G51-N(L51)) -> 9666 | S51: =SUMIFS(Cadenas_vs_FCST!$D$17:$D$652,Cadenas_vs_FCST!$A$17:$A$652,A51) -> 28890 | T51: =SUMIFS(Cadenas_vs_FCST!$E$17:$E$652,Cadenas_vs_FCST!$A$17:$A$652,A51) -> 30396.603 | U51: =IF(T51>0,S51/T51-1,"") -> -0.049564844 | V51: =IF(OR(E51="BAJO SS",E51="BAJO SS (XLIB CUBRE)"),"SÍ","") | W51: =IF(AND(V51="",N(L51)>=Parametros!$B$17,G51>=H51,R51<H51),"SÍ","") | X51: =IF(OR(E51="SOBRE MAX VENDIBLE",N(N51)>=Parametros!$B$17,N(M51)>=Parametros!$B$17),"SÍ","") | Y51: =IF(AND(ISNUMBER(U51),MAX(S51,T51)>=Parametros!$B$15,ABS(N(U51))>Parametros!$B$14),"SÍ","") | Z51: =COUNTIF(V51:Y51,"SÍ") -> 0 | AA51: =(3*(V51="SÍ")+2*(W51="SÍ")+2*(X51="SÍ")+(Y51="SÍ"))*IF(LEFT(D51,1)="A",3,IF(OR(LEFT(D51,1)="B",D51="SIN HIST"),2,1)) -> 0 | AB51: =IF(AA51>=9,"1-ALTA",IF(AA51>=4,"2-MEDIA",IF(AA51>0,"3-BAJA",""))) | AC51: =IF(E51="BAJO SS","Stock + XLIB bajo el SS: riesgo real de quiebre, adelantar producción. ","")&IF(E51="BAJO SS (XLIB CUBRE)","Disponible bajo el SS; depende de liberar "&TEXT(J51,"#,##0")&" kg"&IF(ISNUMBER(K51)," el "&TEXT(K51,"dd-mm"),"")&". ","")&IF(W51="SÍ","Stock parece sano pero "&TEXT(L51,"#,##0")&" kg no pasan filtro "&Stock_Seguridad!O51&": sin ellos queda bajo el SS para esa cadena. ","")&IF(E51="SOBRE MAX VENDIBLE","Sobrestock vs vida útil: frenar producción/activar venta. ","")&IF(N(N51)>=Parametros!$B$17,TEXT(N51,"#,##0")&" kg ya no los acepta ninguna cadena: venta intermedia/liquidación. ","")&IF(N(M51)>=Parametros!$B$17,TEXT(M51,"#,##0")&" kg a punto de salir del filtro: despachar primero (FEFO). ","")&IF(Y51="SÍ","Pedidos "&IF(N(U51)>0,"sobre","bajo")&" FCST "&TEXT(ABS(N(U51)),"0%")&": revisar forecast con KAM.","")
A52: =Stock_Seguridad!A52 -> 30001895 | B52: =Stock_Seguridad!B52 -> LECHE POLVO LONCO DESCREMADA 20X760GR | C52: =Stock_Seguridad!C52 -> LECHES EN POLVO | D52: =Stock_Seguridad!F52 -> BY | E52: =Stock_Seguridad!X52 -> OK | F52: =Stock_Seguridad!W52 -> 4.7370297 | G52: =Stock_Seguridad!T52 -> 28971.2 | H52: =Stock_Seguridad!R52 -> 4344.0921 | I52: =Stock_Seguridad!S52 -> 10459.992 | J52: =Stock_Seguridad!U52 -> 0 | L52: 380 | M52: 0 | N52: 0 | O52: 0.036292017 | P52: =IF(ISNUMBER(Stock_Seguridad!N52),Stock_Seguridad!N52,"") -> 0.19708029 | Q52: =IF(AND(ISNUMBER(O52),ISNUMBER(P52)),P52-O52,"") -> 0.16078828 | R52: =MAX(0,G52-N(L52)) -> 28591.2 | S52: =SUMIFS(Cadenas_vs_FCST!$D$17:$D$652,Cadenas_vs_FCST!$A$17:$A$652,A52) -> 18908.8 | T52: =SUMIFS(Cadenas_vs_FCST!$E$17:$E$652,Cadenas_vs_FCST!$A$17:$A$652,A52) -> 25675.114 | U52: =IF(T52>0,S52/T52-1,"") -> -0.2635359 | V52: =IF(OR(E52="BAJO SS",E52="BAJO SS (XLIB CUBRE)"),"SÍ","") | W52: =IF(AND(V52="",N(L52)>=Parametros!$B$17,G52>=H52,R52<H52),"SÍ","") | X52: =IF(OR(E52="SOBRE MAX VENDIBLE",N(N52)>=Parametros!$B$17,N(M52)>=Parametros!$B$17),"SÍ","") | Y52: =IF(AND(ISNUMBER(U52),MAX(S52,T52)>=Parametros!$B$15,ABS(N(U52))>Parametros!$B$14),"SÍ","") -> SÍ | Z52: =COUNTIF(V52:Y52,"SÍ") -> 1 | AA52: =(3*(V52="SÍ")+2*(W52="SÍ")+2*(X52="SÍ")+(Y52="SÍ"))*IF(LEFT(D52,1)="A",3,IF(OR(LEFT(D52,1)="B",D52="SIN HIST"),2,1)) -> 2 | AB52: =IF(AA52>=9,"1-ALTA",IF(AA52>=4,"2-MEDIA",IF(AA52>0,"3-BAJA",""))) -> 3-BAJA | AC52: =IF(E52="BAJO SS","Stock + XLIB bajo el SS: riesgo real de quiebre, adelantar producción. ","")&IF(E52="BAJO SS (XLIB CUBRE)","Disponible bajo el SS; depende de liberar "&TEXT(J52,"#,##0")&" kg"&IF(ISNUMBER(K52)," el "&TEXT(K52,"dd-mm"),"")&". ","")&IF(W52="SÍ","Stock parece sano pero "&TEXT(L52,"#,##0")&" kg no pasan filtro "&Stock_Seguridad!O52&": sin ellos queda bajo el SS para esa cadena. ","")&IF(E52="SOBRE MAX VENDIBLE","Sobrestock vs vida útil: frenar producción/activar venta. ","")&IF(N(N52)>=Parametros!$B$17,TEXT(N52,"#,##0")&" kg ya no los acepta ninguna cadena: venta intermedia/liquidación. ","")&IF(N(M52)>=Parametros!$B$17,TEXT(M52,"#,##0")&" kg a punto de salir del filtro: despachar primero (FEFO). ","")&IF(Y52="SÍ","Pedidos "&IF(N(U52)>0,"sobre","bajo")&" FCST "&TEXT(ABS(N(U52)),"0%")&": revisar forecast con KAM.","") -> Pedidos bajo FCST 26%: revisar forecast con KAM.
A53: =Stock_Seguridad!A53 -> 30000328 | B53: =Stock_Seguridad!B53 -> LECHE LONCO S/LACTOSA CHOCO 12X1LT | C53: =Stock_Seguridad!C53 -> LECHES LIQUIDAS | D53: =Stock_Seguridad!F53 -> BX | E53: =Stock_Seguridad!X53 -> OK | F53: =Stock_Seguridad!W53 -> 2.3120328 | G53: =Stock_Seguridad!T53 -> 14136 | H53: =Stock_Seguridad!R53 -> 3414.0036 | I53: =Stock_Seguridad!S53 -> 9528.1036 | J53: =Stock_Seguridad!U53 -> 0 | L53: 2016 | M53: 0 | N53: 228 | O53: 0.18196262 | P53: =IF(ISNUMBER(Stock_Seguridad!N53),Stock_Seguridad!N53,"") -> 0.25925926 | Q53: =IF(AND(ISNUMBER(O53),ISNUMBER(P53)),P53-O53,"") -> 0.077296642 | R53: =MAX(0,G53-N(L53)) -> 12120 | S53: =SUMIFS(Cadenas_vs_FCST!$D$17:$D$652,Cadenas_vs_FCST!$A$17:$A$652,A53) -> 21840 | T53: =SUMIFS(Cadenas_vs_FCST!$E$17:$E$652,Cadenas_vs_FCST!$A$17:$A$652,A53) -> 26225.371 | U53: =IF(T53>0,S53/T53-1,"") -> -0.16721865 | V53: =IF(OR(E53="BAJO SS",E53="BAJO SS (XLIB CUBRE)"),"SÍ","") | W53: =IF(AND(V53="",N(L53)>=Parametros!$B$17,G53>=H53,R53<H53),"SÍ","") | X53: =IF(OR(E53="SOBRE MAX VENDIBLE",N(N53)>=Parametros!$B$17,N(M53)>=Parametros!$B$17),"SÍ","") | Y53: =IF(AND(ISNUMBER(U53),MAX(S53,T53)>=Parametros!$B$15,ABS(N(U53))>Parametros!$B$14),"SÍ","") | Z53: =COUNTIF(V53:Y53,"SÍ") -> 0 | AA53: =(3*(V53="SÍ")+2*(W53="SÍ")+2*(X53="SÍ")+(Y53="SÍ"))*IF(LEFT(D53,1)="A",3,IF(OR(LEFT(D53,1)="B",D53="SIN HIST"),2,1)) -> 0 | AB53: =IF(AA53>=9,"1-ALTA",IF(AA53>=4,"2-MEDIA",IF(AA53>0,"3-BAJA",""))) | AC53: =IF(E53="BAJO SS","Stock + XLIB bajo el SS: riesgo real de quiebre, adelantar producción. ","")&IF(E53="BAJO SS (XLIB CUBRE)","Disponible bajo el SS; depende de liberar "&TEXT(J53,"#,##0")&" kg"&IF(ISNUMBER(K53)," el "&TEXT(K53,"dd-mm"),"")&". ","")&IF(W53="SÍ","Stock parece sano pero "&TEXT(L53,"#,##0")&" kg no pasan filtro "&Stock_Seguridad!O53&": sin ellos queda bajo el SS para esa cadena. ","")&IF(E53="SOBRE MAX VENDIBLE","Sobrestock vs vida útil: frenar producción/activar venta. ","")&IF(N(N53)>=Parametros!$B$17,TEXT(N53,"#,##0")&" kg ya no los acepta ninguna cadena: venta intermedia/liquidación. ","")&IF(N(M53)>=Parametros!$B$17,TEXT(M53,"#,##0")&" kg a punto de salir del filtro: despachar primero (FEFO). ","")&IF(Y53="SÍ","Pedidos "&IF(N(U53)>0,"sobre","bajo")&" FCST "&TEXT(ABS(N(U53)),"0%")&": revisar forecast con KAM.","")
A54: =Stock_Seguridad!A54 -> 30001487 | B54: =Stock_Seguridad!B54 -> JUGO 100% WATTS MZNA LV 30X200ML | C54: =Stock_Seguridad!C54 -> JUGOS Y NECTARES | D54: =Stock_Seguridad!F54 -> BX | E54: =Stock_Seguridad!X54 -> OK | F54: =Stock_Seguridad!W54 -> 4.0527788 | G54: =Stock_Seguridad!T54 -> 11316 | H54: =Stock_Seguridad!R54 -> 3645.7187 | I54: =Stock_Seguridad!S54 -> 9686.0187 | J54: =Stock_Seguridad!U54 -> 13164 | K54: 46318 | L54: 30 | M54: 246 | N54: 0 | O54: 0.050334152 | P54: =IF(ISNUMBER(Stock_Seguridad!N54),Stock_Seguridad!N54,"") -> 0.31111111 | Q54: =IF(AND(ISNUMBER(O54),ISNUMBER(P54)),P54-O54,"") -> 0.26077696 | R54: =MAX(0,G54-N(L54)) -> 11286 | S54: =SUMIFS(Cadenas_vs_FCST!$D$17:$D$652,Cadenas_vs_FCST!$A$17:$A$652,A54) -> 26442 | T54: =SUMIFS(Cadenas_vs_FCST!$E$17:$E$652,Cadenas_vs_FCST!$A$17:$A$652,A54) -> 23999.774 | U54: =IF(T54>0,S54/T54-1,"") -> 0.10176039 | V54: =IF(OR(E54="BAJO SS",E54="BAJO SS (XLIB CUBRE)"),"SÍ","") | W54: =IF(AND(V54="",N(L54)>=Parametros!$B$17,G54>=H54,R54<H54),"SÍ","") | X54: =IF(OR(E54="SOBRE MAX VENDIBLE",N(N54)>=Parametros!$B$17,N(M54)>=Parametros!$B$17),"SÍ","") | Y54: =IF(AND(ISNUMBER(U54),MAX(S54,T54)>=Parametros!$B$15,ABS(N(U54))>Parametros!$B$14),"SÍ","") | Z54: =COUNTIF(V54:Y54,"SÍ") -> 0 | AA54: =(3*(V54="SÍ")+2*(W54="SÍ")+2*(X54="SÍ")+(Y54="SÍ"))*IF(LEFT(D54,1)="A",3,IF(OR(LEFT(D54,1)="B",D54="SIN HIST"),2,1)) -> 0 | AB54: =IF(AA54>=9,"1-ALTA",IF(AA54>=4,"2-MEDIA",IF(AA54>0,"3-BAJA",""))) | AC54: =IF(E54="BAJO SS","Stock + XLIB bajo el SS: riesgo real de quiebre, adelantar producción. ","")&IF(E54="BAJO SS (XLIB CUBRE)","Disponible bajo el SS; depende de liberar "&TEXT(J54,"#,##0")&" kg"&IF(ISNUMBER(K54)," el "&TEXT(K54,"dd-mm"),"")&". ","")&IF(W54="SÍ","Stock parece sano pero "&TEXT(L54,"#,##0")&" kg no pasan filtro "&Stock_Seguridad!O54&": sin ellos queda bajo el SS para esa cadena. ","")&IF(E54="SOBRE MAX VENDIBLE","Sobrestock vs vida útil: frenar producción/activar venta. ","")&IF(N(N54)>=Parametros!$B$17,TEXT(N54,"#,##0")&" kg ya no los acepta ninguna cadena: venta intermedia/liquidación. ","")&IF(N(M54)>=Parametros!$B$17,TEXT(M54,"#,##0")&" kg a punto de salir del filtro: despachar primero (FEFO). ","")&IF(Y54="SÍ","Pedidos "&IF(N(U54)>0,"sobre","bajo")&" FCST "&TEXT(ABS(N(U54)),"0%")&": revisar forecast con KAM.","")
A55: =Stock_Seguridad!A55 -> 30002098 | B55: =Stock_Seguridad!B55 -> MANJAR LONCOLECHE DP 12X750GR | C55: =Stock_Seguridad!C55 -> MANJAR | D55: =Stock_Seguridad!F55 -> CX | E55: =Stock_Seguridad!X55 -> OK | F55: =Stock_Seguridad!W55 -> 2.9538872 | G55: =Stock_Seguridad!T55 -> 16623 | H55: =Stock_Seguridad!R55 -> 1696.6148 | I55: =Stock_Seguridad!S55 -> 7324.1148 | J55: =Stock_Seguridad!U55 -> 0 | L55: 6345 | M55: 0 | N55: 45 | O55: 0.14813211 | P55: =IF(ISNUMBER(Stock_Seguridad!N55),Stock_Seguridad!N55,"") -> 0.19021739 | Q55: =IF(AND(ISNUMBER(O55),ISNUMBER(P55)),P55-O55,"") -> 0.042085285 | R55: =MAX(0,G55-N(L55)) -> 10278 | S55: =SUMIFS(Cadenas_vs_FCST!$D$17:$D$652,Cadenas_vs_FCST!$A$17:$A$652,A55) -> 10602 | T55: =SUMIFS(Cadenas_vs_FCST!$E$17:$E$652,Cadenas_vs_FCST!$A$17:$A$652,A55) -> 15603.692 | U55: =IF(T55>0,S55/T55-1,"") -> -0.3205454 | V55: =IF(OR(E55="BAJO SS",E55="BAJO SS (XLIB CUBRE)"),"SÍ","") | W55: =IF(AND(V55="",N(L55)>=Parametros!$B$17,G55>=H55,R55<H55),"SÍ","") | X55: =IF(OR(E55="SOBRE MAX VENDIBLE",N(N55)>=Parametros!$B$17,N(M55)>=Parametros!$B$17),"SÍ","") | Y55: =IF(AND(ISNUMBER(U55),MAX(S55,T55)>=Parametros!$B$15,ABS(N(U55))>Parametros!$B$14),"SÍ","") -> SÍ | Z55: =COUNTIF(V55:Y55,"SÍ") -> 1 | AA55: =(3*(V55="SÍ")+2*(W55="SÍ")+2*(X55="SÍ")+(Y55="SÍ"))*IF(LEFT(D55,1)="A",3,IF(OR(LEFT(D55,1)="B",D55="SIN HIST"),2,1)) -> 1 | AB55: =IF(AA55>=9,"1-ALTA",IF(AA55>=4,"2-MEDIA",IF(AA55>0,"3-BAJA",""))) -> 3-BAJA | AC55: =IF(E55="BAJO SS","Stock + XLIB bajo el SS: riesgo real de quiebre, adelantar producción. ","")&IF(E55="BAJO SS (XLIB CUBRE)","Disponible bajo el SS; depende de liberar "&TEXT(J55,"#,##0")&" kg"&IF(ISNUMBER(K55)," el "&TEXT(K55,"dd-mm"),"")&". ","")&IF(W55="SÍ","Stock parece sano pero "&TEXT(L55,"#,##0")&" kg no pasan filtro "&Stock_Seguridad!O55&": sin ellos queda bajo el SS para esa cadena. ","")&IF(E55="SOBRE MAX VENDIBLE","Sobrestock vs vida útil: frenar producción/activar venta. ","")&IF(N(N55)>=Parametros!$B$17,TEXT(N55,"#,##0")&" kg ya no los acepta ninguna cadena: venta intermedia/liquidación. ","")&IF(N(M55)>=Parametros!$B$17,TEXT(M55,"#,##0")&" kg a punto de salir del filtro: despachar primero (FEFO). ","")&IF(Y55="SÍ","Pedidos "&IF(N(U55)>0,"sobre","bajo")&" FCST "&TEXT(ABS(N(U55)),"0%")&": revisar forecast con KAM.","") -> Pedidos bajo FCST 32%: revisar forecast con KAM.
A56: =Stock_Seguridad!A56 -> 30001715 | B56: =Stock_Seguridad!B56 -> LECHE POLVO LONCO SEMIDESCREMADA10X760GR | C56: =Stock_Seguridad!C56 -> LECHES EN POLVO | D56: =Stock_Seguridad!F56 -> BX | E56: =Stock_Seguridad!X56 -> OK | F56: =Stock_Seguridad!W56 -> 5.2942726 | G56: =Stock_Seguridad!T56 -> 28933.2 | H56: =Stock_Seguridad!R56 -> 9819.0114 | I56: =Stock_Seguridad!S56 -> 15284.011 | J56: =Stock_Seguridad!U56 -> 0 | L56: 0 | M56: 129.2 | N56: 0 | O56: 0.063832808 | P56: =IF(ISNUMBER(Stock_Seguridad!N56),Stock_Seguridad!N56,"") -> 0.19452055 | Q56: =IF(AND(ISNUMBER(O56),ISNUMBER(P56)),P56-O56,"") -> 0.13068774 | R56: =MAX(0,G56-N(L56)) -> 28933.2 | S56: =SUMIFS(Cadenas_vs_FCST!$D$17:$D$652,Cadenas_vs_FCST!$A$17:$A$652,A56) -> 23848.8 | T56: =SUMIFS(Cadenas_vs_FCST!$E$17:$E$652,Cadenas_vs_FCST!$A$17:$A$652,A56) -> 40004.854 | U56: =IF(T56>0,S56/T56-1,"") -> -0.40385234 | V56: =IF(OR(E56="BAJO SS",E56="BAJO SS (XLIB CUBRE)"),"SÍ","") | W56: =IF(AND(V56="",N(L56)>=Parametros!$B$17,G56>=H56,R56<H56),"SÍ","") | X56: =IF(OR(E56="SOBRE MAX VENDIBLE",N(N56)>=Parametros!$B$17,N(M56)>=Parametros!$B$17),"SÍ","") | Y56: =IF(AND(ISNUMBER(U56),MAX(S56,T56)>=Parametros!$B$15,ABS(N(U56))>Parametros!$B$14),"SÍ","") -> SÍ | Z56: =COUNTIF(V56:Y56,"SÍ") -> 1 | AA56: =(3*(V56="SÍ")+2*(W56="SÍ")+2*(X56="SÍ")+(Y56="SÍ"))*IF(LEFT(D56,1)="A",3,IF(OR(LEFT(D56,1)="B",D56="SIN HIST"),2,1)) -> 2 | AB56: =IF(AA56>=9,"1-ALTA",IF(AA56>=4,"2-MEDIA",IF(AA56>0,"3-BAJA",""))) -> 3-BAJA | AC56: =IF(E56="BAJO SS","Stock + XLIB bajo el SS: riesgo real de quiebre, adelantar producción. ","")&IF(E56="BAJO SS (XLIB CUBRE)","Disponible bajo el SS; depende de liberar "&TEXT(J56,"#,##0")&" kg"&IF(ISNUMBER(K56)," el "&TEXT(K56,"dd-mm"),"")&". ","")&IF(W56="SÍ","Stock parece sano pero "&TEXT(L56,"#,##0")&" kg no pasan filtro "&Stock_Seguridad!O56&": sin ellos queda bajo el SS para esa cadena. ","")&IF(E56="SOBRE MAX VENDIBLE","Sobrestock vs vida útil: frenar producción/activar venta. ","")&IF(N(N56)>=Parametros!$B$17,TEXT(N56,"#,##0")&" kg ya no los acepta ninguna cadena: venta intermedia/liquidación. ","")&IF(N(M56)>=Parametros!$B$17,TEXT(M56,"#,##0")&" kg a punto de salir del filtro: despachar primero (FEFO). ","")&IF(Y56="SÍ","Pedidos "&IF(N(U56)>0,"sobre","bajo")&" FCST "&TEXT(ABS(N(U56)),"0%")&": revisar forecast con KAM.","") -> Pedidos bajo FCST 40%: revisar forecast con KAM.
A57: =Stock_Seguridad!A57 -> 30000321 | B57: =Stock_Seguridad!B57 -> LECHE POLVO LONCO S/LACT 10X800GR | C57: =Stock_Seguridad!C57 -> LECHES EN POLVO | D57: =Stock_Seguridad!F57 -> BX | E57: =Stock_Seguridad!X57 -> OK | F57: =Stock_Seguridad!W57 -> 3.1495125 | G57: =Stock_Seguridad!T57 -> 16928 | H57: =Stock_Seguridad!R57 -> 1134.1442 | I57: =Stock_Seguridad!S57 -> 6508.9442 | J57: =Stock_Seguridad!U57 -> 0 | L57: 0 | M57: 0 | N57: 0 | O57: 0.052468025 | P57: =IF(ISNUMBER(Stock_Seguridad!N57),Stock_Seguridad!N57,"") -> 0.32054795 | Q57: =IF(AND(ISNUMBER(O57),ISNUMBER(P57)),P57-O57,"") -> 0.26807992 | R57: =MAX(0,G57-N(L57)) -> 16928 | S57: =SUMIFS(Cadenas_vs_FCST!$D$17:$D$652,Cadenas_vs_FCST!$A$17:$A$652,A57) -> 21128 | T57: =SUMIFS(Cadenas_vs_FCST!$E$17:$E$652,Cadenas_vs_FCST!$A$17:$A$652,A57) -> 19478.523 | U57: =IF(T57>0,S57/T57-1,"") -> 0.084681828 | V57: =IF(OR(E57="BAJO SS",E57="BAJO SS (XLIB CUBRE)"),"SÍ","") | W57: =IF(AND(V57="",N(L57)>=Parametros!$B$17,G57>=H57,R57<H57),"SÍ","") | X57: =IF(OR(E57="SOBRE MAX VENDIBLE",N(N57)>=Parametros!$B$17,N(M57)>=Parametros!$B$17),"SÍ","") | Y57: =IF(AND(ISNUMBER(U57),MAX(S57,T57)>=Parametros!$B$15,ABS(N(U57))>Parametros!$B$14),"SÍ","") | Z57: =COUNTIF(V57:Y57,"SÍ") -> 0 | AA57: =(3*(V57="SÍ")+2*(W57="SÍ")+2*(X57="SÍ")+(Y57="SÍ"))*IF(LEFT(D57,1)="A",3,IF(OR(LEFT(D57,1)="B",D57="SIN HIST"),2,1)) -> 0 | AB57: =IF(AA57>=9,"1-ALTA",IF(AA57>=4,"2-MEDIA",IF(AA57>0,"3-BAJA",""))) | AC57: =IF(E57="BAJO SS","Stock + XLIB bajo el SS: riesgo real de quiebre, adelantar producción. ","")&IF(E57="BAJO SS (XLIB CUBRE)","Disponible bajo el SS; depende de liberar "&TEXT(J57,"#,##0")&" kg"&IF(ISNUMBER(K57)," el "&TEXT(K57,"dd-mm"),"")&". ","")&IF(W57="SÍ","Stock parece sano pero "&TEXT(L57,"#,##0")&" kg no pasan filtro "&Stock_Seguridad!O57&": sin ellos queda bajo el SS para esa cadena. ","")&IF(E57="SOBRE MAX VENDIBLE","Sobrestock vs vida útil: frenar producción/activar venta. ","")&IF(N(N57)>=Parametros!$B$17,TEXT(N57,"#,##0")&" kg ya no los acepta ninguna cadena: venta intermedia/liquidación. ","")&IF(N(M57)>=Parametros!$B$17,TEXT(M57,"#,##0")&" kg a punto de salir del filtro: despachar primero (FEFO). ","")&IF(Y57="SÍ","Pedidos "&IF(N(U57)>0,"sobre","bajo")&" FCST "&TEXT(ABS(N(U57)),"0%")&": revisar forecast con KAM.","")
A58: =Stock_Seguridad!A58 -> 30001410 | B58: =Stock_Seguridad!B58 -> LECHE POLVO CALO ENTERA INST 6X1,440KG | C58: =Stock_Seguridad!C58 -> LECHES EN POLVO | D58: =Stock_Seguridad!F58 -> BX | E58: =Stock_Seguridad!X58 -> OK | F58: =Stock_Seguridad!W58 -> 6.225256 | G58: =Stock_Seguridad!T58 -> 26853.1 | H58: =Stock_Seguridad!R58 -> 4030.8749 | I58: =Stock_Seguridad!S58 -> 9293.7749 | J58: =Stock_Seguridad!U58 -> 5909.8 | K58: 46321 | L58: 630.72 | M58: 0 | N58: 0 | O58: 0.036191983 | P58: =IF(ISNUMBER(Stock_Seguridad!N58),Stock_Seguridad!N58,"") -> 0.19452055 | Q58: =IF(AND(ISNUMBER(O58),ISNUMBER(P58)),P58-O58,"") -> 0.15832856 | R58: =MAX(0,G58-N(L58)) -> 26222.38 | S58: =SUMIFS(Cadenas_vs_FCST!$D$17:$D$652,Cadenas_vs_FCST!$A$17:$A$652,A58) -> 26049.6 | T58: =SUMIFS(Cadenas_vs_FCST!$E$17:$E$652,Cadenas_vs_FCST!$A$17:$A$652,A58) -> 22796.111 | U58: =IF(T58>0,S58/T58-1,"") -> 0.14272125 | V58: =IF(OR(E58="BAJO SS",E58="BAJO SS (XLIB CUBRE)"),"SÍ","") | W58: =IF(AND(V58="",N(L58)>=Parametros!$B$17,G58>=H58,R58<H58),"SÍ","") | X58: =IF(OR(E58="SOBRE MAX VENDIBLE",N(N58)>=Parametros!$B$17,N(M58)>=Parametros!$B$17),"SÍ","") | Y58: =IF(AND(ISNUMBER(U58),MAX(S58,T58)>=Parametros!$B$15,ABS(N(U58))>Parametros!$B$14),"SÍ","") | Z58: =COUNTIF(V58:Y58,"SÍ") -> 0 | AA58: =(3*(V58="SÍ")+2*(W58="SÍ")+2*(X58="SÍ")+(Y58="SÍ"))*IF(LEFT(D58,1)="A",3,IF(OR(LEFT(D58,1)="B",D58="SIN HIST"),2,1)) -> 0 | AB58: =IF(AA58>=9,"1-ALTA",IF(AA58>=4,"2-MEDIA",IF(AA58>0,"3-BAJA",""))) | AC58: =IF(E58="BAJO SS","Stock + XLIB bajo el SS: riesgo real de quiebre, adelantar producción. ","")&IF(E58="BAJO SS (XLIB CUBRE)","Disponible bajo el SS; depende de liberar "&TEXT(J58,"#,##0")&" kg"&IF(ISNUMBER(K58)," el "&TEXT(K58,"dd-mm"),"")&". ","")&IF(W58="SÍ","Stock parece sano pero "&TEXT(L58,"#,##0")&" kg no pasan filtro "&Stock_Seguridad!O58&": sin ellos queda bajo el SS para esa cadena. ","")&IF(E58="SOBRE MAX VENDIBLE","Sobrestock vs vida útil: frenar producción/activar venta. ","")&IF(N(N58)>=Parametros!$B$17,TEXT(N58,"#,##0")&" kg ya no los acepta ninguna cadena: venta intermedia/liquidación. ","")&IF(N(M58)>=Parametros!$B$17,TEXT(M58,"#,##0")&" kg a punto de salir del filtro: despachar primero (FEFO). ","")&IF(Y58="SÍ","Pedidos "&IF(N(U58)>0,"sobre","bajo")&" FCST "&TEXT(ABS(N(U58)),"0%")&": revisar forecast con KAM.","")
A59: =Stock_Seguridad!A59 -> 30002125 | B59: =Stock_Seguridad!B59 -> LECHE EN POLVO ENTERA LONCO 20X760GR | C59: =Stock_Seguridad!C59 -> LECHES EN POLVO | D59: =Stock_Seguridad!F59 -> CY | E59: =Stock_Seguridad!X59 -> OK | F59: =Stock_Seguridad!W59 -> 3.0424011 | G59: =Stock_Seguridad!T59 -> 15792.8 | H59: =Stock_Seguridad!R59 -> 698.35027 | I59: =Stock_Seguridad!S59 -> 5889.2503 | J59: =Stock_Seguridad!U59 -> 0 | L59: 0 | M59: 0 | N59: 0 | O59: 0.06080847 | P59: =IF(ISNUMBER(Stock_Seguridad!N59),Stock_Seguridad!N59,"") -> 0.32054795 | Q59: =IF(AND(ISNUMBER(O59),ISNUMBER(P59)),P59-O59,"") -> 0.25973948 | R59: =MAX(0,G59-N(L59)) -> 15792.8 | S59: =SUMIFS(Cadenas_vs_FCST!$D$17:$D$652,Cadenas_vs_FCST!$A$17:$A$652,A59) -> 8284 | T59: =SUMIFS(Cadenas_vs_FCST!$E$17:$E$652,Cadenas_vs_FCST!$A$17:$A$652,A59) -> 9350.1254 | U59: =IF(T59>0,S59/T59-1,"") -> -0.11402258 | V59: =IF(OR(E59="BAJO SS",E59="BAJO SS (XLIB CUBRE)"),"SÍ","") | W59: =IF(AND(V59="",N(L59)>=Parametros!$B$17,G59>=H59,R59<H59),"SÍ","") | X59: =IF(OR(E59="SOBRE MAX VENDIBLE",N(N59)>=Parametros!$B$17,N(M59)>=Parametros!$B$17),"SÍ","") | Y59: =IF(AND(ISNUMBER(U59),MAX(S59,T59)>=Parametros!$B$15,ABS(N(U59))>Parametros!$B$14),"SÍ","") | Z59: =COUNTIF(V59:Y59,"SÍ") -> 0 | AA59: =(3*(V59="SÍ")+2*(W59="SÍ")+2*(X59="SÍ")+(Y59="SÍ"))*IF(LEFT(D59,1)="A",3,IF(OR(LEFT(D59,1)="B",D59="SIN HIST"),2,1)) -> 0 | AB59: =IF(AA59>=9,"1-ALTA",IF(AA59>=4,"2-MEDIA",IF(AA59>0,"3-BAJA",""))) | AC59: =IF(E59="BAJO SS","Stock + XLIB bajo el SS: riesgo real de quiebre, adelantar producción. ","")&IF(E59="BAJO SS (XLIB CUBRE)","Disponible bajo el SS; depende de liberar "&TEXT(J59,"#,##0")&" kg"&IF(ISNUMBER(K59)," el "&TEXT(K59,"dd-mm"),"")&". ","")&IF(W59="SÍ","Stock parece sano pero "&TEXT(L59,"#,##0")&" kg no pasan filtro "&Stock_Seguridad!O59&": sin ellos queda bajo el SS para esa cadena. ","")&IF(E59="SOBRE MAX VENDIBLE","Sobrestock vs vida útil: frenar producción/activar venta. ","")&IF(N(N59)>=Parametros!$B$17,TEXT(N59,"#,##0")&" kg ya no los acepta ninguna cadena: venta intermedia/liquidación. ","")&IF(N(M59)>=Parametros!$B$17,TEXT(M59,"#,##0")&" kg a punto de salir del filtro: despachar primero (FEFO). ","")&IF(Y59="SÍ","Pedidos "&IF(N(U59)>0,"sobre","bajo")&" FCST "&TEXT(ABS(N(U59)),"0%")&": revisar forecast con KAM.","")
A60: =Stock_Seguridad!A60 -> 30000244 | B60: =Stock_Seguridad!B60 -> NECTAR WATTS NARANJA 12X1LT | C60: =Stock_Seguridad!C60 -> JUGOS Y NECTARES | D60: =Stock_Seguridad!F60 -> CX | E60: =Stock_Seguridad!X60 -> OK | F60: =Stock_Seguridad!W60 -> 6.2258889 | G60: =Stock_Seguridad!T60 -> 32148 | H60: =Stock_Seguridad!R60 -> 2295.8222 | I60: =Stock_Seguridad!S60 -> 7459.4222 | J60: =Stock_Seguridad!U60 -> 0 | L60: 0 | M60: 672 | N60: 0 | O60: 0.057274085 | P60: =IF(ISNUMBER(Stock_Seguridad!N60),Stock_Seguridad!N60,"") -> 0.19452055 | Q60: =IF(AND(ISNUMBER(O60),ISNUMBER(P60)),P60-O60,"") -> 0.13724646 | R60: =MAX(0,G60-N(L60)) -> 32148 | S60: =SUMIFS(Cadenas_vs_FCST!$D$17:$D$652,Cadenas_vs_FCST!$A$17:$A$652,A60) -> 15384 | T60: =SUMIFS(Cadenas_vs_FCST!$E$17:$E$652,Cadenas_vs_FCST!$A$17:$A$652,A60) -> 23268.939 | U60: =IF(T60>0,S60/T60-1,"") -> -0.33886113 | V60: =IF(OR(E60="BAJO SS",E60="BAJO SS (XLIB CUBRE)"),"SÍ","") | W60: =IF(AND(V60="",N(L60)>=Parametros!$B$17,G60>=H60,R60<H60),"SÍ","") | X60: =IF(OR(E60="SOBRE MAX VENDIBLE",N(N60)>=Parametros!$B$17,N(M60)>=Parametros!$B$17),"SÍ","") -> SÍ | Y60: =IF(AND(ISNUMBER(U60),MAX(S60,T60)>=Parametros!$B$15,ABS(N(U60))>Parametros!$B$14),"SÍ","") -> SÍ | Z60: =COUNTIF(V60:Y60,"SÍ") -> 2 | AA60: =(3*(V60="SÍ")+2*(W60="SÍ")+2*(X60="SÍ")+(Y60="SÍ"))*IF(LEFT(D60,1)="A",3,IF(OR(LEFT(D60,1)="B",D60="SIN HIST"),2,1)) -> 3 | AB60: =IF(AA60>=9,"1-ALTA",IF(AA60>=4,"2-MEDIA",IF(AA60>0,"3-BAJA",""))) -> 3-BAJA | AC60: =IF(E60="BAJO SS","Stock + XLIB bajo el SS: riesgo real de quiebre, adelantar producción. ","")&IF(E60="BAJO SS (XLIB CUBRE)","Disponible bajo el SS; depende de liberar "&TEXT(J60,"#,##0")&" kg"&IF(ISNUMBER(K60)," el "&TEXT(K60,"dd-mm"),"")&". ","")&IF(W60="SÍ","Stock parece sano pero "&TEXT(L60,"#,##0")&" kg no pasan filtro "&Stock_Seguridad!O60&": sin ellos queda bajo el SS para esa cadena. ","")&IF(E60="SOBRE MAX VENDIBLE","Sobrestock vs vida útil: frenar producción/activar venta. ","")&IF(N(N60)>=Parametros!$B$17,TEXT(N60,"#,##0")&" kg ya no los acepta ninguna cadena: venta intermedia/liquidación. ","")&IF(N(M60)>=Parametros!$B$17,TEXT(M60,"#,##0")&" kg a punto de salir del filtro: despachar primero (FEFO). ","")&IF(Y60="SÍ","Pedidos "&IF(N(U60)>0,"sobre","bajo")&" FCST "&TEXT(ABS(N(U60)),"0%")&": revisar forecast con KAM.","") -> 672 kg a punto de salir del filtro: despachar primero (FEFO). Pedidos bajo FCST 34%: revisar forecast con KAM.
A61: =Stock_Seguridad!A61 -> 30000543 | B61: =Stock_Seguridad!B61 -> BEBIDA VEGETAL LONCO AVENA LCO 6X1LT | C61: =Stock_Seguridad!C61 -> LECHES LIQUIDAS | D61: =Stock_Seguridad!F61 -> CX | E61: =Stock_Seguridad!X61 -> BAJO P.REORDEN | F61: =Stock_Seguridad!W61 -> 0.89406887 | G61: =Stock_Seguridad!T61 -> 4572 | H61: =Stock_Seguridad!R61 -> 2639.2966 | I61: =Stock_Seguridad!S61 -> 7752.9966 | J61: =Stock_Seguridad!U61 -> 0 | L61: 0 | M61: 0 | N61: 0 | O61: 0.27392388 | P61: =IF(ISNUMBER(Stock_Seguridad!N61),Stock_Seguridad!N61,"") -> 0.47945205 | Q61: =IF(AND(ISNUMBER(O61),ISNUMBER(P61)),P61-O61,"") -> 0.20552817 | R61: =MAX(0,G61-N(L61)) -> 4572 | S61: =SUMIFS(Cadenas_vs_FCST!$D$17:$D$652,Cadenas_vs_FCST!$A$17:$A$652,A61) -> 11862 | T61: =SUMIFS(Cadenas_vs_FCST!$E$17:$E$652,Cadenas_vs_FCST!$A$17:$A$652,A61) -> 17969.521 | U61: =IF(T61>0,S61/T61-1,"") -> -0.33988223 | V61: =IF(OR(E61="BAJO SS",E61="BAJO SS (XLIB CUBRE)"),"SÍ","") | W61: =IF(AND(V61="",N(L61)>=Parametros!$B$17,G61>=H61,R61<H61),"SÍ","") | X61: =IF(OR(E61="SOBRE MAX VENDIBLE",N(N61)>=Parametros!$B$17,N(M61)>=Parametros!$B$17),"SÍ","") | Y61: =IF(AND(ISNUMBER(U61),MAX(S61,T61)>=Parametros!$B$15,ABS(N(U61))>Parametros!$B$14),"SÍ","") -> SÍ | Z61: =COUNTIF(V61:Y61,"SÍ") -> 1 | AA61: =(3*(V61="SÍ")+2*(W61="SÍ")+2*(X61="SÍ")+(Y61="SÍ"))*IF(LEFT(D61,1)="A",3,IF(OR(LEFT(D61,1)="B",D61="SIN HIST"),2,1)) -> 1 | AB61: =IF(AA61>=9,"1-ALTA",IF(AA61>=4,"2-MEDIA",IF(AA61>0,"3-BAJA",""))) -> 3-BAJA | AC61: =IF(E61="BAJO SS","Stock + XLIB bajo el SS: riesgo real de quiebre, adelantar producción. ","")&IF(E61="BAJO SS (XLIB CUBRE)","Disponible bajo el SS; depende de liberar "&TEXT(J61,"#,##0")&" kg"&IF(ISNUMBER(K61)," el "&TEXT(K61,"dd-mm"),"")&". ","")&IF(W61="SÍ","Stock parece sano pero "&TEXT(L61,"#,##0")&" kg no pasan filtro "&Stock_Seguridad!O61&": sin ellos queda bajo el SS para esa cadena. ","")&IF(E61="SOBRE MAX VENDIBLE","Sobrestock vs vida útil: frenar producción/activar venta. ","")&IF(N(N61)>=Parametros!$B$17,TEXT(N61,"#,##0")&" kg ya no los acepta ninguna cadena: venta intermedia/liquidación. ","")&IF(N(M61)>=Parametros!$B$17,TEXT(M61,"#,##0")&" kg a punto de salir del filtro: despachar primero (FEFO). ","")&IF(Y61="SÍ","Pedidos "&IF(N(U61)>0,"sobre","bajo")&" FCST "&TEXT(ABS(N(U61)),"0%")&": revisar forecast con KAM.","") -> Pedidos bajo FCST 34%: revisar forecast con KAM.
A62: =Stock_Seguridad!A62 -> 30002077 | B62: =Stock_Seguridad!B62 -> LECHE VAINILLA LONCOLECHE 12X1LT | C62: =Stock_Seguridad!C62 -> LECHES LIQUIDAS | D62: =Stock_Seguridad!F62 -> BY | E62: =Stock_Seguridad!X62 -> OK | F62: =Stock_Seguridad!W62 -> 2.7328431 | G62: =Stock_Seguridad!T62 -> 7332 | H62: =Stock_Seguridad!R62 -> 6891.371 | I62: =Stock_Seguridad!S62 -> 11787.371 | J62: =Stock_Seguridad!U62 -> 6048 | K62: 46322 | L62: 180 | M62: 0 | N62: 72 | O62: 0.064017937 | P62: =IF(ISNUMBER(Stock_Seguridad!N62),Stock_Seguridad!N62,"") -> 0.21962617 | Q62: =IF(AND(ISNUMBER(O62),ISNUMBER(P62)),P62-O62,"") -> 0.15560823 | R62: =MAX(0,G62-N(L62)) -> 7152 | S62: =SUMIFS(Cadenas_vs_FCST!$D$17:$D$652,Cadenas_vs_FCST!$A$17:$A$652,A62) -> 19944 | T62: =SUMIFS(Cadenas_vs_FCST!$E$17:$E$652,Cadenas_vs_FCST!$A$17:$A$652,A62) -> 12652.89 | U62: =IF(T62>0,S62/T62-1,"") -> 0.57624074 | V62: =IF(OR(E62="BAJO SS",E62="BAJO SS (XLIB CUBRE)"),"SÍ","") | W62: =IF(AND(V62="",N(L62)>=Parametros!$B$17,G62>=H62,R62<H62),"SÍ","") | X62: =IF(OR(E62="SOBRE MAX VENDIBLE",N(N62)>=Parametros!$B$17,N(M62)>=Parametros!$B$17),"SÍ","") | Y62: =IF(AND(ISNUMBER(U62),MAX(S62,T62)>=Parametros!$B$15,ABS(N(U62))>Parametros!$B$14),"SÍ","") -> SÍ | Z62: =COUNTIF(V62:Y62,"SÍ") -> 1 | AA62: =(3*(V62="SÍ")+2*(W62="SÍ")+2*(X62="SÍ")+(Y62="SÍ"))*IF(LEFT(D62,1)="A",3,IF(OR(LEFT(D62,1)="B",D62="SIN HIST"),2,1)) -> 2 | AB62: =IF(AA62>=9,"1-ALTA",IF(AA62>=4,"2-MEDIA",IF(AA62>0,"3-BAJA",""))) -> 3-BAJA | AC62: =IF(E62="BAJO SS","Stock + XLIB bajo el SS: riesgo real de quiebre, adelantar producción. ","")&IF(E62="BAJO SS (XLIB CUBRE)","Disponible bajo el SS; depende de liberar "&TEXT(J62,"#,##0")&" kg"&IF(ISNUMBER(K62)," el "&TEXT(K62,"dd-mm"),"")&". ","")&IF(W62="SÍ","Stock parece sano pero "&TEXT(L62,"#,##0")&" kg no pasan filtro "&Stock_Seguridad!O62&": sin ellos queda bajo el SS para esa cadena. ","")&IF(E62="SOBRE MAX VENDIBLE","Sobrestock vs vida útil: frenar producción/activar venta. ","")&IF(N(N62)>=Parametros!$B$17,TEXT(N62,"#,##0")&" kg ya no los acepta ninguna cadena: venta intermedia/liquidación. ","")&IF(N(M62)>=Parametros!$B$17,TEXT(M62,"#,##0")&" kg a punto de salir del filtro: despachar primero (FEFO). ","")&IF(Y62="SÍ","Pedidos "&IF(N(U62)>0,"sobre","bajo")&" FCST "&TEXT(ABS(N(U62)),"0%")&": revisar forecast con KAM.","") -> Pedidos sobre FCST 58%: revisar forecast con KAM.
A63: =Stock_Seguridad!A63 -> 30000307 | B63: =Stock_Seguridad!B63 -> YOGU YOGU PINA 30X200GR | C63: =Stock_Seguridad!C63 -> LECHES LIQUIDAS | D63: =Stock_Seguridad!F63 -> CX | E63: =Stock_Seguridad!X63 -> OK | F63: =Stock_Seguridad!W63 -> 3.2522397 | G63: =Stock_Seguridad!T63 -> 15828 | H63: =Stock_Seguridad!R63 -> 1493.1599 | I63: =Stock_Seguridad!S63 -> 6359.9599 | J63: =Stock_Seguridad!U63 -> 0 | L63: 48 | M63: 1266 | N63: 0 | O63: 0.11786231 | P63: =IF(ISNUMBER(Stock_Seguridad!N63),Stock_Seguridad!N63,"") -> 0.22040816 | Q63: =IF(AND(ISNUMBER(O63),ISNUMBER(P63)),P63-O63,"") -> 0.10254586 | R63: =MAX(0,G63-N(L63)) -> 15780 | S63: =SUMIFS(Cadenas_vs_FCST!$D$17:$D$652,Cadenas_vs_FCST!$A$17:$A$652,A63) -> 14226 | T63: =SUMIFS(Cadenas_vs_FCST!$E$17:$E$652,Cadenas_vs_FCST!$A$17:$A$652,A63) -> 16885.727 | U63: =IF(T63>0,S63/T63-1,"") -> -0.15751333 | V63: =IF(OR(E63="BAJO SS",E63="BAJO SS (XLIB CUBRE)"),"SÍ","") | W63: =IF(AND(V63="",N(L63)>=Parametros!$B$17,G63>=H63,R63<H63),"SÍ","") | X63: =IF(OR(E63="SOBRE MAX VENDIBLE",N(N63)>=Parametros!$B$17,N(M63)>=Parametros!$B$17),"SÍ","") -> SÍ | Y63: =IF(AND(ISNUMBER(U63),MAX(S63,T63)>=Parametros!$B$15,ABS(N(U63))>Parametros!$B$14),"SÍ","") | Z63: =COUNTIF(V63:Y63,"SÍ") -> 1 | AA63: =(3*(V63="SÍ")+2*(W63="SÍ")+2*(X63="SÍ")+(Y63="SÍ"))*IF(LEFT(D63,1)="A",3,IF(OR(LEFT(D63,1)="B",D63="SIN HIST"),2,1)) -> 2 | AB63: =IF(AA63>=9,"1-ALTA",IF(AA63>=4,"2-MEDIA",IF(AA63>0,"3-BAJA",""))) -> 3-BAJA | AC63: =IF(E63="BAJO SS","Stock + XLIB bajo el SS: riesgo real de quiebre, adelantar producción. ","")&IF(E63="BAJO SS (XLIB CUBRE)","Disponible bajo el SS; depende de liberar "&TEXT(J63,"#,##0")&" kg"&IF(ISNUMBER(K63)," el "&TEXT(K63,"dd-mm"),"")&". ","")&IF(W63="SÍ","Stock parece sano pero "&TEXT(L63,"#,##0")&" kg no pasan filtro "&Stock_Seguridad!O63&": sin ellos queda bajo el SS para esa cadena. ","")&IF(E63="SOBRE MAX VENDIBLE","Sobrestock vs vida útil: frenar producción/activar venta. ","")&IF(N(N63)>=Parametros!$B$17,TEXT(N63,"#,##0")&" kg ya no los acepta ninguna cadena: venta intermedia/liquidación. ","")&IF(N(M63)>=Parametros!$B$17,TEXT(M63,"#,##0")&" kg a punto de salir del filtro: despachar primero (FEFO). ","")&IF(Y63="SÍ","Pedidos "&IF(N(U63)>0,"sobre","bajo")&" FCST "&TEXT(ABS(N(U63)),"0%")&": revisar forecast con KAM.","") -> 1,266 kg a punto de salir del filtro: despachar primero (FEFO).
A64: =Stock_Seguridad!A64 -> 30002180 | B64: =Stock_Seguridad!B64 -> SHAKE SHAKE MANJAR 30X190ML | C64: =Stock_Seguridad!C64 -> LECHES LIQUIDAS | D64: =Stock_Seguridad!F64 -> CX | E64: =Stock_Seguridad!X64 -> OK | F64: =Stock_Seguridad!W64 -> 4.2983766 | G64: =Stock_Seguridad!T64 -> 14540.7 | H64: =Stock_Seguridad!R64 -> 1884.1346 | I64: =Stock_Seguridad!S64 -> 6571.8346 | J64: =Stock_Seguridad!U64 -> 5608.8 | K64: 46319 | L64: 4708.2 | M64: 0 | N64: 0 | O64: 0.092656294 | P64: =IF(ISNUMBER(Stock_Seguridad!N64),Stock_Seguridad!N64,"") -> 0.19 | Q64: =IF(AND(ISNUMBER(O64),ISNUMBER(P64)),P64-O64,"") -> 0.097343706 | R64: =MAX(0,G64-N(L64)) -> 9832.5 | S64: =SUMIFS(Cadenas_vs_FCST!$D$17:$D$652,Cadenas_vs_FCST!$A$17:$A$652,A64) -> 10157.4 | T64: =SUMIFS(Cadenas_vs_FCST!$E$17:$E$652,Cadenas_vs_FCST!$A$17:$A$652,A64) -> 16777.486 | U64: =IF(T64>0,S64/T64-1,"") -> -0.39458153 | V64: =IF(OR(E64="BAJO SS",E64="BAJO SS (XLIB CUBRE)"),"SÍ","") | W64: =IF(AND(V64="",N(L64)>=Parametros!$B$17,G64>=H64,R64<H64),"SÍ","") | X64: =IF(OR(E64="SOBRE MAX VENDIBLE",N(N64)>=Parametros!$B$17,N(M64)>=Parametros!$B$17),"SÍ","") | Y64: =IF(AND(ISNUMBER(U64),MAX(S64,T64)>=Parametros!$B$15,ABS(N(U64))>Parametros!$B$14),"SÍ","") -> SÍ | Z64: =COUNTIF(V64:Y64,"SÍ") -> 1 | AA64: =(3*(V64="SÍ")+2*(W64="SÍ")+2*(X64="SÍ")+(Y64="SÍ"))*IF(LEFT(D64,1)="A",3,IF(OR(LEFT(D64,1)="B",D64="SIN HIST"),2,1)) -> 1 | AB64: =IF(AA64>=9,"1-ALTA",IF(AA64>=4,"2-MEDIA",IF(AA64>0,"3-BAJA",""))) -> 3-BAJA | AC64: =IF(E64="BAJO SS","Stock + XLIB bajo el SS: riesgo real de quiebre, adelantar producción. ","")&IF(E64="BAJO SS (XLIB CUBRE)","Disponible bajo el SS; depende de liberar "&TEXT(J64,"#,##0")&" kg"&IF(ISNUMBER(K64)," el "&TEXT(K64,"dd-mm"),"")&". ","")&IF(W64="SÍ","Stock parece sano pero "&TEXT(L64,"#,##0")&" kg no pasan filtro "&Stock_Seguridad!O64&": sin ellos queda bajo el SS para esa cadena. ","")&IF(E64="SOBRE MAX VENDIBLE","Sobrestock vs vida útil: frenar producción/activar venta. ","")&IF(N(N64)>=Parametros!$B$17,TEXT(N64,"#,##0")&" kg ya no los acepta ninguna cadena: venta intermedia/liquidación. ","")&IF(N(M64)>=Parametros!$B$17,TEXT(M64,"#,##0")&" kg a punto de salir del filtro: despachar primero (FEFO). ","")&IF(Y64="SÍ","Pedidos "&IF(N(U64)>0,"sobre","bajo")&" FCST "&TEXT(ABS(N(U64)),"0%")&": revisar forecast con KAM.","") -> Pedidos bajo FCST 39%: revisar forecast con KAM.
A65: =Stock_Seguridad!A65 -> 30001376 | B65: =Stock_Seguridad!B65 -> LECHE LONCO FULL PROTEIN CHOCOLATE18X250 | C65: =Stock_Seguridad!C65 -> LECHES LIQUIDAS | D65: =Stock_Seguridad!F65 -> CX | E65: =Stock_Seguridad!X65 -> OK | F65: =Stock_Seguridad!W65 -> 2.4739821 | G65: =Stock_Seguridad!T65 -> 11101.5 | H65: =Stock_Seguridad!R65 -> 1021.1585 | I65: =Stock_Seguridad!S65 -> 5508.4585 | J65: =Stock_Seguridad!U65 -> 0 | L65: 945 | M65: 0 | N65: 756 | O65: 0.13323732 | P65: =IF(ISNUMBER(Stock_Seguridad!N65),Stock_Seguridad!N65,"") -> 0.21164021 | Q65: =IF(AND(ISNUMBER(O65),ISNUMBER(P65)),P65-O65,"") -> 0.078402889 | R65: =MAX(0,G65-N(L65)) -> 10156.5 | S65: =SUMIFS(Cadenas_vs_FCST!$D$17:$D$652,Cadenas_vs_FCST!$A$17:$A$652,A65) -> 16731 | T65: =SUMIFS(Cadenas_vs_FCST!$E$17:$E$652,Cadenas_vs_FCST!$A$17:$A$652,A65) -> 17029.618 | U65: =IF(T65>0,S65/T65-1,"") -> -0.017535234 | V65: =IF(OR(E65="BAJO SS",E65="BAJO SS (XLIB CUBRE)"),"SÍ","") | W65: =IF(AND(V65="",N(L65)>=Parametros!$B$17,G65>=H65,R65<H65),"SÍ","") | X65: =IF(OR(E65="SOBRE MAX VENDIBLE",N(N65)>=Parametros!$B$17,N(M65)>=Parametros!$B$17),"SÍ","") -> SÍ | Y65: =IF(AND(ISNUMBER(U65),MAX(S65,T65)>=Parametros!$B$15,ABS(N(U65))>Parametros!$B$14),"SÍ","") | Z65: =COUNTIF(V65:Y65,"SÍ") -> 1 | AA65: =(3*(V65="SÍ")+2*(W65="SÍ")+2*(X65="SÍ")+(Y65="SÍ"))*IF(LEFT(D65,1)="A",3,IF(OR(LEFT(D65,1)="B",D65="SIN HIST"),2,1)) -> 2 | AB65: =IF(AA65>=9,"1-ALTA",IF(AA65>=4,"2-MEDIA",IF(AA65>0,"3-BAJA",""))) -> 3-BAJA | AC65: =IF(E65="BAJO SS","Stock + XLIB bajo el SS: riesgo real de quiebre, adelantar producción. ","")&IF(E65="BAJO SS (XLIB CUBRE)","Disponible bajo el SS; depende de liberar "&TEXT(J65,"#,##0")&" kg"&IF(ISNUMBER(K65)," el "&TEXT(K65,"dd-mm"),"")&". ","")&IF(W65="SÍ","Stock parece sano pero "&TEXT(L65,"#,##0")&" kg no pasan filtro "&Stock_Seguridad!O65&": sin ellos queda bajo el SS para esa cadena. ","")&IF(E65="SOBRE MAX VENDIBLE","Sobrestock vs vida útil: frenar producción/activar venta. ","")&IF(N(N65)>=Parametros!$B$17,TEXT(N65,"#,##0")&" kg ya no los acepta ninguna cadena: venta intermedia/liquidación. ","")&IF(N(M65)>=Parametros!$B$17,TEXT(M65,"#,##0")&" kg a punto de salir del filtro: despachar primero (FEFO). ","")&IF(Y65="SÍ","Pedidos "&IF(N(U65)>0,"sobre","bajo")&" FCST "&TEXT(ABS(N(U65)),"0%")&": revisar forecast con KAM.","") -> 756 kg ya no los acepta ninguna cadena: venta intermedia/liquidación.
A66: =Stock_Seguridad!A66 -> 30001405 | B66: =Stock_Seguridad!B66 -> LECHE BREAK CARAMEL LONCO 18X250ML | C66: =Stock_Seguridad!C66 -> LECHES LIQUIDAS | D66: =Stock_Seguridad!F66 -> BX | E66: =Stock_Seguridad!X66 -> BAJO SS (XLIB CUBRE) | F66: =Stock_Seguridad!W66 -> 3.7016296 | G66: =Stock_Seguridad!T66 -> 1800 | H66: =Stock_Seguridad!R66 -> 1861.2728 | I66: =Stock_Seguridad!S66 -> 6218.2728 | J66: =Stock_Seguridad!U66 -> 14328 | K66: 46321 | L66: 225 | M66: 1566 | N66: 0 | O66: 0.019034059 | P66: =IF(ISNUMBER(Stock_Seguridad!N66),Stock_Seguridad!N66,"") -> 0.208 | Q66: =IF(AND(ISNUMBER(O66),ISNUMBER(P66)),P66-O66,"") -> 0.18896594 | R66: =MAX(0,G66-N(L66)) -> 1575 | S66: =SUMIFS(Cadenas_vs_FCST!$D$17:$D$652,Cadenas_vs_FCST!$A$17:$A$652,A66) -> 17856 | T66: =SUMIFS(Cadenas_vs_FCST!$E$17:$E$652,Cadenas_vs_FCST!$A$17:$A$652,A66) -> 14799.59 | U66: =IF(T66>0,S66/T66-1,"") -> 0.20651991 | V66: =IF(OR(E66="BAJO SS",E66="BAJO SS (XLIB CUBRE)"),"SÍ","") -> SÍ | W66: =IF(AND(V66="",N(L66)>=Parametros!$B$17,G66>=H66,R66<H66),"SÍ","") | X66: =IF(OR(E66="SOBRE MAX VENDIBLE",N(N66)>=Parametros!$B$17,N(M66)>=Parametros!$B$17),"SÍ","") -> SÍ | Y66: =IF(AND(ISNUMBER(U66),MAX(S66,T66)>=Parametros!$B$15,ABS(N(U66))>Parametros!$B$14),"SÍ","") -> SÍ | Z66: =COUNTIF(V66:Y66,"SÍ") -> 3 | AA66: =(3*(V66="SÍ")+2*(W66="SÍ")+2*(X66="SÍ")+(Y66="SÍ"))*IF(LEFT(D66,1)="A",3,IF(OR(LEFT(D66,1)="B",D66="SIN HIST"),2,1)) -> 12 | AB66: =IF(AA66>=9,"1-ALTA",IF(AA66>=4,"2-MEDIA",IF(AA66>0,"3-BAJA",""))) -> 1-ALTA | AC66: =IF(E66="BAJO SS","Stock + XLIB bajo el SS: riesgo real de quiebre, adelantar producción. ","")&IF(E66="BAJO SS (XLIB CUBRE)","Disponible bajo el SS; depende de liberar "&TEXT(J66,"#,##0")&" kg"&IF(ISNUMBER(K66)," el "&TEXT(K66,"dd-mm"),"")&". ","")&IF(W66="SÍ","Stock parece sano pero "&TEXT(L66,"#,##0")&" kg no pasan filtro "&Stock_Seguridad!O66&": sin ellos queda bajo el SS para esa cadena. ","")&IF(E66="SOBRE MAX VENDIBLE","Sobrestock vs vida útil: frenar producción/activar venta. ","")&IF(N(N66)>=Parametros!$B$17,TEXT(N66,"#,##0")&" kg ya no los acepta ninguna cadena: venta intermedia/liquidación. ","")&IF(N(M66)>=Parametros!$B$17,TEXT(M66,"#,##0")&" kg a punto de salir del filtro: despachar primero (FEFO). ","")&IF(Y66="SÍ","Pedidos "&IF(N(U66)>0,"sobre","bajo")&" FCST "&TEXT(ABS(N(U66)),"0%")&": revisar forecast con KAM.","") -> Disponible bajo el SS; depende de liberar 14,328 kg el 26-10. 1,566 kg a punto de salir del filtro: despachar primero (FEFO). Pedidos sobre FCST 21%: revisar forecast con KAM.
A67: =Stock_Seguridad!A67 -> 30000351 | B67: =Stock_Seguridad!B67 -> LECHE VAINILLA 30X200ML | C67: =Stock_Seguridad!C67 -> LECHES LIQUIDAS | D67: =Stock_Seguridad!F67 -> BX | E67: =Stock_Seguridad!X67 -> SOBRE MAX VENDIBLE | F67: =Stock_Seguridad!W67 -> 8.772543 | G67: =Stock_Seguridad!T67 -> 16116 | H67: =Stock_Seguridad!R67 -> 1474.6994 | I67: =Stock_Seguridad!S67 -> 5766.4994 | J67: =Stock_Seguridad!U67 -> 21534 | K67: 46321 | L67: 228 | M67: 15186 | N67: 78 | O67: 0.08009581 | P67: =IF(ISNUMBER(Stock_Seguridad!N67),Stock_Seguridad!N67,"") -> 0.23831776 | Q67: =IF(AND(ISNUMBER(O67),ISNUMBER(P67)),P67-O67,"") -> 0.15822195 | R67: =MAX(0,G67-N(L67)) -> 15888 | S67: =SUMIFS(Cadenas_vs_FCST!$D$17:$D$652,Cadenas_vs_FCST!$A$17:$A$652,A67) -> 17784 | T67: =SUMIFS(Cadenas_vs_FCST!$E$17:$E$652,Cadenas_vs_FCST!$A$17:$A$652,A67) -> 15971.182 | U67: =IF(T67>0,S67/T67-1,"") -> 0.11350554 | V67: =IF(OR(E67="BAJO SS",E67="BAJO SS (XLIB CUBRE)"),"SÍ","") | W67: =IF(AND(V67="",N(L67)>=Parametros!$B$17,G67>=H67,R67<H67),"SÍ","") | X67: =IF(OR(E67="SOBRE MAX VENDIBLE",N(N67)>=Parametros!$B$17,N(M67)>=Parametros!$B$17),"SÍ","") -> SÍ | Y67: =IF(AND(ISNUMBER(U67),MAX(S67,T67)>=Parametros!$B$15,ABS(N(U67))>Parametros!$B$14),"SÍ","") | Z67: =COUNTIF(V67:Y67,"SÍ") -> 1 | AA67: =(3*(V67="SÍ")+2*(W67="SÍ")+2*(X67="SÍ")+(Y67="SÍ"))*IF(LEFT(D67,1)="A",3,IF(OR(LEFT(D67,1)="B",D67="SIN HIST"),2,1)) -> 4 | AB67: =IF(AA67>=9,"1-ALTA",IF(AA67>=4,"2-MEDIA",IF(AA67>0,"3-BAJA",""))) -> 2-MEDIA | AC67: =IF(E67="BAJO SS","Stock + XLIB bajo el SS: riesgo real de quiebre, adelantar producción. ","")&IF(E67="BAJO SS (XLIB CUBRE)","Disponible bajo el SS; depende de liberar "&TEXT(J67,"#,##0")&" kg"&IF(ISNUMBER(K67)," el "&TEXT(K67,"dd-mm"),"")&". ","")&IF(W67="SÍ","Stock parece sano pero "&TEXT(L67,"#,##0")&" kg no pasan filtro "&Stock_Seguridad!O67&": sin ellos queda bajo el SS para esa cadena. ","")&IF(E67="SOBRE MAX VENDIBLE","Sobrestock vs vida útil: frenar producción/activar venta. ","")&IF(N(N67)>=Parametros!$B$17,TEXT(N67,"#,##0")&" kg ya no los acepta ninguna cadena: venta intermedia/liquidación. ","")&IF(N(M67)>=Parametros!$B$17,TEXT(M67,"#,##0")&" kg a punto de salir del filtro: despachar primero (FEFO). ","")&IF(Y67="SÍ","Pedidos "&IF(N(U67)>0,"sobre","bajo")&" FCST "&TEXT(ABS(N(U67)),"0%")&": revisar forecast con KAM.","") -> Sobrestock vs vida útil: frenar producción/activar venta. 15,186 kg a punto de salir del filtro: despachar primero (FEFO).
A68: =Stock_Seguridad!A68 -> 30000360 | B68: =Stock_Seguridad!B68 -> LECHE S/LACT EXTRA CALCIO 12X1LT | C68: =Stock_Seguridad!C68 -> LECHES LIQUIDAS | D68: =Stock_Seguridad!F68 -> BY | E68: =Stock_Seguridad!X68 -> OK | F68: =Stock_Seguridad!W68 -> 6.2955616 | G68: =Stock_Seguridad!T68 -> 13308 | H68: =Stock_Seguridad!R68 -> 4397.9211 | I68: =Stock_Seguridad!S68 -> 8581.8211 | J68: =Stock_Seguridad!U68 -> 13032 | K68: 46319 | L68: 0 | M68: 1020 | N68: 0 | O68: 0.084838121 | P68: =IF(ISNUMBER(Stock_Seguridad!N68),Stock_Seguridad!N68,"") -> 0.25925926 | Q68: =IF(AND(ISNUMBER(O68),ISNUMBER(P68)),P68-O68,"") -> 0.17442114 | R68: =MAX(0,G68-N(L68)) -> 13308 | S68: =SUMIFS(Cadenas_vs_FCST!$D$17:$D$652,Cadenas_vs_FCST!$A$17:$A$652,A68) -> 18804 | T68: =SUMIFS(Cadenas_vs_FCST!$E$17:$E$652,Cadenas_vs_FCST!$A$17:$A$652,A68) -> 17771.293 | U68: =IF(T68>0,S68/T68-1,"") -> 0.058110962 | V68: =IF(OR(E68="BAJO SS",E68="BAJO SS (XLIB CUBRE)"),"SÍ","") | W68: =IF(AND(V68="",N(L68)>=Parametros!$B$17,G68>=H68,R68<H68),"SÍ","") | X68: =IF(OR(E68="SOBRE MAX VENDIBLE",N(N68)>=Parametros!$B$17,N(M68)>=Parametros!$B$17),"SÍ","") -> SÍ | Y68: =IF(AND(ISNUMBER(U68),MAX(S68,T68)>=Parametros!$B$15,ABS(N(U68))>Parametros!$B$14),"SÍ","") | Z68: =COUNTIF(V68:Y68,"SÍ") -> 1 | AA68: =(3*(V68="SÍ")+2*(W68="SÍ")+2*(X68="SÍ")+(Y68="SÍ"))*IF(LEFT(D68,1)="A",3,IF(OR(LEFT(D68,1)="B",D68="SIN HIST"),2,1)) -> 4 | AB68: =IF(AA68>=9,"1-ALTA",IF(AA68>=4,"2-MEDIA",IF(AA68>0,"3-BAJA",""))) -> 2-MEDIA | AC68: =IF(E68="BAJO SS","Stock + XLIB bajo el SS: riesgo real de quiebre, adelantar producción. ","")&IF(E68="BAJO SS (XLIB CUBRE)","Disponible bajo el SS; depende de liberar "&TEXT(J68,"#,##0")&" kg"&IF(ISNUMBER(K68)," el "&TEXT(K68,"dd-mm"),"")&". ","")&IF(W68="SÍ","Stock parece sano pero "&TEXT(L68,"#,##0")&" kg no pasan filtro "&Stock_Seguridad!O68&": sin ellos queda bajo el SS para esa cadena. ","")&IF(E68="SOBRE MAX VENDIBLE","Sobrestock vs vida útil: frenar producción/activar venta. ","")&IF(N(N68)>=Parametros!$B$17,TEXT(N68,"#,##0")&" kg ya no los acepta ninguna cadena: venta intermedia/liquidación. ","")&IF(N(M68)>=Parametros!$B$17,TEXT(M68,"#,##0")&" kg a punto de salir del filtro: despachar primero (FEFO). ","")&IF(Y68="SÍ","Pedidos "&IF(N(U68)>0,"sobre","bajo")&" FCST "&TEXT(ABS(N(U68)),"0%")&": revisar forecast con KAM.","") -> 1,020 kg a punto de salir del filtro: despachar primero (FEFO).
A69: =Stock_Seguridad!A69 -> 30001980 | B69: =Stock_Seguridad!B69 -> LECHE FULL PRO CAPPUCCINO LONCO 18X250ML | C69: =Stock_Seguridad!C69 -> LECHES LIQUIDAS | D69: =Stock_Seguridad!F69 -> BX | E69: =Stock_Seguridad!X69 -> OK | F69: =Stock_Seguridad!W69 -> 5.4690832 | G69: =Stock_Seguridad!T69 -> 22572 | H69: =Stock_Seguridad!R69 -> 1657.9867 | I69: =Stock_Seguridad!S69 -> 5785.1867 | J69: =Stock_Seguridad!U69 -> 0 | L69: 0 | M69: 54 | N69: 0 | O69: 0.060283094 | P69: =IF(ISNUMBER(Stock_Seguridad!N69),Stock_Seguridad!N69,"") -> 0.30687831 | Q69: =IF(AND(ISNUMBER(O69),ISNUMBER(P69)),P69-O69,"") -> 0.24659521 | R69: =MAX(0,G69-N(L69)) -> 22572 | S69: =SUMIFS(Cadenas_vs_FCST!$D$17:$D$652,Cadenas_vs_FCST!$A$17:$A$652,A69) -> 18526.5 | T69: =SUMIFS(Cadenas_vs_FCST!$E$17:$E$652,Cadenas_vs_FCST!$A$17:$A$652,A69) -> 18554.158 | U69: =IF(T69>0,S69/T69-1,"") -> -0.0014906665 | V69: =IF(OR(E69="BAJO SS",E69="BAJO SS (XLIB CUBRE)"),"SÍ","") | W69: =IF(AND(V69="",N(L69)>=Parametros!$B$17,G69>=H69,R69<H69),"SÍ","") | X69: =IF(OR(E69="SOBRE MAX VENDIBLE",N(N69)>=Parametros!$B$17,N(M69)>=Parametros!$B$17),"SÍ","") | Y69: =IF(AND(ISNUMBER(U69),MAX(S69,T69)>=Parametros!$B$15,ABS(N(U69))>Parametros!$B$14),"SÍ","") | Z69: =COUNTIF(V69:Y69,"SÍ") -> 0 | AA69: =(3*(V69="SÍ")+2*(W69="SÍ")+2*(X69="SÍ")+(Y69="SÍ"))*IF(LEFT(D69,1)="A",3,IF(OR(LEFT(D69,1)="B",D69="SIN HIST"),2,1)) -> 0 | AB69: =IF(AA69>=9,"1-ALTA",IF(AA69>=4,"2-MEDIA",IF(AA69>0,"3-BAJA",""))) | AC69: =IF(E69="BAJO SS","Stock + XLIB bajo el SS: riesgo real de quiebre, adelantar producción. ","")&IF(E69="BAJO SS (XLIB CUBRE)","Disponible bajo el SS; depende de liberar "&TEXT(J69,"#,##0")&" kg"&IF(ISNUMBER(K69)," el "&TEXT(K69,"dd-mm"),"")&". ","")&IF(W69="SÍ","Stock parece sano pero "&TEXT(L69,"#,##0")&" kg no pasan filtro "&Stock_Seguridad!O69&": sin ellos queda bajo el SS para esa cadena. ","")&IF(E69="SOBRE MAX VENDIBLE","Sobrestock vs vida útil: frenar producción/activar venta. ","")&IF(N(N69)>=Parametros!$B$17,TEXT(N69,"#,##0")&" kg ya no los acepta ninguna cadena: venta intermedia/liquidación. ","")&IF(N(M69)>=Parametros!$B$17,TEXT(M69,"#,##0")&" kg a punto de salir del filtro: despachar primero (FEFO). ","")&IF(Y69="SÍ","Pedidos "&IF(N(U69)>0,"sobre","bajo")&" FCST "&TEXT(ABS(N(U69)),"0%")&": revisar forecast con KAM.","")
A70: =Stock_Seguridad!A70 -> 30001992 | B70: =Stock_Seguridad!B70 -> LECHE LONCOLECHE BREAK CARAMEL 12X1LT | C70: =Stock_Seguridad!C70 -> LECHES LIQUIDAS | D70: =Stock_Seguridad!F70 -> CX | E70: =Stock_Seguridad!X70 -> OK | F70: =Stock_Seguridad!W70 -> 6.1140216 | G70: =Stock_Seguridad!T70 -> 9468 | H70: =Stock_Seguridad!R70 -> 1430.0271 | I70: =Stock_Seguridad!S70 -> 5324.0271 | J70: =Stock_Seguridad!U70 -> 14340 | K70: 46317 | L70: 576 | M70: 444 | N70: 348 | O70: 0.066688508 | P70: =IF(ISNUMBER(Stock_Seguridad!N70),Stock_Seguridad!N70,"") -> 0.268 | Q70: =IF(AND(ISNUMBER(O70),ISNUMBER(P70)),P70-O70,"") -> 0.20131149 | R70: =MAX(0,G70-N(L70)) -> 8892 | S70: =SUMIFS(Cadenas_vs_FCST!$D$17:$D$652,Cadenas_vs_FCST!$A$17:$A$652,A70) -> 8880 | T70: =SUMIFS(Cadenas_vs_FCST!$E$17:$E$652,Cadenas_vs_FCST!$A$17:$A$652,A70) -> 12493.555 | U70: =IF(T70>0,S70/T70-1,"") -> -0.28923355 | V70: =IF(OR(E70="BAJO SS",E70="BAJO SS (XLIB CUBRE)"),"SÍ","") | W70: =IF(AND(V70="",N(L70)>=Parametros!$B$17,G70>=H70,R70<H70),"SÍ","") | X70: =IF(OR(E70="SOBRE MAX VENDIBLE",N(N70)>=Parametros!$B$17,N(M70)>=Parametros!$B$17),"SÍ","") | Y70: =IF(AND(ISNUMBER(U70),MAX(S70,T70)>=Parametros!$B$15,ABS(N(U70))>Parametros!$B$14),"SÍ","") -> SÍ | Z70: =COUNTIF(V70:Y70,"SÍ") -> 1 | AA70: =(3*(V70="SÍ")+2*(W70="SÍ")+2*(X70="SÍ")+(Y70="SÍ"))*IF(LEFT(D70,1)="A",3,IF(OR(LEFT(D70,1)="B",D70="SIN HIST"),2,1)) -> 1 | AB70: =IF(AA70>=9,"1-ALTA",IF(AA70>=4,"2-MEDIA",IF(AA70>0,"3-BAJA",""))) -> 3-BAJA | AC70: =IF(E70="BAJO SS","Stock + XLIB bajo el SS: riesgo real de quiebre, adelantar producción. ","")&IF(E70="BAJO SS (XLIB CUBRE)","Disponible bajo el SS; depende de liberar "&TEXT(J70,"#,##0")&" kg"&IF(ISNUMBER(K70)," el "&TEXT(K70,"dd-mm"),"")&". ","")&IF(W70="SÍ","Stock parece sano pero "&TEXT(L70,"#,##0")&" kg no pasan filtro "&Stock_Seguridad!O70&": sin ellos queda bajo el SS para esa cadena. ","")&IF(E70="SOBRE MAX VENDIBLE","Sobrestock vs vida útil: frenar producción/activar venta. ","")&IF(N(N70)>=Parametros!$B$17,TEXT(N70,"#,##0")&" kg ya no los acepta ninguna cadena: venta intermedia/liquidación. ","")&IF(N(M70)>=Parametros!$B$17,TEXT(M70,"#,##0")&" kg a punto de salir del filtro: despachar primero (FEFO). ","")&IF(Y70="SÍ","Pedidos "&IF(N(U70)>0,"sobre","bajo")&" FCST "&TEXT(ABS(N(U70)),"0%")&": revisar forecast con KAM.","") -> Pedidos bajo FCST 29%: revisar forecast con KAM.
A71: =Stock_Seguridad!A71 -> 30000246 | B71: =Stock_Seguridad!B71 -> NECTAR WATTS DURAZNO 12X1LT | C71: =Stock_Seguridad!C71 -> JUGOS Y NECTARES | D71: =Stock_Seguridad!F71 -> CX | E71: =Stock_Seguridad!X71 -> OK | F71: =Stock_Seguridad!W71 -> 3.7772549 | G71: =Stock_Seguridad!T71 -> 14448 | H71: =Stock_Seguridad!R71 -> 1296.5279 | I71: =Stock_Seguridad!S71 -> 5121.5279 | J71: =Stock_Seguridad!U71 -> 0 | L71: 0 | M71: 0 | N71: 0 | O71: 0.033405316 | P71: =IF(ISNUMBER(Stock_Seguridad!N71),Stock_Seguridad!N71,"") -> 0.19452055 | Q71: =IF(AND(ISNUMBER(O71),ISNUMBER(P71)),P71-O71,"") -> 0.16111523 | R71: =MAX(0,G71-N(L71)) -> 14448 | S71: =SUMIFS(Cadenas_vs_FCST!$D$17:$D$652,Cadenas_vs_FCST!$A$17:$A$652,A71) -> 12504 | T71: =SUMIFS(Cadenas_vs_FCST!$E$17:$E$652,Cadenas_vs_FCST!$A$17:$A$652,A71) -> 16459.392 | U71: =IF(T71>0,S71/T71-1,"") -> -0.24031214 | V71: =IF(OR(E71="BAJO SS",E71="BAJO SS (XLIB CUBRE)"),"SÍ","") | W71: =IF(AND(V71="",N(L71)>=Parametros!$B$17,G71>=H71,R71<H71),"SÍ","") | X71: =IF(OR(E71="SOBRE MAX VENDIBLE",N(N71)>=Parametros!$B$17,N(M71)>=Parametros!$B$17),"SÍ","") | Y71: =IF(AND(ISNUMBER(U71),MAX(S71,T71)>=Parametros!$B$15,ABS(N(U71))>Parametros!$B$14),"SÍ","") -> SÍ | Z71: =COUNTIF(V71:Y71,"SÍ") -> 1 | AA71: =(3*(V71="SÍ")+2*(W71="SÍ")+2*(X71="SÍ")+(Y71="SÍ"))*IF(LEFT(D71,1)="A",3,IF(OR(LEFT(D71,1)="B",D71="SIN HIST"),2,1)) -> 1 | AB71: =IF(AA71>=9,"1-ALTA",IF(AA71>=4,"2-MEDIA",IF(AA71>0,"3-BAJA",""))) -> 3-BAJA | AC71: =IF(E71="BAJO SS","Stock + XLIB bajo el SS: riesgo real de quiebre, adelantar producción. ","")&IF(E71="BAJO SS (XLIB CUBRE)","Disponible bajo el SS; depende de liberar "&TEXT(J71,"#,##0")&" kg"&IF(ISNUMBER(K71)," el "&TEXT(K71,"dd-mm"),"")&". ","")&IF(W71="SÍ","Stock parece sano pero "&TEXT(L71,"#,##0")&" kg no pasan filtro "&Stock_Seguridad!O71&": sin ellos queda bajo el SS para esa cadena. ","")&IF(E71="SOBRE MAX VENDIBLE","Sobrestock vs vida útil: frenar producción/activar venta. ","")&IF(N(N71)>=Parametros!$B$17,TEXT(N71,"#,##0")&" kg ya no los acepta ninguna cadena: venta intermedia/liquidación. ","")&IF(N(M71)>=Parametros!$B$17,TEXT(M71,"#,##0")&" kg a punto de salir del filtro: despachar primero (FEFO). ","")&IF(Y71="SÍ","Pedidos "&IF(N(U71)>0,"sobre","bajo")&" FCST "&TEXT(ABS(N(U71)),"0%")&": revisar forecast con KAM.","") -> Pedidos bajo FCST 24%: revisar forecast con KAM.
A72: =Stock_Seguridad!A72 -> 30000334 | B72: =Stock_Seguridad!B72 -> CREMA BATIR LONCO 12X1LT | C72: =Stock_Seguridad!C72 -> CREMA | D72: =Stock_Seguridad!F72 -> CX | E72: =Stock_Seguridad!X72 -> OK | F72: =Stock_Seguridad!W72 -> 3.6622801 | G72: =Stock_Seguridad!T72 -> 5808 | H72: =Stock_Seguridad!R72 -> 2078.1767 | I72: =Stock_Seguridad!S72 -> 5459.6767 | J72: =Stock_Seguridad!U72 -> 6576 | K72: 46319 | L72: 0 | M72: 0 | N72: 0 | O72: 0.054015519 | P72: =IF(ISNUMBER(Stock_Seguridad!N72),Stock_Seguridad!N72,"") -> 0.27173913 | Q72: =IF(AND(ISNUMBER(O72),ISNUMBER(P72)),P72-O72,"") -> 0.21772361 | R72: =MAX(0,G72-N(L72)) -> 5808 | S72: =SUMIFS(Cadenas_vs_FCST!$D$17:$D$652,Cadenas_vs_FCST!$A$17:$A$652,A72) -> 12780 | T72: =SUMIFS(Cadenas_vs_FCST!$E$17:$E$652,Cadenas_vs_FCST!$A$17:$A$652,A72) -> 10809.444 | U72: =IF(T72>0,S72/T72-1,"") -> 0.1822995 | V72: =IF(OR(E72="BAJO SS",E72="BAJO SS (XLIB CUBRE)"),"SÍ","") | W72: =IF(AND(V72="",N(L72)>=Parametros!$B$17,G72>=H72,R72<H72),"SÍ","") | X72: =IF(OR(E72="SOBRE MAX VENDIBLE",N(N72)>=Parametros!$B$17,N(M72)>=Parametros!$B$17),"SÍ","") | Y72: =IF(AND(ISNUMBER(U72),MAX(S72,T72)>=Parametros!$B$15,ABS(N(U72))>Parametros!$B$14),"SÍ","") | Z72: =COUNTIF(V72:Y72,"SÍ") -> 0 | AA72: =(3*(V72="SÍ")+2*(W72="SÍ")+2*(X72="SÍ")+(Y72="SÍ"))*IF(LEFT(D72,1)="A",3,IF(OR(LEFT(D72,1)="B",D72="SIN HIST"),2,1)) -> 0 | AB72: =IF(AA72>=9,"1-ALTA",IF(AA72>=4,"2-MEDIA",IF(AA72>0,"3-BAJA",""))) | AC72: =IF(E72="BAJO SS","Stock + XLIB bajo el SS: riesgo real de quiebre, adelantar producción. ","")&IF(E72="BAJO SS (XLIB CUBRE)","Disponible bajo el SS; depende de liberar "&TEXT(J72,"#,##0")&" kg"&IF(ISNUMBER(K72)," el "&TEXT(K72,"dd-mm"),"")&". ","")&IF(W72="SÍ","Stock parece sano pero "&TEXT(L72,"#,##0")&" kg no pasan filtro "&Stock_Seguridad!O72&": sin ellos queda bajo el SS para esa cadena. ","")&IF(E72="SOBRE MAX VENDIBLE","Sobrestock vs vida útil: frenar producción/activar venta. ","")&IF(N(N72)>=Parametros!$B$17,TEXT(N72,"#,##0")&" kg ya no los acepta ninguna cadena: venta intermedia/liquidación. ","")&IF(N(M72)>=Parametros!$B$17,TEXT(M72,"#,##0")&" kg a punto de salir del filtro: despachar primero (FEFO). ","")&IF(Y72="SÍ","Pedidos "&IF(N(U72)>0,"sobre","bajo")&" FCST "&TEXT(ABS(N(U72)),"0%")&": revisar forecast con KAM.","")
A73: =Stock_Seguridad!A73 -> 30002292 | B73: =Stock_Seguridad!B73 -> JUGO 100% WATTS TUTTIMANGO LV 30X200ML | C73: =Stock_Seguridad!C73 -> JUGOS Y NECTARES | D73: =Stock_Seguridad!F73 -> CX | E73: =Stock_Seguridad!X73 -> OK | F73: =Stock_Seguridad!W73 -> 2.2349202 | G73: =Stock_Seguridad!T73 -> 7314 | H73: =Stock_Seguridad!R73 -> 1471.384 | I73: =Stock_Seguridad!S73 -> 4743.984 | J73: =Stock_Seguridad!U73 -> 0 | L73: 0 | M73: 0 | N73: 0 | O73: 0.052223134 | P73: =IF(ISNUMBER(Stock_Seguridad!N73),Stock_Seguridad!N73,"") | Q73: =IF(AND(ISNUMBER(O73),ISNUMBER(P73)),P73-O73,"") | R73: =MAX(0,G73-N(L73)) -> 7314 | S73: =SUMIFS(Cadenas_vs_FCST!$D$17:$D$652,Cadenas_vs_FCST!$A$17:$A$652,A73) -> 14004 | T73: =SUMIFS(Cadenas_vs_FCST!$E$17:$E$652,Cadenas_vs_FCST!$A$17:$A$652,A73) -> 10905.339 | U73: =IF(T73>0,S73/T73-1,"") -> 0.28414166 | V73: =IF(OR(E73="BAJO SS",E73="BAJO SS (XLIB CUBRE)"),"SÍ","") | W73: =IF(AND(V73="",N(L73)>=Parametros!$B$17,G73>=H73,R73<H73),"SÍ","") | X73: =IF(OR(E73="SOBRE MAX VENDIBLE",N(N73)>=Parametros!$B$17,N(M73)>=Parametros!$B$17),"SÍ","") | Y73: =IF(AND(ISNUMBER(U73),MAX(S73,T73)>=Parametros!$B$15,ABS(N(U73))>Parametros!$B$14),"SÍ","") -> SÍ | Z73: =COUNTIF(V73:Y73,"SÍ") -> 1 | AA73: =(3*(V73="SÍ")+2*(W73="SÍ")+2*(X73="SÍ")+(Y73="SÍ"))*IF(LEFT(D73,1)="A",3,IF(OR(LEFT(D73,1)="B",D73="SIN HIST"),2,1)) -> 1 | AB73: =IF(AA73>=9,"1-ALTA",IF(AA73>=4,"2-MEDIA",IF(AA73>0,"3-BAJA",""))) -> 3-BAJA | AC73: =IF(E73="BAJO SS","Stock + XLIB bajo el SS: riesgo real de quiebre, adelantar producción. ","")&IF(E73="BAJO SS (XLIB CUBRE)","Disponible bajo el SS; depende de liberar "&TEXT(J73,"#,##0")&" kg"&IF(ISNUMBER(K73)," el "&TEXT(K73,"dd-mm"),"")&". ","")&IF(W73="SÍ","Stock parece sano pero "&TEXT(L73,"#,##0")&" kg no pasan filtro "&Stock_Seguridad!O73&": sin ellos queda bajo el SS para esa cadena. ","")&IF(E73="SOBRE MAX VENDIBLE","Sobrestock vs vida útil: frenar producción/activar venta. ","")&IF(N(N73)>=Parametros!$B$17,TEXT(N73,"#,##0")&" kg ya no los acepta ninguna cadena: venta intermedia/liquidación. ","")&IF(N(M73)>=Parametros!$B$17,TEXT(M73,"#,##0")&" kg a punto de salir del filtro: despachar primero (FEFO). ","")&IF(Y73="SÍ","Pedidos "&IF(N(U73)>0,"sobre","bajo")&" FCST "&TEXT(ABS(N(U73)),"0%")&": revisar forecast con KAM.","") -> Pedidos sobre FCST 28%: revisar forecast con KAM.
A74: =Stock_Seguridad!A74 -> 30000245 | B74: =Stock_Seguridad!B74 -> NECTAR WATTS MANZANA 12X1LT | C74: =Stock_Seguridad!C74 -> JUGOS Y NECTARES | D74: =Stock_Seguridad!F74 -> BX | E74: =Stock_Seguridad!X74 -> OK | F74: =Stock_Seguridad!W74 -> 10.13124 | G74: =Stock_Seguridad!T74 -> 32268 | H74: =Stock_Seguridad!R74 -> 3499.5158 | I74: =Stock_Seguridad!S74 -> 6684.5158 | J74: =Stock_Seguridad!U74 -> 0 | L74: 240 | M74: 10500 | N74: 0 | O74: 0.061995532 | P74: =IF(ISNUMBER(Stock_Seguridad!N74),Stock_Seguridad!N74,"") -> 0.19452055 | Q74: =IF(AND(ISNUMBER(O74),ISNUMBER(P74)),P74-O74,"") -> 0.13252502 | R74: =MAX(0,G74-N(L74)) -> 32028 | S74: =SUMIFS(Cadenas_vs_FCST!$D$17:$D$652,Cadenas_vs_FCST!$A$17:$A$652,A74) -> 12408 | T74: =SUMIFS(Cadenas_vs_FCST!$E$17:$E$652,Cadenas_vs_FCST!$A$17:$A$652,A74) -> 13608.117 | U74: =IF(T74>0,S74/T74-1,"") -> -0.088191248 | V74: =IF(OR(E74="BAJO SS",E74="BAJO SS (XLIB CUBRE)"),"SÍ","") | W74: =IF(AND(V74="",N(L74)>=Parametros!$B$17,G74>=H74,R74<H74),"SÍ","") | X74: =IF(OR(E74="SOBRE MAX VENDIBLE",N(N74)>=Parametros!$B$17,N(M74)>=Parametros!$B$17),"SÍ","") -> SÍ | Y74: =IF(AND(ISNUMBER(U74),MAX(S74,T74)>=Parametros!$B$15,ABS(N(U74))>Parametros!$B$14),"SÍ","") | Z74: =COUNTIF(V74:Y74,"SÍ") -> 1 | AA74: =(3*(V74="SÍ")+2*(W74="SÍ")+2*(X74="SÍ")+(Y74="SÍ"))*IF(LEFT(D74,1)="A",3,IF(OR(LEFT(D74,1)="B",D74="SIN HIST"),2,1)) -> 4 | AB74: =IF(AA74>=9,"1-ALTA",IF(AA74>=4,"2-MEDIA",IF(AA74>0,"3-BAJA",""))) -> 2-MEDIA | AC74: =IF(E74="BAJO SS","Stock + XLIB bajo el SS: riesgo real de quiebre, adelantar producción. ","")&IF(E74="BAJO SS (XLIB CUBRE)","Disponible bajo el SS; depende de liberar "&TEXT(J74,"#,##0")&" kg"&IF(ISNUMBER(K74)," el "&TEXT(K74,"dd-mm"),"")&". ","")&IF(W74="SÍ","Stock parece sano pero "&TEXT(L74,"#,##0")&" kg no pasan filtro "&Stock_Seguridad!O74&": sin ellos queda bajo el SS para esa cadena. ","")&IF(E74="SOBRE MAX VENDIBLE","Sobrestock vs vida útil: frenar producción/activar venta. ","")&IF(N(N74)>=Parametros!$B$17,TEXT(N74,"#,##0")&" kg ya no los acepta ninguna cadena: venta intermedia/liquidación. ","")&IF(N(M74)>=Parametros!$B$17,TEXT(M74,"#,##0")&" kg a punto de salir del filtro: despachar primero (FEFO). ","")&IF(Y74="SÍ","Pedidos "&IF(N(U74)>0,"sobre","bajo")&" FCST "&TEXT(ABS(N(U74)),"0%")&": revisar forecast con KAM.","") -> 10,500 kg a punto de salir del filtro: despachar primero (FEFO).
A75: =Stock_Seguridad!A75 -> 30001925 | B75: =Stock_Seguridad!B75 -> LECHE CHOCOLATE LONCOLECHE 30X115ML | C75: =Stock_Seguridad!C75 -> LECHES LIQUIDAS | D75: =Stock_Seguridad!F75 -> CZ | E75: =Stock_Seguridad!X75 -> SOBRE MAX VENDIBLE | F75: =Stock_Seguridad!W75 -> 10.343427 | G75: =Stock_Seguridad!T75 -> 32654.2 | H75: =Stock_Seguridad!R75 -> 4118.8392 | I75: =Stock_Seguridad!S75 -> 7275.8392 | J75: =Stock_Seguridad!U75 -> 0 | L75: 172.5 | M75: 32481.75 | N75: 0 | O75: 0.22545272 | P75: =IF(ISNUMBER(Stock_Seguridad!N75),Stock_Seguridad!N75,"") -> 0.26635514 | Q75: =IF(AND(ISNUMBER(O75),ISNUMBER(P75)),P75-O75,"") -> 0.04090242 | R75: =MAX(0,G75-N(L75)) -> 32481.7 | S75: =SUMIFS(Cadenas_vs_FCST!$D$17:$D$652,Cadenas_vs_FCST!$A$17:$A$652,A75) -> 4795.5 | T75: =SUMIFS(Cadenas_vs_FCST!$E$17:$E$652,Cadenas_vs_FCST!$A$17:$A$652,A75) -> 12948.442 | U75: =IF(T75>0,S75/T75-1,"") -> -0.62964656 | V75: =IF(OR(E75="BAJO SS",E75="BAJO SS (XLIB CUBRE)"),"SÍ","") | W75: =IF(AND(V75="",N(L75)>=Parametros!$B$17,G75>=H75,R75<H75),"SÍ","") | X75: =IF(OR(E75="SOBRE MAX VENDIBLE",N(N75)>=Parametros!$B$17,N(M75)>=Parametros!$B$17),"SÍ","") -> SÍ | Y75: =IF(AND(ISNUMBER(U75),MAX(S75,T75)>=Parametros!$B$15,ABS(N(U75))>Parametros!$B$14),"SÍ","") -> SÍ | Z75: =COUNTIF(V75:Y75,"SÍ") -> 2 | AA75: =(3*(V75="SÍ")+2*(W75="SÍ")+2*(X75="SÍ")+(Y75="SÍ"))*IF(LEFT(D75,1)="A",3,IF(OR(LEFT(D75,1)="B",D75="SIN HIST"),2,1)) -> 3 | AB75: =IF(AA75>=9,"1-ALTA",IF(AA75>=4,"2-MEDIA",IF(AA75>0,"3-BAJA",""))) -> 3-BAJA | AC75: =IF(E75="BAJO SS","Stock + XLIB bajo el SS: riesgo real de quiebre, adelantar producción. ","")&IF(E75="BAJO SS (XLIB CUBRE)","Disponible bajo el SS; depende de liberar "&TEXT(J75,"#,##0")&" kg"&IF(ISNUMBER(K75)," el "&TEXT(K75,"dd-mm"),"")&". ","")&IF(W75="SÍ","Stock parece sano pero "&TEXT(L75,"#,##0")&" kg no pasan filtro "&Stock_Seguridad!O75&": sin ellos queda bajo el SS para esa cadena. ","")&IF(E75="SOBRE MAX VENDIBLE","Sobrestock vs vida útil: frenar producción/activar venta. ","")&IF(N(N75)>=Parametros!$B$17,TEXT(N75,"#,##0")&" kg ya no los acepta ninguna cadena: venta intermedia/liquidación. ","")&IF(N(M75)>=Parametros!$B$17,TEXT(M75,"#,##0")&" kg a punto de salir del filtro: despachar primero (FEFO). ","")&IF(Y75="SÍ","Pedidos "&IF(N(U75)>0,"sobre","bajo")&" FCST "&TEXT(ABS(N(U75)),"0%")&": revisar forecast con KAM.","") -> Sobrestock vs vida útil: frenar producción/activar venta. 32,482 kg a punto de salir del filtro: despachar primero (FEFO). Pedidos bajo FCST 63%: revisar forecast con KAM.
A76: =Stock_Seguridad!A76 -> 30002326 | B76: =Stock_Seguridad!B76 -> CREMA S/L LISTA LONCO 18X250ML | C76: =Stock_Seguridad!C76 -> CREMA | D76: =Stock_Seguridad!F76 -> CZ | E76: =Stock_Seguridad!X76 -> OK | F76: =Stock_Seguridad!W76 -> 3.18096 | G76: =Stock_Seguridad!T76 -> 9940.5 | H76: =Stock_Seguridad!R76 -> 3811.8878 | I76: =Stock_Seguridad!S76 -> 6936.8878 | J76: =Stock_Seguridad!U76 -> 0 | L76: 0 | M76: 0 | N76: 0 | O76: 0.040638298 | P76: =IF(ISNUMBER(Stock_Seguridad!N76),Stock_Seguridad!N76,"") | Q76: =IF(AND(ISNUMBER(O76),ISNUMBER(P76)),P76-O76,"") | R76: =MAX(0,G76-N(L76)) -> 9940.5 | S76: =SUMIFS(Cadenas_vs_FCST!$D$17:$D$652,Cadenas_vs_FCST!$A$17:$A$652,A76) -> 10323 | T76: =SUMIFS(Cadenas_vs_FCST!$E$17:$E$652,Cadenas_vs_FCST!$A$17:$A$652,A76) -> 6000 | U76: =IF(T76>0,S76/T76-1,"") -> 0.7205 | V76: =IF(OR(E76="BAJO SS",E76="BAJO SS (XLIB CUBRE)"),"SÍ","") | W76: =IF(AND(V76="",N(L76)>=Parametros!$B$17,G76>=H76,R76<H76),"SÍ","") | X76: =IF(OR(E76="SOBRE MAX VENDIBLE",N(N76)>=Parametros!$B$17,N(M76)>=Parametros!$B$17),"SÍ","") | Y76: =IF(AND(ISNUMBER(U76),MAX(S76,T76)>=Parametros!$B$15,ABS(N(U76))>Parametros!$B$14),"SÍ","") -> SÍ | Z76: =COUNTIF(V76:Y76,"SÍ") -> 1 | AA76: =(3*(V76="SÍ")+2*(W76="SÍ")+2*(X76="SÍ")+(Y76="SÍ"))*IF(LEFT(D76,1)="A",3,IF(OR(LEFT(D76,1)="B",D76="SIN HIST"),2,1)) -> 1 | AB76: =IF(AA76>=9,"1-ALTA",IF(AA76>=4,"2-MEDIA",IF(AA76>0,"3-BAJA",""))) -> 3-BAJA | AC76: =IF(E76="BAJO SS","Stock + XLIB bajo el SS: riesgo real de quiebre, adelantar producción. ","")&IF(E76="BAJO SS (XLIB CUBRE)","Disponible bajo el SS; depende de liberar "&TEXT(J76,"#,##0")&" kg"&IF(ISNUMBER(K76)," el "&TEXT(K76,"dd-mm"),"")&". ","")&IF(W76="SÍ","Stock parece sano pero "&TEXT(L76,"#,##0")&" kg no pasan filtro "&Stock_Seguridad!O76&": sin ellos queda bajo el SS para esa cadena. ","")&IF(E76="SOBRE MAX VENDIBLE","Sobrestock vs vida útil: frenar producción/activar venta. ","")&IF(N(N76)>=Parametros!$B$17,TEXT(N76,"#,##0")&" kg ya no los acepta ninguna cadena: venta intermedia/liquidación. ","")&IF(N(M76)>=Parametros!$B$17,TEXT(M76,"#,##0")&" kg a punto de salir del filtro: despachar primero (FEFO). ","")&IF(Y76="SÍ","Pedidos "&IF(N(U76)>0,"sobre","bajo")&" FCST "&TEXT(ABS(N(U76)),"0%")&": revisar forecast con KAM.","") -> Pedidos sobre FCST 72%: revisar forecast con KAM.
A77: =Stock_Seguridad!A77 -> 30001976 | B77: =Stock_Seguridad!B77 -> BEBIDA LONCOLECHE VEGETAL SOYA 6X1LT | C77: =Stock_Seguridad!C77 -> LECHES LIQUIDAS | D77: =Stock_Seguridad!F77 -> CX | E77: =Stock_Seguridad!X77 -> OK | F77: =Stock_Seguridad!W77 -> 6.4748483 | G77: =Stock_Seguridad!T77 -> 19848 | H77: =Stock_Seguridad!R77 -> 2156.2673 | I77: =Stock_Seguridad!S77 -> 5221.6673 | J77: =Stock_Seguridad!U77 -> 0 | L77: 6 | M77: 0 | N77: 6 | O77: 0.31199577 | P77: =IF(ISNUMBER(Stock_Seguridad!N77),Stock_Seguridad!N77,"") -> 0.49863014 | Q77: =IF(AND(ISNUMBER(O77),ISNUMBER(P77)),P77-O77,"") -> 0.18663437 | R77: =MAX(0,G77-N(L77)) -> 19842 | S77: =SUMIFS(Cadenas_vs_FCST!$D$17:$D$652,Cadenas_vs_FCST!$A$17:$A$652,A77) -> 13212 | T77: =SUMIFS(Cadenas_vs_FCST!$E$17:$E$652,Cadenas_vs_FCST!$A$17:$A$652,A77) -> 11500.678 | U77: =IF(T77>0,S77/T77-1,"") -> 0.14880185 | V77: =IF(OR(E77="BAJO SS",E77="BAJO SS (XLIB CUBRE)"),"SÍ","") | W77: =IF(AND(V77="",N(L77)>=Parametros!$B$17,G77>=H77,R77<H77),"SÍ","") | X77: =IF(OR(E77="SOBRE MAX VENDIBLE",N(N77)>=Parametros!$B$17,N(M77)>=Parametros!$B$17),"SÍ","") | Y77: =IF(AND(ISNUMBER(U77),MAX(S77,T77)>=Parametros!$B$15,ABS(N(U77))>Parametros!$B$14),"SÍ","") | Z77: =COUNTIF(V77:Y77,"SÍ") -> 0 | AA77: =(3*(V77="SÍ")+2*(W77="SÍ")+2*(X77="SÍ")+(Y77="SÍ"))*IF(LEFT(D77,1)="A",3,IF(OR(LEFT(D77,1)="B",D77="SIN HIST"),2,1)) -> 0 | AB77: =IF(AA77>=9,"1-ALTA",IF(AA77>=4,"2-MEDIA",IF(AA77>0,"3-BAJA",""))) | AC77: =IF(E77="BAJO SS","Stock + XLIB bajo el SS: riesgo real de quiebre, adelantar producción. ","")&IF(E77="BAJO SS (XLIB CUBRE)","Disponible bajo el SS; depende de liberar "&TEXT(J77,"#,##0")&" kg"&IF(ISNUMBER(K77)," el "&TEXT(K77,"dd-mm"),"")&". ","")&IF(W77="SÍ","Stock parece sano pero "&TEXT(L77,"#,##0")&" kg no pasan filtro "&Stock_Seguridad!O77&": sin ellos queda bajo el SS para esa cadena. ","")&IF(E77="SOBRE MAX VENDIBLE","Sobrestock vs vida útil: frenar producción/activar venta. ","")&IF(N(N77)>=Parametros!$B$17,TEXT(N77,"#,##0")&" kg ya no los acepta ninguna cadena: venta intermedia/liquidación. ","")&IF(N(M77)>=Parametros!$B$17,TEXT(M77,"#,##0")&" kg a punto de salir del filtro: despachar primero (FEFO). ","")&IF(Y77="SÍ","Pedidos "&IF(N(U77)>0,"sobre","bajo")&" FCST "&TEXT(ABS(N(U77)),"0%")&": revisar forecast con KAM.","")
A78: =Stock_Seguridad!A78 -> 30002229 | B78: =Stock_Seguridad!B78 -> NECTAR WATTS DURAZNO 5X10X115ML | C78: =Stock_Seguridad!C78 -> JUGOS Y NECTARES | D78: =Stock_Seguridad!F78 -> BY | E78: =Stock_Seguridad!X78 -> SOBRE MAX VENDIBLE | F78: =Stock_Seguridad!W78 -> 29.820744 | G78: =Stock_Seguridad!T78 -> 90798.2 | H78: =Stock_Seguridad!R78 -> 6474.6104 | I78: =Stock_Seguridad!S78 -> 9519.4104 | J78: =Stock_Seguridad!U78 -> 0 | L78: 1150 | M78: 1196 | N78: 1150 | O78: 0.06599582 | P78: =IF(ISNUMBER(Stock_Seguridad!N78),Stock_Seguridad!N78,"") -> 0.2739726 | Q78: =IF(AND(ISNUMBER(O78),ISNUMBER(P78)),P78-O78,"") -> 0.20797678 | R78: =MAX(0,G78-N(L78)) -> 89648.2 | S78: =SUMIFS(Cadenas_vs_FCST!$D$17:$D$652,Cadenas_vs_FCST!$A$17:$A$652,A78) -> 35765 | T78: =SUMIFS(Cadenas_vs_FCST!$E$17:$E$652,Cadenas_vs_FCST!$A$17:$A$652,A78) -> 23418.833 | U78: =IF(T78>0,S78/T78-1,"") -> 0.52718966 | V78: =IF(OR(E78="BAJO SS",E78="BAJO SS (XLIB CUBRE)"),"SÍ","") | W78: =IF(AND(V78="",N(L78)>=Parametros!$B$17,G78>=H78,R78<H78),"SÍ","") | X78: =IF(OR(E78="SOBRE MAX VENDIBLE",N(N78)>=Parametros!$B$17,N(M78)>=Parametros!$B$17),"SÍ","") -> SÍ | Y78: =IF(AND(ISNUMBER(U78),MAX(S78,T78)>=Parametros!$B$15,ABS(N(U78))>Parametros!$B$14),"SÍ","") -> SÍ | Z78: =COUNTIF(V78:Y78,"SÍ") -> 2 | AA78: =(3*(V78="SÍ")+2*(W78="SÍ")+2*(X78="SÍ")+(Y78="SÍ"))*IF(LEFT(D78,1)="A",3,IF(OR(LEFT(D78,1)="B",D78="SIN HIST"),2,1)) -> 6 | AB78: =IF(AA78>=9,"1-ALTA",IF(AA78>=4,"2-MEDIA",IF(AA78>0,"3-BAJA",""))) -> 2-MEDIA | AC78: =IF(E78="BAJO SS","Stock + XLIB bajo el SS: riesgo real de quiebre, adelantar producción. ","")&IF(E78="BAJO SS (XLIB CUBRE)","Disponible bajo el SS; depende de liberar "&TEXT(J78,"#,##0")&" kg"&IF(ISNUMBER(K78)," el "&TEXT(K78,"dd-mm"),"")&". ","")&IF(W78="SÍ","Stock parece sano pero "&TEXT(L78,"#,##0")&" kg no pasan filtro "&Stock_Seguridad!O78&": sin ellos queda bajo el SS para esa cadena. ","")&IF(E78="SOBRE MAX VENDIBLE","Sobrestock vs vida útil: frenar producción/activar venta. ","")&IF(N(N78)>=Parametros!$B$17,TEXT(N78,"#,##0")&" kg ya no los acepta ninguna cadena: venta intermedia/liquidación. ","")&IF(N(M78)>=Parametros!$B$17,TEXT(M78,"#,##0")&" kg a punto de salir del filtro: despachar primero (FEFO). ","")&IF(Y78="SÍ","Pedidos "&IF(N(U78)>0,"sobre","bajo")&" FCST "&TEXT(ABS(N(U78)),"0%")&": revisar forecast con KAM.","") -> Sobrestock vs vida útil: frenar producción/activar venta. 1,150 kg ya no los acepta ninguna cadena: venta intermedia/liquidación. 1,196 kg a punto de salir del filtro: despachar primero (FEFO). Pedidos sobre FCST 53%: revisar forecast con KAM.
A79: =Stock_Seguridad!A79 -> 30000248 | B79: =Stock_Seguridad!B79 -> NECTAR WATTS PIÑA 12X1LT | C79: =Stock_Seguridad!C79 -> JUGOS Y NECTARES | D79: =Stock_Seguridad!F79 -> CX | E79: =Stock_Seguridad!X79 -> OK | F79: =Stock_Seguridad!W79 -> 6.0551378 | G79: =Stock_Seguridad!T79 -> 18120 | H79: =Stock_Seguridad!R79 -> 1053.2232 | I79: =Stock_Seguridad!S79 -> 4045.7232 | J79: =Stock_Seguridad!U79 -> 0 | L79: 0 | M79: 1308 | N79: 0 | O79: 0.028685259 | P79: =IF(ISNUMBER(Stock_Seguridad!N79),Stock_Seguridad!N79,"") -> 0.19452055 | Q79: =IF(AND(ISNUMBER(O79),ISNUMBER(P79)),P79-O79,"") -> 0.16583529 | R79: =MAX(0,G79-N(L79)) -> 18120 | S79: =SUMIFS(Cadenas_vs_FCST!$D$17:$D$652,Cadenas_vs_FCST!$A$17:$A$652,A79) -> 12024 | T79: =SUMIFS(Cadenas_vs_FCST!$E$17:$E$652,Cadenas_vs_FCST!$A$17:$A$652,A79) -> 13236.563 | U79: =IF(T79>0,S79/T79-1,"") -> -0.091607099 | V79: =IF(OR(E79="BAJO SS",E79="BAJO SS (XLIB CUBRE)"),"SÍ","") | W79: =IF(AND(V79="",N(L79)>=Parametros!$B$17,G79>=H79,R79<H79),"SÍ","") | X79: =IF(OR(E79="SOBRE MAX VENDIBLE",N(N79)>=Parametros!$B$17,N(M79)>=Parametros!$B$17),"SÍ","") -> SÍ | Y79: =IF(AND(ISNUMBER(U79),MAX(S79,T79)>=Parametros!$B$15,ABS(N(U79))>Parametros!$B$14),"SÍ","") | Z79: =COUNTIF(V79:Y79,"SÍ") -> 1 | AA79: =(3*(V79="SÍ")+2*(W79="SÍ")+2*(X79="SÍ")+(Y79="SÍ"))*IF(LEFT(D79,1)="A",3,IF(OR(LEFT(D79,1)="B",D79="SIN HIST"),2,1)) -> 2 | AB79: =IF(AA79>=9,"1-ALTA",IF(AA79>=4,"2-MEDIA",IF(AA79>0,"3-BAJA",""))) -> 3-BAJA | AC79: =IF(E79="BAJO SS","Stock + XLIB bajo el SS: riesgo real de quiebre, adelantar producción. ","")&IF(E79="BAJO SS (XLIB CUBRE)","Disponible bajo el SS; depende de liberar "&TEXT(J79,"#,##0")&" kg"&IF(ISNUMBER(K79)," el "&TEXT(K79,"dd-mm"),"")&". ","")&IF(W79="SÍ","Stock parece sano pero "&TEXT(L79,"#,##0")&" kg no pasan filtro "&Stock_Seguridad!O79&": sin ellos queda bajo el SS para esa cadena. ","")&IF(E79="SOBRE MAX VENDIBLE","Sobrestock vs vida útil: frenar producción/activar venta. ","")&IF(N(N79)>=Parametros!$B$17,TEXT(N79,"#,##0")&" kg ya no los acepta ninguna cadena: venta intermedia/liquidación. ","")&IF(N(M79)>=Parametros!$B$17,TEXT(M79,"#,##0")&" kg a punto de salir del filtro: despachar primero (FEFO). ","")&IF(Y79="SÍ","Pedidos "&IF(N(U79)>0,"sobre","bajo")&" FCST "&TEXT(ABS(N(U79)),"0%")&": revisar forecast con KAM.","") -> 1,308 kg a punto de salir del filtro: despachar primero (FEFO).
A80: =Stock_Seguridad!A80 -> 30000421 | B80: =Stock_Seguridad!B80 -> LECHE S/LACTOSA VAINILLA 12X1LT | C80: =Stock_Seguridad!C80 -> LECHES LIQUIDAS | D80: =Stock_Seguridad!F80 -> CX | E80: =Stock_Seguridad!X80 -> OK | F80: =Stock_Seguridad!W80 -> 3.5872509 | G80: =Stock_Seguridad!T80 -> 10332 | H80: =Stock_Seguridad!R80 -> 658.85796 | I80: =Stock_Seguridad!S80 -> 3539.058 | J80: =Stock_Seguridad!U80 -> 0 | L80: 168 | M80: 756 | N80: 24 | O80: 0.14994179 | P80: =IF(ISNUMBER(Stock_Seguridad!N80),Stock_Seguridad!N80,"") -> 0.25925926 | Q80: =IF(AND(ISNUMBER(O80),ISNUMBER(P80)),P80-O80,"") -> 0.10931747 | R80: =MAX(0,G80-N(L80)) -> 10164 | S80: =SUMIFS(Cadenas_vs_FCST!$D$17:$D$652,Cadenas_vs_FCST!$A$17:$A$652,A80) -> 10764 | T80: =SUMIFS(Cadenas_vs_FCST!$E$17:$E$652,Cadenas_vs_FCST!$A$17:$A$652,A80) -> 9983.0989 | U80: =IF(T80>0,S80/T80-1,"") -> 0.078222316 | V80: =IF(OR(E80="BAJO SS",E80="BAJO SS (XLIB CUBRE)"),"SÍ","") | W80: =IF(AND(V80="",N(L80)>=Parametros!$B$17,G80>=H80,R80<H80),"SÍ","") | X80: =IF(OR(E80="SOBRE MAX VENDIBLE",N(N80)>=Parametros!$B$17,N(M80)>=Parametros!$B$17),"SÍ","") -> SÍ | Y80: =IF(AND(ISNUMBER(U80),MAX(S80,T80)>=Parametros!$B$15,ABS(N(U80))>Parametros!$B$14),"SÍ","") | Z80: =COUNTIF(V80:Y80,"SÍ") -> 1 | AA80: =(3*(V80="SÍ")+2*(W80="SÍ")+2*(X80="SÍ")+(Y80="SÍ"))*IF(LEFT(D80,1)="A",3,IF(OR(LEFT(D80,1)="B",D80="SIN HIST"),2,1)) -> 2 | AB80: =IF(AA80>=9,"1-ALTA",IF(AA80>=4,"2-MEDIA",IF(AA80>0,"3-BAJA",""))) -> 3-BAJA | AC80: =IF(E80="BAJO SS","Stock + XLIB bajo el SS: riesgo real de quiebre, adelantar producción. ","")&IF(E80="BAJO SS (XLIB CUBRE)","Disponible bajo el SS; depende de liberar "&TEXT(J80,"#,##0")&" kg"&IF(ISNUMBER(K80)," el "&TEXT(K80,"dd-mm"),"")&". ","")&IF(W80="SÍ","Stock parece sano pero "&TEXT(L80,"#,##0")&" kg no pasan filtro "&Stock_Seguridad!O80&": sin ellos queda bajo el SS para esa cadena. ","")&IF(E80="SOBRE MAX VENDIBLE","Sobrestock vs vida útil: frenar producción/activar venta. ","")&IF(N(N80)>=Parametros!$B$17,TEXT(N80,"#,##0")&" kg ya no los acepta ninguna cadena: venta intermedia/liquidación. ","")&IF(N(M80)>=Parametros!$B$17,TEXT(M80,"#,##0")&" kg a punto de salir del filtro: despachar primero (FEFO). ","")&IF(Y80="SÍ","Pedidos "&IF(N(U80)>0,"sobre","bajo")&" FCST "&TEXT(ABS(N(U80)),"0%")&": revisar forecast con KAM.","") -> 756 kg a punto de salir del filtro: despachar primero (FEFO).
A81: =Stock_Seguridad!A81 -> 30002359 | B81: =Stock_Seguridad!B81 -> LECHE BON MOMENT DAN CAPPUCCINO 30X200ML | C81: =Stock_Seguridad!C81 -> LECHES LIQUIDAS | D81: =Stock_Seguridad!F81 -> BX | E81: =Stock_Seguridad!X81 -> BAJO SS | F81: =Stock_Seguridad!W81 -> 0.31563018 | G81: =Stock_Seguridad!T81 -> 876 | H81: =Stock_Seguridad!R81 -> 2571.671 | I81: =Stock_Seguridad!S81 -> 5347.071 | J81: =Stock_Seguridad!U81 -> 0 | L81: 0 | M81: 0 | N81: 0 | O81: 0.27123288 | P81: =IF(ISNUMBER(Stock_Seguridad!N81),Stock_Seguridad!N81,"") | Q81: =IF(AND(ISNUMBER(O81),ISNUMBER(P81)),P81-O81,"") | R81: =MAX(0,G81-N(L81)) -> 876 | S81: =SUMIFS(Cadenas_vs_FCST!$D$17:$D$652,Cadenas_vs_FCST!$A$17:$A$652,A81) -> 16392 | T81: =SUMIFS(Cadenas_vs_FCST!$E$17:$E$652,Cadenas_vs_FCST!$A$17:$A$652,A81) -> 12626.131 | U81: =IF(T81>0,S81/T81-1,"") -> 0.29825997 | V81: =IF(OR(E81="BAJO SS",E81="BAJO SS (XLIB CUBRE)"),"SÍ","") -> SÍ | W81: =IF(AND(V81="",N(L81)>=Parametros!$B$17,G81>=H81,R81<H81),"SÍ","") | X81: =IF(OR(E81="SOBRE MAX VENDIBLE",N(N81)>=Parametros!$B$17,N(M81)>=Parametros!$B$17),"SÍ","") | Y81: =IF(AND(ISNUMBER(U81),MAX(S81,T81)>=Parametros!$B$15,ABS(N(U81))>Parametros!$B$14),"SÍ","") -> SÍ | Z81: =COUNTIF(V81:Y81,"SÍ") -> 2 | AA81: =(3*(V81="SÍ")+2*(W81="SÍ")+2*(X81="SÍ")+(Y81="SÍ"))*IF(LEFT(D81,1)="A",3,IF(OR(LEFT(D81,1)="B",D81="SIN HIST"),2,1)) -> 8 | AB81: =IF(AA81>=9,"1-ALTA",IF(AA81>=4,"2-MEDIA",IF(AA81>0,"3-BAJA",""))) -> 2-MEDIA | AC81: =IF(E81="BAJO SS","Stock + XLIB bajo el SS: riesgo real de quiebre, adelantar producción. ","")&IF(E81="BAJO SS (XLIB CUBRE)","Disponible bajo el SS; depende de liberar "&TEXT(J81,"#,##0")&" kg"&IF(ISNUMBER(K81)," el "&TEXT(K81,"dd-mm"),"")&". ","")&IF(W81="SÍ","Stock parece sano pero "&TEXT(L81,"#,##0")&" kg no pasan filtro "&Stock_Seguridad!O81&": sin ellos queda bajo el SS para esa cadena. ","")&IF(E81="SOBRE MAX VENDIBLE","Sobrestock vs vida útil: frenar producción/activar venta. ","")&IF(N(N81)>=Parametros!$B$17,TEXT(N81,"#,##0")&" kg ya no los acepta ninguna cadena: venta intermedia/liquidación. ","")&IF(N(M81)>=Parametros!$B$17,TEXT(M81,"#,##0")&" kg a punto de salir del filtro: despachar primero (FEFO). ","")&IF(Y81="SÍ","Pedidos "&IF(N(U81)>0,"sobre","bajo")&" FCST "&TEXT(ABS(N(U81)),"0%")&": revisar forecast con KAM.","") -> Stock + XLIB bajo el SS: riesgo real de quiebre, adelantar producción. Pedidos sobre FCST 30%: revisar forecast con KAM.
A82: =Stock_Seguridad!A82 -> 30000327 | B82: =Stock_Seguridad!B82 -> LECHE LONCO S/LACTOSA FRUTILLA 12X1LT | C82: =Stock_Seguridad!C82 -> LECHES LIQUIDAS | D82: =Stock_Seguridad!F82 -> CY | E82: =Stock_Seguridad!X82 -> OK | F82: =Stock_Seguridad!W82 -> 6.1978625 | G82: =Stock_Seguridad!T82 -> 14904 | H82: =Stock_Seguridad!R82 -> 3965.4944 | I82: =Stock_Seguridad!S82 -> 6370.1944 | J82: =Stock_Seguridad!U82 -> 0 | L82: 48 | M82: 0 | N82: 0 | O82: 0.088748991 | P82: =IF(ISNUMBER(Stock_Seguridad!N82),Stock_Seguridad!N82,"") -> 0.33333333 | Q82: =IF(AND(ISNUMBER(O82),ISNUMBER(P82)),P82-O82,"") -> 0.24458434 | R82: =MAX(0,G82-N(L82)) -> 14856 | S82: =SUMIFS(Cadenas_vs_FCST!$D$17:$D$652,Cadenas_vs_FCST!$A$17:$A$652,A82) -> 14280 | T82: =SUMIFS(Cadenas_vs_FCST!$E$17:$E$652,Cadenas_vs_FCST!$A$17:$A$652,A82) -> 9614.4169 | U82: =IF(T82>0,S82/T82-1,"") -> 0.48526949 | V82: =IF(OR(E82="BAJO SS",E82="BAJO SS (XLIB CUBRE)"),"SÍ","") | W82: =IF(AND(V82="",N(L82)>=Parametros!$B$17,G82>=H82,R82<H82),"SÍ","") | X82: =IF(OR(E82="SOBRE MAX VENDIBLE",N(N82)>=Parametros!$B$17,N(M82)>=Parametros!$B$17),"SÍ","") | Y82: =IF(AND(ISNUMBER(U82),MAX(S82,T82)>=Parametros!$B$15,ABS(N(U82))>Parametros!$B$14),"SÍ","") -> SÍ | Z82: =COUNTIF(V82:Y82,"SÍ") -> 1 | AA82: =(3*(V82="SÍ")+2*(W82="SÍ")+2*(X82="SÍ")+(Y82="SÍ"))*IF(LEFT(D82,1)="A",3,IF(OR(LEFT(D82,1)="B",D82="SIN HIST"),2,1)) -> 1 | AB82: =IF(AA82>=9,"1-ALTA",IF(AA82>=4,"2-MEDIA",IF(AA82>0,"3-BAJA",""))) -> 3-BAJA | AC82: =IF(E82="BAJO SS","Stock + XLIB bajo el SS: riesgo real de quiebre, adelantar producción. ","")&IF(E82="BAJO SS (XLIB CUBRE)","Disponible bajo el SS; depende de liberar "&TEXT(J82,"#,##0")&" kg"&IF(ISNUMBER(K82)," el "&TEXT(K82,"dd-mm"),"")&". ","")&IF(W82="SÍ","Stock parece sano pero "&TEXT(L82,"#,##0")&" kg no pasan filtro "&Stock_Seguridad!O82&": sin ellos queda bajo el SS para esa cadena. ","")&IF(E82="SOBRE MAX VENDIBLE","Sobrestock vs vida útil: frenar producción/activar venta. ","")&IF(N(N82)>=Parametros!$B$17,TEXT(N82,"#,##0")&" kg ya no los acepta ninguna cadena: venta intermedia/liquidación. ","")&IF(N(M82)>=Parametros!$B$17,TEXT(M82,"#,##0")&" kg a punto de salir del filtro: despachar primero (FEFO). ","")&IF(Y82="SÍ","Pedidos "&IF(N(U82)>0,"sobre","bajo")&" FCST "&TEXT(ABS(N(U82)),"0%")&": revisar forecast con KAM.","") -> Pedidos sobre FCST 49%: revisar forecast con KAM.
A83: =Stock_Seguridad!A83 -> 30002178 | B83: =Stock_Seguridad!B83 -> SHAKE SHAKE CHOCOLATE 30X190ML | C83: =Stock_Seguridad!C83 -> LECHES LIQUIDAS | D83: =Stock_Seguridad!F83 -> CX | E83: =Stock_Seguridad!X83 -> OK | F83: =Stock_Seguridad!W83 -> 3.9977769 | G83: =Stock_Seguridad!T83 -> 9171.3 | H83: =Stock_Seguridad!R83 -> 831.27482 | I83: =Stock_Seguridad!S83 -> 3125.3748 | J83: =Stock_Seguridad!U83 -> 0 | L83: 96.9 | M83: 0 | N83: 0 | O83: 0.082137974 | P83: =IF(ISNUMBER(Stock_Seguridad!N83),Stock_Seguridad!N83,"") -> 0.19 | Q83: =IF(AND(ISNUMBER(O83),ISNUMBER(P83)),P83-O83,"") -> 0.10786203 | R83: =MAX(0,G83-N(L83)) -> 9074.4 | S83: =SUMIFS(Cadenas_vs_FCST!$D$17:$D$652,Cadenas_vs_FCST!$A$17:$A$652,A83) -> 6988.2 | T83: =SUMIFS(Cadenas_vs_FCST!$E$17:$E$652,Cadenas_vs_FCST!$A$17:$A$652,A83) -> 7099.2485 | U83: =IF(T83>0,S83/T83-1,"") -> -0.015642292 | V83: =IF(OR(E83="BAJO SS",E83="BAJO SS (XLIB CUBRE)"),"SÍ","") | W83: =IF(AND(V83="",N(L83)>=Parametros!$B$17,G83>=H83,R83<H83),"SÍ","") | X83: =IF(OR(E83="SOBRE MAX VENDIBLE",N(N83)>=Parametros!$B$17,N(M83)>=Parametros!$B$17),"SÍ","") | Y83: =IF(AND(ISNUMBER(U83),MAX(S83,T83)>=Parametros!$B$15,ABS(N(U83))>Parametros!$B$14),"SÍ","") | Z83: =COUNTIF(V83:Y83,"SÍ") -> 0 | AA83: =(3*(V83="SÍ")+2*(W83="SÍ")+2*(X83="SÍ")+(Y83="SÍ"))*IF(LEFT(D83,1)="A",3,IF(OR(LEFT(D83,1)="B",D83="SIN HIST"),2,1)) -> 0 | AB83: =IF(AA83>=9,"1-ALTA",IF(AA83>=4,"2-MEDIA",IF(AA83>0,"3-BAJA",""))) | AC83: =IF(E83="BAJO SS","Stock + XLIB bajo el SS: riesgo real de quiebre, adelantar producción. ","")&IF(E83="BAJO SS (XLIB CUBRE)","Disponible bajo el SS; depende de liberar "&TEXT(J83,"#,##0")&" kg"&IF(ISNUMBER(K83)," el "&TEXT(K83,"dd-mm"),"")&". ","")&IF(W83="SÍ","Stock parece sano pero "&TEXT(L83,"#,##0")&" kg no pasan filtro "&Stock_Seguridad!O83&": sin ellos queda bajo el SS para esa cadena. ","")&IF(E83="SOBRE MAX VENDIBLE","Sobrestock vs vida útil: frenar producción/activar venta. ","")&IF(N(N83)>=Parametros!$B$17,TEXT(N83,"#,##0")&" kg ya no los acepta ninguna cadena: venta intermedia/liquidación. ","")&IF(N(M83)>=Parametros!$B$17,TEXT(M83,"#,##0")&" kg a punto de salir del filtro: despachar primero (FEFO). ","")&IF(Y83="SÍ","Pedidos "&IF(N(U83)>0,"sobre","bajo")&" FCST "&TEXT(ABS(N(U83)),"0%")&": revisar forecast con KAM.","")
A84: =Stock_Seguridad!A84 -> 30002358 | B84: =Stock_Seguridad!B84 -> LECHE BON MOMENT DAN MOCACCINO 30X200ML | C84: =Stock_Seguridad!C84 -> LECHES LIQUIDAS | D84: =Stock_Seguridad!F84 -> CX | E84: =Stock_Seguridad!X84 -> OK | F84: =Stock_Seguridad!W84 -> 4.6892965 | G84: =Stock_Seguridad!T84 -> 10278 | H84: =Stock_Seguridad!R84 -> 773.5399 | I84: =Stock_Seguridad!S84 -> 2965.3399 | J84: =Stock_Seguridad!U84 -> 0 | L84: 0 | M84: 0 | N84: 0 | O84: 0.10963806 | P84: =IF(ISNUMBER(Stock_Seguridad!N84),Stock_Seguridad!N84,"") | Q84: =IF(AND(ISNUMBER(O84),ISNUMBER(P84)),P84-O84,"") | R84: =MAX(0,G84-N(L84)) -> 10278 | S84: =SUMIFS(Cadenas_vs_FCST!$D$17:$D$652,Cadenas_vs_FCST!$A$17:$A$652,A84) -> 7752 | T84: =SUMIFS(Cadenas_vs_FCST!$E$17:$E$652,Cadenas_vs_FCST!$A$17:$A$652,A84) -> 8573.8596 | U84: =IF(T84>0,S84/T84-1,"") -> -0.095856438 | V84: =IF(OR(E84="BAJO SS",E84="BAJO SS (XLIB CUBRE)"),"SÍ","") | W84: =IF(AND(V84="",N(L84)>=Parametros!$B$17,G84>=H84,R84<H84),"SÍ","") | X84: =IF(OR(E84="SOBRE MAX VENDIBLE",N(N84)>=Parametros!$B$17,N(M84)>=Parametros!$B$17),"SÍ","") | Y84: =IF(AND(ISNUMBER(U84),MAX(S84,T84)>=Parametros!$B$15,ABS(N(U84))>Parametros!$B$14),"SÍ","") | Z84: =COUNTIF(V84:Y84,"SÍ") -> 0 | AA84: =(3*(V84="SÍ")+2*(W84="SÍ")+2*(X84="SÍ")+(Y84="SÍ"))*IF(LEFT(D84,1)="A",3,IF(OR(LEFT(D84,1)="B",D84="SIN HIST"),2,1)) -> 0 | AB84: =IF(AA84>=9,"1-ALTA",IF(AA84>=4,"2-MEDIA",IF(AA84>0,"3-BAJA",""))) | AC84: =IF(E84="BAJO SS","Stock + XLIB bajo el SS: riesgo real de quiebre, adelantar producción. ","")&IF(E84="BAJO SS (XLIB CUBRE)","Disponible bajo el SS; depende de liberar "&TEXT(J84,"#,##0")&" kg"&IF(ISNUMBER(K84)," el "&TEXT(K84,"dd-mm"),"")&". ","")&IF(W84="SÍ","Stock parece sano pero "&TEXT(L84,"#,##0")&" kg no pasan filtro "&Stock_Seguridad!O84&": sin ellos queda bajo el SS para esa cadena. ","")&IF(E84="SOBRE MAX VENDIBLE","Sobrestock vs vida útil: frenar producción/activar venta. ","")&IF(N(N84)>=Parametros!$B$17,TEXT(N84,"#,##0")&" kg ya no los acepta ninguna cadena: venta intermedia/liquidación. ","")&IF(N(M84)>=Parametros!$B$17,TEXT(M84,"#,##0")&" kg a punto de salir del filtro: despachar primero (FEFO). ","")&IF(Y84="SÍ","Pedidos "&IF(N(U84)>0,"sobre","bajo")&" FCST "&TEXT(ABS(N(U84)),"0%")&": revisar forecast con KAM.","")
